Workbook

Sheet 00_LEIA-ME
A1: WORKBOOK PMBOK 8 · ECOSSISTEMA EXECUTAR
A3: Data de geração | B3: 2026-08-31
A4: Data de corte das fontes | B4: 2026-08-31 — DOCUMENTOS.zip, 214 arquivos
A5: Versão | B5: V1
A6: Base documental | B6: 214 arquivos, 18 classificações MECE (C01–C18), 22 tipos documentais. Integridade verificada por SHA-256: 214/214 casaram com o registro; 202 hashes únicos (12 exemplares duplicados em 9 grupos).
A7: Unidades de análise | B7: ECO-01 App EXECUTAR · ECO-02 Blog Risco Cognitivo · ECO-03 Framework e Metodologia · ECO-04 Produtos Físicos · ECO-05 Infoprodutos · ECO-06 Livro · ECO-07 Consultoria · ECO-08 Ecossistema Creator
A9: REGRA EPISTEMOLÓGICA
A10: Nada foi inventado | B10: Toda afirmação aponta para um documento_id real da base e transcreve a evidência. Ausência de dado virou lacuna descrita, nunca estimativa.
A11: Conflitos preservados | B11: Quando duas fontes divergem, as duas versões ficam registradas com suas fontes. Nenhum conflito foi arbitrado em silêncio.
A12: status (evidência) | B12: fact = evidência explícita · inference = derivação a partir de evidência citada · hypothesis = sem evidência · conflict = fontes incompatíveis · gap = pergunta relevante sem dado
A13: evidence_strength | B13: strong · moderate · weak · none
A15: ABAS
A16: 01_MASTER | B16: Consolidação executiva com contagens calculadas por fórmula sobre as demais abas
A17: 02_AREAS | B17: Os 122 campos do formulário fundido, com status e rastreabilidade
A18: 03_FRAMEWORKS | B18: 279 insights estratégicos: 13 frameworks × 8 unidades
A19: 04_EVIDENCIAS | B19: 680 pares afirmação ↔ documento_id (OUT-54)
A20: 05_HIPOTESES | B20: Hipóteses abertas e o teste que as valida (OUT-55)
A21: 06_RISCOS | B21: Riscos de impacto alto ou em conflito (OUT-57)
A22: 07_DECISOES | B22: Decisões e conflitos não arbitrados (OUT-56)
A23: 08_FONTES | B23: Documentos citados, com sha256 e caminho original (OUT-59)
A24: 09_BACKLOG | B24: Lacunas com a pesquisa necessária para fechar cada uma (OUT-58)
A26: COMO CONTINUAR
A27: Próximo passo | B27: Preencher os dias 3 a 6 do formulário (áreas 11 · 12–17 · 5–7 · 3–4), que somam 77 campos ainda pendentes.
A28: Reprodutibilidade | B28: maestro/scripts/gen_registros_auxiliares.py regenera as abas 04 a 09 a partir dos insights e do formulário. IDs derivam de hash do conteúdo e são estáveis entre execuções.

Sheet 01_MASTER
A1: MASTER · ESTADO DO ECOSSISTEMA
A2: Todas as contagens são fórmulas sobre as demais abas — recalculam ao editar os dados.
A4: COBERTURA DOCUMENTAL
A5: Arquivos na base documental | B5: 214 | C5: C01–C18, 18 classificações MECE, integridade SHA-256 verificada 214/214
A6: Documentos citados como evidência | B6: =COUNTA('08_FONTES'!A2:A87) | C6: Os demais ainda não foram lidos ou são duplicatas/binários
A7: Pares afirmação ↔ documento | B7: =COUNTA('04_EVIDENCIAS'!A2:A681) | C7: Registro de evidência OUT-54
A9: ANÁLISE ESTRATÉGICA — 279 INSIGHTS, 8 UNIDADES
A10: fact | B10: =COUNTIF('03_FRAMEWORKS'!K2:K280,"fact") | C10: Evidência explícita no documento
A11: inference | B11: =COUNTIF('03_FRAMEWORKS'!K2:K280,"inference") | C11: Derivação a partir de evidência citada
A12: conflict | B12: =COUNTIF('03_FRAMEWORKS'!K2:K280,"conflict") | C12: Fontes incompatíveis — preservadas, não arbitradas
A13: hypothesis | B13: =COUNTIF('03_FRAMEWORKS'!K2:K280,"hypothesis") | C13: Sem evidência: precisa de teste
A14: gap | B14: =COUNTIF('03_FRAMEWORKS'!K2:K280,"gap") | C14: Pergunta relevante sem dado na base
A15: Total de insights | B15: =SUM(B10:B14) | C15: Soma dos cinco status acima
A17: FORÇA DA EVIDÊNCIA
A18: strong | B18: =COUNTIF('03_FRAMEWORKS'!I2:I280,"strong") | C18: Fonte primária ou dado interno explícito
A19: moderate | B19: =COUNTIF('03_FRAMEWORKS'!I2:I280,"moderate") | C19: Fonte secundária ou parcial
A20: weak | B20: =COUNTIF('03_FRAMEWORKS'!I2:I280,"weak") | C20: Transcrição de imagem, sem metodologia ou sem data
A21: none | B21: =COUNTIF('03_FRAMEWORKS'!I2:I280,"none") | C21: Sem suporte — vira hipótese ou lacuna
A23: INSIGHTS POR UNIDADE DE ANÁLISE
A24: ECO-01 · App EXECUTAR | B24: =COUNTIF('03_FRAMEWORKS'!C2:C280,"ECO-01")
A25: ECO-02 · Blog Risco Cognitivo | B25: =COUNTIF('03_FRAMEWORKS'!C2:C280,"ECO-02")
A26: ECO-03 · Framework e Metodologia | B26: =COUNTIF('03_FRAMEWORKS'!C2:C280,"ECO-03")
A27: ECO-04 · Produtos Físicos | B27: =COUNTIF('03_FRAMEWORKS'!C2:C280,"ECO-04")
A28: ECO-05 · Infoprodutos | B28: =COUNTIF('03_FRAMEWORKS'!C2:C280,"ECO-05")
A29: ECO-06 · Livro | B29: =COUNTIF('03_FRAMEWORKS'!C2:C280,"ECO-06")
A30: ECO-07 · Consultoria | B30: =COUNTIF('03_FRAMEWORKS'!C2:C280,"ECO-07")
A31: ECO-08 · Ecossistema Creator | B31: =COUNTIF('03_FRAMEWORKS'!C2:C280,"ECO-08")
A33: FORMULÁRIO FUNDACIONAL — 122 CAMPOS
A34: preenchido | B34: =COUNTIF('02_AREAS'!F2:F123,"preenchido") | C34: Resposta sustentada por evidência
A35: parcial | B35: =COUNTIF('02_AREAS'!F2:F123,"parcial") | C35: Resposta existe mas incompleta
A36: lacuna | B36: =COUNTIF('02_AREAS'!F2:F123,"lacuna") | C36: Sem dado na base — lacuna descrita, não TBD
A37: conflito | B37: =COUNTIF('02_AREAS'!F2:F123,"conflito") | C37: Fontes divergentes
A38: pendente | B38: =COUNTIF('02_AREAS'!F2:F123,"pendente") | C38: Ainda não trabalhado (dias 3 a 6)
A39: Total de campos | B39: =SUM(B34:B38)
A40: Completeza dos campos trabalhados | B40: =IFERROR((B34+B35)/(B38-B37),0) | C40: Preenchidos + parciais sobre os campos já trabalhados (exclui os pendentes) — OUT-73
A42: BACKLOG E RISCO
A43: Lacunas registradas | B43: =COUNTA('09_BACKLOG'!A2:A69) | C43: Cada uma com a pesquisa necessária para fechar — OUT-58
A44: Riscos registrados | B44: =COUNTA('06_RISCOS'!A2:A200) | C44: Impacto alto ou em conflito — OUT-57
A45: Decisões e conflitos em aberto | B45: =COUNTA('07_DECISOES'!A2:A31) | C45: Conflitos aparecem como NÃO ARBITRADO — OUT-56
A46: Hipóteses a testar | B46: =COUNTA('05_HIPOTESES'!A2:A7) | C46: Com o teste de validação associado — OUT-55
A48: ALERTAS MATERIAIS
A49: TAM/SAM/SOM sem base defensável | C49: Os números do acervo (TAM R$5,07bi · SAM R$357,3mi · SOM R$3,26mi) vêm de transcrição de imagem, com base amostral declarada como não informada e bibliografia ausente. Há ainda um segundo valor de SAM (R$6,0mi) no mesmo dashboard. Registrados como afirmação da fonte, força weak.
A50: Sem pesquisa primária com clientes | C50: Nenhuma das 8 unidades tem escuta direta de cliente. As necessidades registradas derivam de documento interno.
A51: Timer 45 com concorrente abaixo do custo | C51: Custo de fornecedor citado R$39; concorrente a R$28,46 no AliExpress (R$97,90 Mercado Livre, R$95,70 Amazon).
A52: Economia unitária incompleta | C52: Sem custo de produção e sem CAC para nenhuma linha. Landed cost dos físicos com campos literalmente "preencher". Nenhum fornecedor, MOQ ou lead time no acervo.
A53: Sequência editorial × GTM em conflito | C53: A tese manda instalar a categoria antes do produto; o GTM de 07/09 lança app, curso, e-book, Estúdio e Office Kit no dia um.
A54: Fronteira Livro × Infoprodutos | C54: Livros digitais aninhados sob Infoprodutos na árvore, e o nome "livro" designa dois objetos distintos: os e-books comerciais e o livro autoral.

Sheet 02_AREAS
A1: area_id | B1: area | C1: field_id | D1: titulo | E1: origem | F1: status | G1: valor | H1: tipo_informacao | I1: confianca | J1: eco_unit | K1: documento_ids | L1: evidencia | M1: lacuna | N1: proxima_acao
A2: 1 | B2: NEGÓCIO & GTM | C2: 1.1 | D2: Problema central | E2: formulario_original | F2: preenchido | G2: O problema aparece em três camadas distintas, por unidade. (a) ECO-01 App EXECUTAR — problema operacional: “Paralisia por excesso, dificuldade de iniciação das tarefas, não linearidade de execução, troca de contexto cognitivo, retrabalho por não respeitar cadeia única de valor e dependências, memória de trabalho limitada, ausência de processos padronizados e múltiplas fontes de execução e plataformas”. A decisão PROD-03 refina: a dor central é “dificuldade de transformar intenção em comportamento organizado ao longo do tempo”, evitando o posicionamento genérico de “produtividade”; PROD-06 define o problema observável prioritário como a combinação planejamento + memória + tempo + procrastinação. (b) ECO-03 Framework/CERM — problema conceitual: “A distância entre intenção e execução diante de vulnerabilidades cognitivas e demandas reais”; o documento adverte explicitamente para NÃO usar “não execução” como problema principal, por ser estreito demais. (c) ECO-02 Blog Risco Cognitivo — problema estratégico do lançamento editorial: “Apresentar o EXECUTAR cedo demais pode reduzir a credibilidade da investigação e impedir distinguir interesse genuíno pelo problema de interesse no produto”. | H2: fato_interno | I2: alta | J2: TRANSVERSAL (detalhado por ECO-01, ECO-03 e ECO-02) | K2: DOC-C05-001;DOC-C07-009;DOC-C01-005;DOC-C02-039;DOC-C07-002;DOC-C07-010 | L2: DOC-C05-001 (seção “Corpo”, linha Problema): “Paralisia por excesso, dificuldade de iniciação das tarefas, não linearidade de execução, troca de contexto cognitivo, retrabalho por não respeitar cadeia única de valor e dependências, memória de trabalho limitada, ausência de processos padronizados e múltiplas fontes de execução e plataformas.” Perspectiva do usuário no mesmo documento: “Perco dinheiro e oportunidades por atrasos e desorganização. […] O momento de maior ansiedade e aflição são os primeiros 30 minutos iniciais, pois não sei onde estava ontem, o que devo fazer agora e como sei que terminei.” | DOC-C07-009 (decisão PROD-03): “Definir a dor central como dificuldade de transformar intenção em comportamento organizado ao longo do tempo, evitando o posicionamento genérico de ‘produtividade’.” | DOC-C01-005: “Eu evitaria usar não execução como problema principal. É estreito demais.” e “A distância entre intenção e execução diante de vulnerabilidades cognitivas e demandas reais.” | DOC-C02-039 (BMC, célula Problema): “Apresentar o EXECUTAR cedo demais pode reduzir a credibilidade da investigação e impedir distinguir interesse genuíno pelo problema de interesse no produto.” | N2: Registrar no formulário um enunciado de problema por unidade, em vez de fundir as três camadas num único texto.
A3: 1 | B3: NEGÓCIO & GTM | C3: 1.2 | D3: Público-alvo / ICP | E3: formulario_original | F3: conflito | G3: CONFLITO ENTRE DOCUMENTOS. Versão A (DOC-C05-001, workbook Sas-06, seção Público): “Homens, adultos, neurodivergentes, autônomos, na faixa dos 25–35 anos, recém-diagnosticados, que gerenciam múltiplos processos e projetos ao mesmo tempo. Têm consciência básica de terminologia e funções executivas, já utilizaram e abandonaram outros aplicativos por não manterem o uso e rejeitam alta complexidade de configuração.” Versão B (DOC-C07-009, decisão ICP-01 / achado ICP-HYP-01, 15/08/2026): “Profissional independente/solo brasileiro, aproximadamente 25–44 anos, multiprojeto, que perde contexto, tem dificuldade recorrente para escolher próxima ação, já tentou ferramentas de produtividade e controla/influencia a própria compra”, com ressalva explícita de que diagnóstico de TDAH NÃO é critério de entrada. As duas versões divergem em faixa etária (25–35 × 25–44), gênero (homens × não especificado) e no papel da neurodivergência/diagnóstico como critério de ICP. Unidades com público próprio já declarado: ECO-07 Estúdio — “Profissionais solo, autônomos e pequenos negócios com trabalho, informação, clientes e projetos dispersos”; ECO-02 Blog — “Leitores interessados em funções executivas, neurodivergência, trabalho, projetos e risco; especialistas entram como crítica externa, não como endosso.” | H3: decisao | I3: alta | J3: TRANSVERSAL — conflito em ECO-01; ECO-07 e ECO-02 têm públicos próprios | K3: DOC-C05-001;DOC-C07-009;DOC-C02-039 | L3: DOC-C05-001: “Homens, adultos, neurodivergentes, autônomos, na faixa dos 25–35 anos, recém-diagnosticados…” | DOC-C07-009 (ICP-01, status DECIDED_FOR_TEST, confiança MÉDIA-ALTA): “Iniciar testes por profissionais independentes multiprojeto, sem exigir diagnóstico de TDAH”; e “O que não é critério de entrada: Diagnóstico de TDAH. Diagnóstico/autodeclaração deve ser variável opcional posterior, especialmente porque dados de saúde são sensíveis e não são necessários para o core funcional.” | DOC-C05-001 (SSOT Executar Studio, item 02 Público): “Profissionais solo, autônomos e pequenos negócios com trabalho, informação, clientes e projetos dispersos.” | DOC-C02-039 (BMC, Público/validação): “Leitores interessados em funções executivas, neurodivergência, trabalho, projetos e risco.” | M3: Não há registro de qual definição prevalece nem data de supersessão. DOC-C07-009 é de 15/08/2026 e classifica o ICP como hipótese de classe E a validar; DOC-C05-001 não traz data própria de decisão. Faltaria um ADR comercial ou nota de decisão datada. | N3: Decidir explicitamente qual ICP vale para o lançamento de 07/09 e arquivar a versão superada com data e justificativa.
A4: 1 | B4: NEGÓCIO & GTM | C4: 1.3 | D4: Proposta de valor | E4: formulario_original | F4: preenchido | G4: Proposta de valor por unidade. ECO-01 App: “Criar uma situação em que a execução do que foi planejado aconteça com o mínimo possível de carga administrativa e cognitiva sobre o usuário. O sistema assume parte da estrutura, organização e priorização”; promessa: “Zero configuração, mínimo de personalização, uso mínimo do app — cerca de 1–2 vezes por semana — e externalização cognitiva”; mensagem de sustentação: “Você executa. O sistema sustenta a execução.”; headline canônica: “O app de produtividade feito para você não usar.” Posicionamento resultante (DOC-C07-009): “Sistema de execução para profissionais multiprojeto que transforma contexto em próxima ação e preserva o estado do trabalho — neurocompatível por design, mas não apresentado como tratamento de TDAH.” ECO-07 Estúdio: “Traga o problema. Em 7 dias, saia com um sistema funcionando”; “Menos tempo organizando a operação. Mais clareza sobre o que fazer, onde encontrar e como repetir.” ECO-02/ECO-03: “Transformar Risco Cognitivo em uma categoria editorial e investigável antes de conectá-la ao produto.” ECO-05 Infoprodutos: “Livros digitais funcionam como produto de entrada e aplicação. Curso funciona como aplicação guiada.” ECO-04 Físicos: “Neurobook = planejar e registrar → Timer = executar → Organização = reduzir decisões cotidianas → Office Kit = sistema integrado.” | H4: fato_interno | I4: alta | J4: TRANSVERSAL — respostas distintas em ECO-01, ECO-07, ECO-02/03, ECO-05 e ECO-04 | K4: DOC-C05-001;DOC-C07-009;DOC-C09-004;DOC-C09-006;DOC-C09-016;DOC-C09-008;DOC-C02-039 | L4: DOC-C05-001 (Benefício e Promessa principal; Mensagem final): “O usuário executa. O sistema sustenta a execução.”; Headline 01: “O app de produtividade feito para você não usar.”; Descrição 01: “Executar é um sistema de gestão de projetos orientado à execução que reduz configuração, organização manual e decisões repetitivas para mostrar o que pode ser feito agora.” | DOC-C07-009 (campo positioning): “Sistema de execução para profissionais multiprojeto que transforma contexto em próxima ação e preserva o estado do trabalho.” | DOC-C09-004: “O aplicativo de produtividade feito para você usar menos. O sistema sustenta a estrutura; o usuário executa.” | DOC-C09-006: “Traga o problema. Em 7 dias, saia com um sistema funcionando.” | DOC-C02-039 (BMC, Proposta de valor): “Transformar Risco Cognitivo em uma categoria editorial e investigável antes de conectá-la ao produto.”
A5: 1 | B5: NEGÓCIO & GTM | C5: 1.4 | D5: Canais de aquisição | E5: formulario_original | F5: preenchido | G5: Arquitetura de canais em dois níveis (DOC-C05-001). OWNED: 01 executar.com/Blog (fonte canônica do conteúdo); 02 Biblioteca Executar (indexação permanente, guias, referências, e-books); 03 e-mail/newsletter; 04 comunidade futura. DISTRIBUIÇÃO (plataformas alugadas/terceiras): YouTube (explicação + demonstração + descoberta), Instagram (carrossel, visual, Reels), TikTok (descoberta, vídeos curtos), LinkedIn (gestão, operações, risco, conteúdo técnico). Regra de produção “uma fonte, vários outputs”: questão editorial → pesquisa → artigo canônico → diagrama/infográfico → vídeo principal → 2–4 shorts → carrossel → post LinkedIn → newsletter → entrada na Biblioteca → trecho no e-book/curso → CTA de aprofundamento. Canais comerciais: Hotmart (infoprodutos, com cadastro e checkout), afiliados (Barkley ×2 e Ana Beatriz Barbosa Silva), loja própria, formulário visual do Estúdio. Aquisição do ECO-07: “Conteúdo → Showroom → Formulário visual → Encontro → Projeto”. Operacionalmente, os canais estão registrados como 10 chamadas CH-001…CH-010 com destino e estado (DOC-C08-004) e 10 rotas RT-001…RT-010 (DOC-C08-006). Para ECO-02, o canal inaugural é o pacote de 18 ativos em 14 dias: 1 artigo, 1 newsletter, 1 vídeo principal, 3 vídeos curtos, 2 carrosséis, 6 posts curtos, 1 infográfico, 1 checklist, 1 lead magnet e 1 landing page. | H5: decisao | I5: alta | J5: TRANSVERSAL | K5: DOC-C05-001;DOC-C08-004;DOC-C08-006;DOC-C06-001;DOC-C02-043;DOC-C09-015;DOC-C09-018;DOC-C12-004 | L5: DOC-C05-001 (Arquitetura das plataformas): “OWNED 01 executar.com / Blog — Fonte canônica do conteúdo; OWNED 02 Biblioteca Executar; OWNED 03 E-mail / newsletter; DISTRIBUIÇÃO 01 YouTube; 02 Instagram; 03 TikTok; 04 LinkedIn”; e “Instagram, YouTube, TikTok e LinkedIn não são plataformas proprietárias; são plataformas alugadas/terceiras.” | DOC-C05-001 (SSOT Studio, item 13 Aquisição): “Conteúdo → Showroom → Formulário visual → Encontro → Projeto.” | DOC-C08-004: “CH-001 Experimentar Executar → página do aplicativo”, “CH-003 Explorar a biblioteca”, “CH-007 Ver o livro → ligação de afiliado”, “CH-010 Entrar na lista → formulário”. | DOC-C02-043: “Pacote: 1 artigo, 1 newsletter, 1 vídeo principal, 3 vídeos curtos, 2 carrosséis, 6 posts curtos, 1 infográfico, 1 checklist, 1 lead magnet e 1 landing page — 18 ativos principais.” | DOC-C09-018: “Núcleo inicial — Russell A. Barkley · Vencendo o TDAH Adulto; Russell A. Barkley · Executive Functions; Ana Beatriz Barbosa Silva · Mentes Inquietas.” | M5: Nenhum documento define mídia paga, verba por canal ou meta de tráfego. A aquisição paga só aparece implicitamente, como pressuposto do guardrail de CAC em DOC-C07-009. | N5: Decidir se haverá mídia paga no lançamento de 07/09 e, em caso afirmativo, registrar acquisition_source e campaign_id por canal — eventos já especificados na telemetria de DOC-C07-009.
A6: 1 | B6: NEGÓCIO & GTM | C6: 1.5 | D6: Métrica North Star | E6: formulario_original | F6: parcial | G6: Nenhum documento nomeia uma “métrica North Star”. O candidato canônico mais próximo é o VALUE_EVENT-01 da telemetria do EXECUTAR: “Projeto real → contexto interpretado → próxima ação válida → ação executada → conclusão/evidência registrada” — o evento que define valor entregue e que governa ativação, PMF e coortes W1/W2/W4/W8. Os endpoints de eficácia funcional associados são time_to_next_action, resume_latency, completion_rate, context_reconstruction, execution_cycles_per_week e abandonment_rate. Para ECO-02, a meta declarada é de output, não de outcome: “publicar 18 ativos em 14 dias, com artigo dentro de 1.200–1.800 palavras”, capturando baseline de visualizações, retenção, salvamentos, inscrições e downloads — com a regra explícita de “não estabelecer ainda metas arbitrárias de seguidores ou leads sem baseline”. O BMC do ECO-02 registra literalmente “% geral não informado” e “métricas não informadas permanecem desconhecidas”. | H6: inferencia | I6: media | J6: ECO-01 (candidato VALUE_EVENT-01) e ECO-02 (meta de output) | K6: DOC-C07-009;DOC-C02-043;DOC-C02-039;DOC-C16-003;DOC-C16-006 | L6: DOC-C07-009 (objeto telemetry): “value_event_01: Projeto real → contexto interpretado → próxima ação válida → ação executada → conclusão/evidência registrada”; “functional_efficacy_endpoints: time_to_next_action, resume_latency, completion_rate, context_reconstruction, execution_cycles_per_week, abandonment_rate.” | DOC-C02-043 (Objetivo SMART da primeira fase): “Mensurável: publicar 18 ativos em 14 dias, com artigo dentro de 1.200–1.800 palavras”; “Não estabelecer ainda metas arbitrárias de seguidores ou leads sem baseline.” | DOC-C02-039 (rodapé do BMC): “métricas não informadas permanecem desconhecidas”. | DOC-C16-003 (MED-001) lista apenas o que verificar (chamada→destino, formulário→recebimento, download→arquivo), sem métrica-alvo. | M6: Falta a eleição formal de UMA métrica North Star com definição, fórmula, janela de medição e meta. O artefato estaria num documento de métricas/analytics ou num ADR de produto — inexistente no corpus. | N6: Eleger “VALUE_EVENT-01 concluídos por usuário ativo por semana” como NSM candidata e fixar baseline após o piloto de ≥40 usuários previsto em PMF-01.
A7: 1 | B7: NEGÓCIO & GTM | C7: 1.6 | D7: Métricas guardrail | E7: formulario_original | F7: preenchido | G7: Guardrails existentes, por domínio. (a) Econômico — CAC-01: TARGET-CAC provisório ≤ R$70 e alerta/limite de aproximadamente R$95 até existir CAC observado. (b) Regulatório e de comunicação — CLAIM-01, PROD-14 e PROD-15: claims proibidos hoje são “Reduz sintomas de TDAH”, “Melhora função executiva clinicamente”, “Trata TDAH”, “Diagnostica ou identifica TDAH”, “Substitui terapia, tratamento ou medicação” e “Cientificamente comprovado para TDAH”; e é bloqueado qualquer uso do produto como diagnóstico, substituição profissional ou inferência clínica. (c) Gate de PMF — PMF-01: só declarar PMF com convergência de VALUE_EVENT-01, coortes W1/W2/W4/W8, pagamento/renovação e pesquisa de dependência, com heurística n ≥ 40 qualificados e > 40% “muito desapontados”. (d) Operacional de lançamento: “Broken links = 0”, “backlog crítico = 0”, “não existe entrega crítica aguardando produção”. (e) Epistemológico — invariantes: “original ≠ extração ≠ evidência ≠ decisão · candidate ≠ verified · benchmark ≠ dado do EXECUTAR · modelo econômico ≠ unit economics observado · literatura externa ≠ eficácia do EXECUTAR · similaridade ≠ suporte factual”. | H7: decisao | I7: alta | J7: TRANSVERSAL — econômico e de claims em ECO-01; operacional no GTM 07/09 | K7: DOC-C07-009;DOC-C06-001;DOC-C08-007 | L7: DOC-C07-009 (CAC-01): “Usar TARGET-CAC provisório ≤ R$70 e alerta/limite de aproximadamente R$95 até existir CAC observado.” | DOC-C07-009 (claims_policy.prohibited_now): lista literal dos seis claims proibidos. | DOC-C07-009 (Invariantes): “modelo econômico ≠ unit economics observado”. | DOC-C06-001 (D11, DoD do dia): “Broken links = 0; fluxo de conversão testado”; D12: “Tudo agendado; backlog crítico = 0; GTM READY.” | DOC-C08-007: “não existe entrega crítica aguardando produção.” | M7: Não há guardrail técnico de produto nesta área (taxa de erro, latência, custo de IA por usuário). O evento variable_ai_cost é coletado na especificação de telemetria, mas sem limiar definido. | N7: Definir limite para variable_ai_cost por usuário ativo, já que o evento está previsto mas não tem teto declarado.
A8: 1 | B8: NEGÓCIO & GTM | C8: 1.7 | D8: CAC (custo de aquisição) | E8: formulario_original | F8: parcial | G8: Não existe CAC observado. Existe apenas guardrail modelado: TARGET-CAC provisório ≤ R$70 (alvo conservador) e alerta/limite de aproximadamente R$95 (cenário-base); e CAC máximo por cenário para manter LTV:CAC = 3 em R$141 (otimista), R$94 (base) e R$71 (conservador). O próprio documento fixa a regra de cálculo e proíbe substitutos: “CAC observado = gasto atribuível / novos clientes pagantes. CPI, CPM, clique e cadastro não substituem CAC.” Classe epistêmica E (inferido), status DECIDED_AS_GUARDRAIL, confiança MÉDIA na fonte. | H8: hipotese | I8: media | J8: ECO-01 | K8: DOC-C07-009 | L8: DOC-C07-009 (bloco “CAC guardrail”): “≤ R$70 alvo conservador; ≈ R$95 alerta / cenário-base. CAC observado = gasto atribuível / novos clientes pagantes. CPI, CPM, clique e cadastro não substituem CAC.” | Achado CAC-HYP-01 (epistemic_class E, status MODEL_GUARDRAIL): “Guardrail econômico; CAC observado só existe após campanha e aquisição pagante.” | Gap registrado: {gap: CAC, status: “MODELO + GUARDRAIL”, closed: false, remaining: “Campanhas e clientes pagantes.”} | M8: Falta o CAC real. Não há, em nenhum dos 214 arquivos, campanha paga executada, cliente pagante registrado ou tabela de gasto por canal. O dado nasceria dos eventos acquisition_source, campaign_id e paid_at do warehouse de telemetria — já especificados, ainda não instrumentados. | N8: Não preencher com número. Instrumentar acquisition_source/campaign_id/paid_at antes da primeira campanha paga e só então calcular CAC observado.
A9: 1 | B9: NEGÓCIO & GTM | C9: 1.8 | D9: LTV (valor do tempo de vida) | E9: formulario_original | F9: parcial | G9: Não existe LTV observado. Existe apenas LTV modelado sob premissas declaradas como classe E: ARPU mensal de R$49,90 e margem bruta assumida de 85%; cenário otimista com churn mensal de 10% → LTV R$424; cenário base com churn de 15% → LTV R$282,77; cenário conservador com churn de 20% → LTV R$212. O documento instrui explicitamente: “Não persistir como LTV factual. Substituir por cohorts LTV_30/60/90/180/365.” | H9: hipotese | I9: media | J9: ECO-01 | K9: DOC-C07-009 | L9: DOC-C07-009 (unit_economics, status MODEL_HYPOTHESIS_NOT_OBSERVED): “arpu_monthly_brl: 49.9; gross_margin_assumption: 0.85; scenarios: optimistic churn 0.10 → ltv 424; base churn 0.15 → ltv 282.77; conservative churn 0.20 → ltv 212.” | Achado LTV-HYP-01: “LTV_MODEL_BASE ≈ R$282,77 sob ARPU R$49,90, margem bruta 85% e churn mensal 15%. […] Não persistir como LTV factual.” | Gap registrado: {gap: LTV, status: “MODELO HIPOTÉTICO”, closed: false, remaining: “Retenção, churn e margem reais.”} | M9: Falta LTV factual: não há coorte real, churn observado nem pagamento registrado. O dado nasceria das janelas LTV_30/60/90/180/365 do warehouse de telemetria, especificadas mas não populadas. | N9: Não preencher com número. Rodar as coortes LTV_30/60/90 após o primeiro piloto pagante e substituir o modelo.
A10: 1 | B10: NEGÓCIO & GTM | C10: 1.9 | D10: Margem por unidade/usuário | E10: formulario_original | F10: parcial | G10: Há regra de margem, não margem observada, e ela difere por unidade. ECO-01 App: margem bruta de 85% é premissa (classe E) do modelo econômico, não medição. ECO-05 Infoprodutos: a margem deve nascer da cadeia “valor percebido → benchmark → posicionamento → taxa do canal → CAC → margem de contribuição”, com taxa Hotmart projetada por prudência em 9,9% + R$2,49 (a Central de Ajuda ainda mostrava 9,9% + R$1,00, com mudança anunciada para 21/09/2026). ECO-04 Produtos físicos: a margem deve nascer do custo variável total Y, nunca do preço de fornecedor — a planilha de landed cost do Timer 45 parte de R$39 de fornecedor e mantém “preencher” em frete internacional, impostos/importação, frete/localização, embalagem Executar e etiqueta/manual/QR; fórmulas registradas: “Margem bruta = (Preço − Custo) ÷ Preço” e “Markup = Preço ÷ Custo”. Política de margem declarada como a testar, sem percentual fixado: “Eu não fixaria ainda ‘o Timer precisa dar 60%’ ou ‘o Neurobook precisa dar 50%’”, com estratégia diferenciada por classe (Timer = produto comparável, margem disciplinada; Neurobook = proprietário, maior liberdade de preço; Office Kit = bundle, maximizar margem absoluta e ticket, não percentual). | H10: decisao | I10: media | J10: TRANSVERSAL — ECO-01 (premissa 85%), ECO-05 (taxa de canal), ECO-04 (landed cost incompleto) | K10: DOC-C07-009;DOC-C05-001;DOC-C09-008 | L10: DOC-C07-009: “gross_margin_assumption: 0.85”, dentro de unit_economics com status MODEL_HYPOTHESIS_NOT_OBSERVED. | DOC-C05-001 (Hotmart e margem): “a página comercial da Hotmart já anuncia 9,9% + R$2,49. Eu faria suas projeções usando 9,9% + R$2,49, por prudência”; e “valor percebido → benchmark → posicionamento → taxa do canal → CAC → margem de contribuição.” | DOC-C05-001 (Unit Economics — produtos físicos): tabela do Timer 45 com “Preço do fornecedor R$39” e cinco linhas “preencher”; “O preço deve nascer de Y, e não dos R$39.” | DOC-C09-008: “Timer 45 | ferramenta funcional | validar custo e preço”. | M10: Faltam os custos posto (landed cost) reais dos SKUs físicos — as linhas estão literalmente marcadas “preencher” — e falta a margem observada por usuário do app (custo de infraestrutura + variable_ai_cost por usuário ativo). Estaria numa planilha de custo de produto e num relatório de custo por usuário. | N10: Cotar frete, impostos e embalagem dos quatro SKUs para fechar o Y do Timer 45 antes de publicar preço na loja.
A11: 1 | B11: NEGÓCIO & GTM | C11: 1.10 | D11: Ponto de equilíbrio (breakeven) | E11: formulario_original | F11: lacuna | H11: fato_interno | I11: alta | J11: TRANSVERSAL | K11: DOC-C04-001;DOC-C07-009;DOC-C05-001 | L11: Busca literal por “break-even”, “breakeven” e “ponto de equilíbrio” em todos os 214 arquivos retorna um único hit: DOC-C04-001 (Cronograma.md), que é o cronograma do próprio formulário e apenas lista o nome do campo — “1.10 | Ponto de equilíbrio (breakeven) | formulário”. DOC-C07-009, o documento econômico mais avançado do corpus, cobre preço, CAC, LTV e PMF, mas não calcula breakeven, e classifica todo o bloco de unit economics como MODEL_HYPOTHESIS_NOT_OBSERVED. DOC-C05-001 discute margem, markup e capital de giro, mas nunca ponto de equilíbrio. | M11: Falta qualquer cálculo de ponto de equilíbrio: não há custo fixo mensal declarado (infraestrutura, ferramentas, Hotmart, domínios), não há meta de assinantes pagantes e não há receita atual registrada. O dado estaria numa planilha de custos fixos + modelo de receita, ou num P&L simplificado — inexistentes no corpus. | N11: Levantar o custo fixo mensal real (Vercel, Neon, Clerk, Sentry, domínios, Hotmart) e dividi-lo pela margem de contribuição por assinante para obter o número mínimo de assinantes; não estimar antes desse levantamento.
A12: 1 | B12: NEGÓCIO & GTM | C12: 1.11 | D12: Teto de gasto de infraestrutura | E12: formulario_original | F12: lacuna | H12: fato_interno | I12: alta | J12: ECO-01 (e ECO-02, site/CMS) | K12: DOC-C04-002;DOC-C02-017;DOC-C07-009 | L12: A infraestrutura está nomeada em vários documentos — DOC-C04-002 cita monorepo com bun, apps/app em Next.js, apps/mobile em Expo 57, Clerk, Sentry, Vercel Preview, “AWS/Aurora” e app local-first via localStorage; DOC-C02-017 cita “Vercel Payload Website Starter + Next.js + Payload CMS + PostgreSQL/Neon + Vercel Blob”, mais “Vercel Web Analytics + Speed Insights”. Nenhum desses documentos, nem DOC-C07-009, declara valor monetário de gasto de infraestrutura ou teto. Busca por “teto de gasto”, “custo de infra”, “orçamento de infra”, “free tier” e “plano gratuito” em todo o corpus não retorna ocorrências. | M12: Falta o teto de gasto: nenhum documento traz fatura, plano contratado (Hobby/Pro), limite de billing ou alerta de custo de qualquer fornecedor. O dado estaria nos consoles/faturas de Vercel, Neon, Clerk e Sentry, ou num documento de orçamento de infraestrutura. | N12: Exportar o custo mensal atual de cada fornecedor e definir um teto explícito com alerta de billing antes do lançamento de 07/09.
A13: 1 | B13: NEGÓCIO & GTM | C13: 1.12 | D13: Gatilhos de upgrade de infra | E13: formulario_original | F13: lacuna | H13: fato_interno | I13: media | J13: ECO-01 | K13: DOC-C04-002;DOC-C07-009 | L13: Não há gatilho de upgrade de infraestrutura em nenhum documento lido. O único enunciado adjacente é uma decisão de sequenciamento arquitetural, não um gatilho de escala: DOC-C04-002 registra “Integrar o núcleo ao Vercel AI SDK, MCP authority, Clerk e UnitOfWork local antes de Aurora” e “App é local-first: EstadoOperacional hidrata de localStorage via chaveOrganizacao + restaurarEstado, sincroniza com servidor só opcionalmente (remotePersistenceAvailable)”. DOC-C07-009 prevê coletar variable_ai_cost, mas não define limiar de disparo. | M13: Falta o gatilho: não existe métrica-limiar (usuários ativos, requisições, GB de banco, custo mensal, p95 de latência) associada a uma ação de upgrade. O dado estaria num runbook de capacidade/escalabilidade ou num ADR de infraestrutura. | N13: Definir dois ou três limiares objetivos (custo mensal, conexões de banco, p95) que disparem a migração de local-first para persistência remota/Aurora, e registrá-los como ADR.
A14: 1 | B14: NEGÓCIO & GTM | C14: 1.13 | D14: Análise competitiva | E14: enriquecido_via_plugin | F14: preenchido | G14: Há análise competitiva em três frentes, todas com preços e fontes registrados. (a) ECO-05 Infoprodutos — benchmark de e-books: ofertas de TDAH observadas a R$19,90, R$27, R$29,90 e R$37,90, e um e-book comercial da Artmed de Barkley a R$97,28; faixas de posicionamento recomendadas de R$19,90–29,90 (PDF simples) até R$99–129 (bundle de 3 e-books). Benchmark de cursos: curso introdutório 12h/16 aulas a R$89,90; curso neurodivergência/trabalho 15+ aulas a R$97; escola ampla com 200+ aulas a R$197; programa Ana Beatriz a ~R$196; programa guiado de 7 encontros a R$197; programa premium “TDAH 2.0” (90 dias, 75 aulas, app/IA) a R$1.997. (b) ECO-07 Estúdio — benchmark de consultoria: CCN a R$300/h com implantação conduzida; Produtive.Me a R$2.500 por sprint de mapeamento de 15 dias e R$4.000 por 30 dias, sem implementação; benchmark de Work OS usado para decidir vender “transformação operacional”, não “consultoria de Notion”. (c) ECO-03 Framework — prior art: ICF/CIF e WHODAS 2.0 da OMS, Roadmap to Self-Empowerment for Autistic Adults, My Sensory Experiences Tool, ICF Core Sets para autismo e TDAH, “cognitive risk” já existente em ERM, publicação da APM de 26/08/2026 e pesquisa da APM sobre neurodiversidade em project management. Guardrail explícito: “‘Não encontramos’ não significa ‘não existe’.” | H14: evidencia_externa | I14: alta | J14: TRANSVERSAL — forte em ECO-05, ECO-07 e ECO-03; fraco em ECO-01 | K14: DOC-C05-001;DOC-C01-005;DOC-C02-031;DOC-C02-022;DOC-C07-009 | L14: DOC-C05-001 (Benchmark — e-books): “Há ofertas de TDAH por R$ 19,90, R$ 27, R$ 29,90 e R$ 37,90; um e-book comercial da Artmed de Barkley, muito mais extenso e editorialmente tradicional, está em R$ 97,28.” (Benchmark — curso): tabela com seis ofertas de R$89,90 a R$1.997. (Serviços): “a CCN mantém consultoria a R$300/h […]; a Produtive.Me cobra R$2.500 por um sprint de mapeamento de 15 dias e R$4.000 por 30 dias, sem implementação.” | DOC-C01-005: “O framework mais próximo, em termos de estrutura geral, é a ICF/CIF da OMS”; “Há também o WHODAS 2.0, da OMS”. | DOC-C02-031 (item 4, GUARDRAIL): “‘Não encontramos’ não significa ‘não existe’.” | DOC-C02-022 (RC-014): “A APM publicou em 26/08/2026 conteúdo dizendo que projetos também podem falhar cognitivamente.” | DOC-C07-009 (themes_qt): tema “Benchmark de apps concorrentes” com apenas 3 registros. | M14: A análise competitiva do ECO-01 é a mais fraca: apps concorrentes (Notion, ClickUp, Trello, Todoist e similares) aparecem apenas como ferramentas que o cliente já usa, sem comparativo de features, preço ou posicionamento — e a base de evidências tem só 3 registros no tema “Benchmark de apps concorrentes”. | N14: Produzir um comparativo direto de apps concorrentes com preço, modelo de assinatura e tratamento de “próxima ação”, para sustentar o posicionamento de PRICE-01.
A15: 1 | B15: NEGÓCIO & GTM | C15: 1.14 | D15: Dados e warehouse | E15: enriquecido_via_plugin | F15: preenchido | G15: Existe arquitetura de dados documentada em cinco camadas. (a) Base de evidências: base_evidencias_tdah_adulto_WAREHOUSE.json, que encapsula um CSV — file_name base_evidencias_tdah_adulto_WAREHOUSE.csv, sha256 57f2a101…cffdbf, 129.719 bytes, 30 colunas, 240 registros. (b) Canônico e schema: “Google Drive / Supabase-2026-TDHA”, schema_version “DATA-SCHEMA-002 / base 1.1”; estado atual com 31 sources, 248 RAW, 116 knowledge, 161 evidence candidates, 0 strict VERIFIED, 240 evidências legadas, 694 perguntas de framework e 22 decisões operacionais. Gate factual definido: “record_status=VERIFIED · classe A/B/C · source_verified · extraction_verified · context_verified · proveniência · numeric_verified para measurement”. (c) Schema de domínio: SCHEMA_MATRIZ_GESTAO_TDAH_V1 (CSV + YAML), 18 campos, origem DATA-ADHD-PM-001/DRIVE-PROD-002, estado documental “existente + registrado + verificado; não preenchido; não aprovado como schema final”. (d) Telemetria de produto especificada e não instrumentada: acquisition_source, campaign_id, install_or_signup, activated_at, first_value_at, paid_at, plan, gross_revenue, refund, variable_ai_cost, cancelled_at, renewed_at, last_value_event_at; coortes W1/W2/W4/W8; janelas LTV_30/60/90/180/365. (e) Observabilidade editorial: Vercel Web Analytics + Speed Insights, com decisão RC-054 de priorizar métricas agregadas em vez de identificação individual. | H15: fato_interno | I15: alta | J15: TRANSVERSAL | K15: DOC-C07-007;DOC-C07-009;DOC-C07-005;DOC-C07-006;DOC-C02-017 | L15: DOC-C07-007 (cabeçalho do JSON): “format: csv · file_name: base_evidencias_tdah_adulto_WAREHOUSE.csv · sha256: 57f2a1015cf04e67fba04178e038f8d31f617d6e0ec050711280c8b048cffdbf · size_bytes: 129719 · columns: 30 · row_count: 240”. | DOC-C07-009 (status): “canonical: Google Drive / Supabase-2026-TDHA · schema_version: DATA-SCHEMA-002 / base 1.1”; (Estado atual): “31 sources · 248 RAW · 116 knowledge · 161 evidence candidates · 0 strict verified · 22 decisões operacionais.” | DOC-C07-006: “estado_documental: existente + registrado + verificado; não preenchido; não aprovado como schema final”. | DOC-C02-017 (OBSERVABILIDADE): “Vercel Web Analytics + Speed Insights”; RC-054: “Inicialmente priorizar métricas agregadas, não identificação…”. | M15: O warehouse cobre evidência científica, não dados de produto: são 0 registros strict VERIFIED e nenhum evento de telemetria do app foi coletado — a lista de required_events é especificação, não dado. | N15: Instrumentar os 13 required_events antes do lançamento, para que CAC, LTV e PMF possam migrar de modelo para observação.
A16: 1 | B16: NEGÓCIO & GTM | C16: 1.15 | D16: Cadência financeira recorrente | E16: enriquecido_via_plugin | F16: lacuna | H16: fato_interno | I16: alta | J16: TRANSVERSAL | K16: DOC-C04-001;DOC-C06-001;DOC-C07-009;DOC-C07-010 | L16: Busca por “DRE”, “P&L”, “demonstrativo de resultado”, “variância”, “fluxo de caixa” e “MRR” em todo o corpus retorna apenas: DOC-C04-001 (Cronograma.md), que só lista o nome do campo “1.15 | Cadência financeira recorrente (P&L/variância) | 🔌 finance/financial-statements, variance-analysis”, e ocorrências em outro sentido (variância estatística, gates operacionais). Existe cadência OPERACIONAL detalhada — DOC-C06-001 define templates diário e semanal, WEEK-01/WEEK-02, gates G0–G9, DoD diário e somatório de horas por value stream — mas nenhuma cadência FINANCEIRA: não há fechamento mensal, revisão de receita e custo, nem análise de variância orçado × realizado. | M16: Falta a rotina financeira recorrente: quem fecha, com que periodicidade, contra qual orçamento e em qual artefato. O dado estaria num P&L/planilha financeira mensal ou num runbook de fechamento — inexistentes no corpus. | N16: Instituir um fechamento mensal simples (receita por canal, custo fixo, custo variável de IA/infra, margem) assim que houver a primeira venda; hoje não há receita registrada que justifique análise de variância.
A17: 1 | B17: NEGÓCIO & GTM | C17: 1.16 | D17: Pipeline e forecast de vendas | E17: enriquecido_via_plugin | F17: parcial | G17: Há pipeline definido para ECO-07 (Estúdio) e nenhum forecast quantificado em nenhuma unidade. Pipeline do Estúdio: “Conteúdo → problema reconhecido → showroom demonstra solução concreta → formulário visual de 5 min → seleção de fit → D1 entender + cocriar → D2–D3 estruturar + construir → D4 demonstrar protótipo → D5 Studio + teste assíncrono → D6 implementar + onboarding → D7 validar → 10/20/30 manutenção → caso + evidência → novo projeto / indicação / expansão”. Capacidade declarada: 1 cliente por semana, 1 projeto, 1 entrega principal, 7 dias. Escada comercial que funciona como estágio de pipeline: Piloto 01–03 a R$0 (para construir processo, métricas e portfólio) → Founding 04–06 a R$700 (primeiros clientes pagantes) → Regular Workflow a partir de R$1.490, Automação/Agente a partir de R$1.990, App/Sistema a partir de R$2.490. A qualificação é capturada no FORM-001, que inclui “prazo desejado” e “faixa de investimento” (Até R$1.500 · R$1.500–2.500 · R$2.500–5.000 · Ainda não sei), além da tabela de fit “É para / Não é para”. | H17: decisao | I17: media | J17: ECO-07 (pipeline definido); forecast ausente em todas as unidades | K17: DOC-C05-001;DOC-C12-003;DOC-C09-006;DOC-C11-010 | L17: DOC-C05-001 (Cadeia única de valor final): “Conteúdo ↓ problema reconhecido ↓ showroom demonstra solução concreta ↓ formulário visual de 5 min ↓ seleção de fit ↓ D1 · entender + cocriar […] ↓ caso + evidência ↓ novo projeto / indicação / expansão.” (Escada recomendada): “Piloto 01–03 · R$0; Founding 04–06 · R$700; Regular Workflow · desde R$1.490; Regular Automação/Agente · desde R$1.990; Regular App/Sistema · desde R$2.490.” | DOC-C09-006 (Modelo): “1 cliente por semana · 1 projeto · 1 entrega principal · 7 dias.” | DOC-C12-003: “10 · Faixa de investimento imaginada: Até R$1.500 · R$1.500–2.500 · R$2.500–5.000 · Ainda não sei.” | M17: Falta o forecast: não há número esperado de leads, taxa de conversão por estágio, ticket médio projetado nem receita prevista por mês. E não há pipeline algum para ECO-01 (assinaturas) nem ECO-05 (infoprodutos). O dado estaria num CRM ou planilha de forecast — inexistentes no corpus. | N17: Instrumentar o FORM-001 para contar leads por estágio a partir de 07/09 e só então projetar conversão, dado que a capacidade está travada em 1 cliente por semana.
A18: 2 | B18: PRODUTO | C18: 2.1 | D18: Nome do produto/feature | E18: formulario_original | F18: preenchido | G18: Nomes canônicos por unidade. ECO-01 — produto: EXECUTAR (grafado “Executar”), com três features de destaque: Feature 01 Agente 007 / Autogestão adaptativa; Feature 02 Scanner / QR / Atalhos; Feature 03 Mapa-OS / Analógico / Prisma. No código, a identidade unificada chama-se “tokens exec.*” e as rotas entregues são /scanner e /mapa-os (formatos ?format=prisma, A4 retrato, e ?format=tripe, A4 paisagem). ECO-07: “Executar Studio”, com três famílias — 01 Processos & Workflows, 02 Automações & Agentes, 03 Apps & Sistemas de Trabalho. ECO-02/ECO-03: marca editorial “Risco Cognitivo” (publicação riscocognitivo.org, canais @riscocognitivo) e framework técnico provisório “Cognitive Execution Risk Management — CERM”. ECO-05: curso “Gerenciando o TDAH Adulto” (I0) e e-books I1 “Aplicando o TDAH Adulto — Tutorial Prático”, I2 “TDAH Risk Management na Prática”, I3 “Gerenciando o TDAH Adulto / 360”. ECO-04: P0 “Executar Office Kit” (hero product), P1 “Executar Neurobook”, P2 “Timer 45”, P3 “Kit de Organização Física”. ECO-02: “Biblioteca Executar”. | H18: fato_interno | I18: alta | J18: TRANSVERSAL — nomes distintos por unidade | K18: DOC-C05-001;DOC-C04-002;DOC-C09-004;DOC-C09-011;DOC-C09-013;DOC-C09-008;DOC-C01-006;DOC-C02-016 | L18: DOC-C05-001: “Feature 01 — Agente 007 / Autogestão adaptativa”, “Feature 02 — Scanner / QR / Atalhos”, “Feature 03 — Mapa-OS / Analógico / Prisma”; Master Index dos infoprodutos I0–I4; Master Index — Produtos Físicos P0–P4. | DOC-C04-002: “PR #77 — feat(design-system): identidade única de tokens exec.*”; rotas “apps/app/app/(authenticated)/scanner/” e “/mapa-os?format=prisma (padrão, A4 retrato) e /mapa-os?format=tripe (A4 paisagem)”. | DOC-C01-006: “Risco Cognitivo → é a marca editorial; riscocognitivo.org → é a publicação/site; @riscocognitivo → são os canais da publicação.” | DOC-C02-016: “TÍTULO: Cognitive Execution Risk Management — v0.1”, com guardrail “Não reivindicar criação de ‘Cognitive Risk Management’”.
A19: 2 | B19: PRODUTO | C19: 2.2 | D19: Contexto do PRD | E19: formulario_original | F19: parcial | G19: Não existe PRD no corpus. O que existe é a base que antecede e alimenta um PRD, mais referências a PRDs que estão fora do conjunto documental. (a) Base: DATA-ADHD-PM-001 — “Matriz paralela Gestão de Projetos → exigência humana → vulnerabilidade associada ao TDAH → impacto operacional → compensação sistêmica → decisão de produto”, versão 1.0, de 19/08/2026, owner “Não determinado”, com o Next 01 explícito de “transformar a matriz em requisitos funcionais e princípios de design verificáveis”. (b) 22 decisões operacionais governadas (PROD-01…PROD-15 mais ICP-01, POSITION-01, PRICE-01, CAC-01, PMF-01, EFFICACY-01 e CLAIM-01), que funcionam como o contexto decisório que um PRD consumiria. (c) Referências a artefatos ausentes: DOC-C04-002 cita “PRD-006/UX-004” como critério de UX do Scanner e “OQ-008 do FRD original do Scanner” — nem o PRD-006 nem o FRD constam do inventário de 214 arquivos. | H19: fato_interno | I19: media | J19: ECO-01 | K19: DOC-C07-010;DOC-C07-009;DOC-C04-002;DOC-C07-002 | L19: DOC-C07-010: “ID DATA-ADHD-PM-001 · Tipo Pesquisa — Matriz de evidências e implicações de produto · Owner Não determinado · Versão 1.0 · Data 19/08/2026”; “Next 01 Transformar a matriz abaixo em requisitos funcionais e princípios de design verificáveis.” | DOC-C04-002: “Câmera compacta por padrão (PRD-006/UX-004: velocidade de captura antes de prévia grande)” e “Offline (OQ-008 do FRD original do Scanner) segue fora de escopo, nunca implementado.” | M19: Falta o PRD propriamente dito. Os documentos citam PRD-006 e um FRD do Scanner que não estão entre os 214 arquivos — provavelmente vivem no repositório Sas-Executar/Sas-Executar ou no Drive, não no conjunto entregue. | N19: Localizar PRD-006 e o FRD do Scanner no repositório/Drive e incorporá-los ao registro documental, ou declará-los inexistentes e escrever o PRD a partir de DATA-ADHD-PM-001.
A20: 2 | B20: PRODUTO | C20: 2.3 | D20: Objetivos (goals) | E20: formulario_original | F20: preenchido | G20: Objetivos por unidade. ECO-01 App: “transferir carga executiva evitável do operador para o sistema, preservando decisão e autonomia do usuário”; e “criar uma situação em que a execução do que foi planejado aconteça com o mínimo possível de carga administrativa e cognitiva”. ECO-03 Framework: “Investigar riscos cognitivos endógenos como vulnerabilidades capazes de aumentar a probabilidade de desvio entre intenção e execução”, com cinco componentes provisórios — Cognitive Risk Profile, Cognitive Demand Map, Cognitive Risk Register, Compensating Controls e Execution Evidence. ECO-02 Blog: “Publicar o artigo fundador e iniciar a campanha inaugural de 14 dias sem transformar a campanha em lançamento de produto”; objetivo SMART: “lançar Risco Cognitivo e validar interesse pela tese”. GTM 07/09 (transversal): 60h comprometidas + 12h de reserva em 12 dias produtivos (83% da capacidade), com tudo “produzido, integrado, configurado e agendado” até 05/09. ECO-05 Curso: quatro módulos Entender → Estruturar → Executar → Evoluir. ECO-02 site/CMS: autonomia editorial total, sem tocar em código. | H20: decisao | I20: alta | J20: TRANSVERSAL — objetivos distintos por unidade | K20: DOC-C07-002;DOC-C02-016;DOC-C02-014;DOC-C06-001;DOC-C09-013;DOC-C02-017 | L20: DOC-C07-002 (Tese operacional): “transferir carga executiva evitável do operador para o sistema, preservando decisão e autonomia do usuário.” | DOC-C02-016 (PROPOSIÇÃO): “Investigar riscos cognitivos endógenos como vulnerabilidades capazes de aumentar a probabilidade de desvio entre intenção e execução”; COMPONENTES PROVISÓRIOS 1–5. | DOC-C02-014 (OBJETIVO): “Publicar o artigo fundador e iniciar a campanha inaugural de 14 dias sem transformar a campanha em lançamento de produto.” | DOC-C06-001: “recomendação: 60h comprometidas + 12h de reserva (83% da capacidade)”. | DOC-C09-013: “4 módulos: Entender → Estruturar → Executar → Evoluir.”
A21: 2 | B21: PRODUTO | C21: 2.4 | D21: Não-objetivos (non-goals) | E21: formulario_original | F21: preenchido | G21: Não-objetivos explícitos e abundantes, por unidade. ECO-01: PROD-14 — “Bloquear usos do produto como diagnóstico, substituição profissional ou inferência clínica a partir de desempenho em tarefas”; CLAIM-01 proíbe “Reduz sintomas de TDAH”, “Melhora função executiva clinicamente”, “Trata TDAH”, “Diagnostica ou identifica TDAH”, “Substitui terapia, tratamento ou medicação” e “Cientificamente comprovado para TDAH”; POSITION-01 — “não como tratamento de TDAH”; EFFICACY-01 — “não iniciar com claim de redução de sintomas”. No código: “Offline (OQ-008) segue fora de escopo, nunca implementado”; e o primitivo concluirPorGestoHumano é “reservado DELIBERADAMENTE só para gesto humano direto — o Copiloto/IA continua passando por executarFerramenta”. Duas explorações de design foram registradas e deliberadamente NÃO adotadas: “Fractal Fluent” e “3PN + Good Path”. ECO-02: “O artigo não termina vendendo EXECUTAR”; “O CTA do D14 não deve vender EXECUTAR na campanha inaugural.” ECO-03: “Não reivindicar criação de ‘Cognitive Risk Management’”; não afirmar que “déficit de atenção” é termo abolido; não afirmar que pessoas neurotípicas não possuem riscos cognitivos. ECO-04: “Roupas — fora do escopo atual […] Não lançar agora”; “Não imobilizar estoque relevante antes de validar intenção.” ECO-07: tabela “Não é para” (quem busca tratamento de saúde, quem quer só uma dica rápida, projeto sem dono, escopo indefinido, grande transformação corporativa em sete dias); e “Eu não publicaria ‘consulta sem limite de tempo’ literalmente.” GTM 07/09: “Não é: Editar landing · Terminar vídeo · Produzir post · Cadastrar produto.” | H21: decisao | I21: alta | J21: TRANSVERSAL | K21: DOC-C07-009;DOC-C04-002;DOC-C02-043;DOC-C02-014;DOC-C02-016;DOC-C09-008;DOC-C05-001;DOC-C06-001 | L21: DOC-C07-009 (PROD-14): “Bloquear usos do produto como diagnóstico, substituição profissional ou inferência clínica a partir de desempenho em tarefas”; (claims_policy.prohibited_now): lista literal dos seis claims. | DOC-C04-002 (item 4e): “Offline (OQ-008 do FRD original do Scanner) segue fora de escopo, nunca implementado.”; e “Duas explorações de design JÁ REGISTRADAS no ecossistema e DELIBERADAMENTE NÃO ADOTADAS aqui”. | DOC-C02-043: “O artigo não termina vendendo EXECUTAR.” | DOC-C02-016 (GUARDRAIL): “Não reivindicar criação de ‘Cognitive Risk Management’.” | DOC-C09-008 (Regra): “Não imobilizar estoque relevante antes de validar intenção.” | DOC-C06-001 (07/09): “Não é: Editar landing · Terminar vídeo · Produzir post · Cadastrar produto. Se isso estiver acontecendo em 07/09, o Freeze falhou.”
A22: 2 | B22: PRODUTO | C22: 2.5 | D22: Requisitos funcionais (FRD) | E22: formulario_original | F22: preenchido | G22: Requisitos funcionais existem em dois níveis. (a) Componentes sistêmicos derivados da compensação (DOC-C05-001, item 16): “memória externa persistente, decomposição assistida, motor de prioridade, próxima ação, contexto persistente, throughput observado, sistema temporal, grafo de dependências, progresso automático, DoD e retomada de estado”; automações (item 18): “recalcular prioridades, filtrar elegibilidade, preservar contexto, atualizar progresso e selecionar a próxima ação”. Regras do motor: dependências, tempo, WIP e ciclo definem elegibilidade; Flow Score e Context Score ordenam as alternativas válidas; Progress Points registram somente trabalho efetivamente concluído. (b) Requisitos já implementados e verificáveis (DOC-C04-002): rota /scanner com reconhecimento de forma, sem QR, dos cinco símbolos administrativos entrada | copiloto | seletor | feito | saída; resolverPayloadScanner(payload); idempotencyKeyScanner com bucket de 10s contra duplo-scan acidental; Undo com janela de 8s restaurando o EstadoOperacional anterior via expectedRevision (concorrência otimista); rota /mapa-os com projetarMapaOS — projeção pura, “nenhum estado novo” — nos formatos prisma (A4 retrato) e tripé (A4 paisagem); primitivo concluirPorGestoHumano, que ignora requireDod, requireEvidence, requireHumanApproval e requireVerification mesmo sob POLITICA_CONCLUSAO_PADRAO, mas apenas para gesto humano direto e mantendo registro auditável no event log; toda mutação oficial passa por executarFerramenta, com idempotência e replay via run-ledger. (c) Requisitos de UX derivados das decisões PROD-05 e PROD-09…PROD-13: uma única próxima ação principal explícita; nos primeiros segundos mostrar estado atual, resultado necessário e próxima ação; persistir contexto e posição de execução para retomada; interromper apenas por evento crítico; exigir confirmação só em ações irreversíveis. | H22: fato_interno | I22: alta | J22: ECO-01 | K22: DOC-C04-002;DOC-C05-001;DOC-C07-009;DOC-C11-006;DOC-C11-004 | L22: DOC-C04-002: “idempotencyKeyScanner(organizationId, acao, alvo, nowMs) → bucket de 10s, evita duplo-scan acidental”; “Undo: janela de 8s, restaura o EstadoOperacional anterior via o mesmo endpoint de salvar estado com expectedRevision”; “concluirPorGestoHumano(tasks, state, taskId, nota) — Ignora TODAS as flags de PoliticaConclusao […] Reservado DELIBERADAMENTE só para gesto humano direto”. | DOC-C05-001 (item 16 Componentes sistêmicos): lista literal dos onze componentes. | DOC-C07-009 (PROD-09): “A interface deve tornar explícita uma única próxima ação principal e esconder complexidade secundária até ser necessária.” | M22: Não há FRD consolidado: os requisitos estão distribuídos entre handoff técnico, workbook e decisões. O Scanner mobile (Expo) só é validável em device físico e não foi testado além de typecheck/build. | N22: Consolidar os requisitos dispersos num FRD único e validar o Scanner mobile em device físico antes do lançamento.
A23: 2 | B23: PRODUTO | C23: 2.6 | D23: Critérios de aceite | E23: formulario_original | F23: preenchido | G23: Critérios de aceite existem em cinco camadas. (a) DoD editorial do GTM: “texto aprovado + assets presentes + CTA funcional + brinde funcional + CMS carregado + SEO preenchido + links testados + publicação/agendamento confirmado + evidência registrada”, sobre a cadeia de pacote “conteúdo → assets → CTA → brinde → destino → CMS → distribuição → agendamento → tracking → evidência = DONE”. (b) Critérios de lançamento de 05/09 (dez itens): páginas críticas abrem em celular e computador; todas as chamadas chegam ao destino correto; formulários recebem respostas; ofertas digitais estão cadastradas; ligações de afiliado estão identificadas; peças editoriais publicadas ou agendadas; demonstrações acessíveis; materiais para redes agendados; medição básica funcionando; não existe entrega crítica aguardando produção. (c) DoD técnico verificado: typecheck limpo, bun run check limpo, 51/51 testes vitest, 347/347 testes de governança e 3/3 checks de CI verdes por PR. (d) DoD do site/CMS: “Abrir /admin → criar artigo → escrever/colar → categorizar → inserir imagem → preencher SEO → ver palavras/parágrafos → preview → publicar, sem editar código.” (e) Critério de conclusão do ECO-02: “Artigo 1.200–1.800 palavras publicado, landing disponível, CTA editorial funcionando e cronograma D1–D14 iniciado.” Princípio de produto que rege todos: “DONE deve ser uma transição verificável, não uma sensação de conclusão.” | H23: fato_interno | I23: alta | J23: TRANSVERSAL | K23: DOC-C06-001;DOC-C08-007;DOC-C04-002;DOC-C02-017;DOC-C02-014;DOC-C07-002;DOC-C10-010;DOC-C10-018;DOC-C10-026 | L23: DOC-C06-001: “Definition of Done editorial: texto aprovado + assets presentes + CTA funcional + brinde funcional + CMS carregado + SEO preenchido + links testados + publicação/agendamento confirmado + evidência registrada.” | DOC-C08-007: lista literal dos dez critérios de congelamento de 05/09. | DOC-C04-002: “bun run --filter=app test (vitest) → 51/51 passando”; “node --test tests/ondas/*.test.mjs (governança) → 347/347 passando”. | DOC-C02-017 (DEFINITION OF DONE): “Abrir /admin → criar artigo → […] → publicar, sem editar código.” | DOC-C07-002 (GP-10, decisão de produto): “DONE deve ser uma transição verificável, não uma sensação de conclusão.” | DOC-C10-010/018/026: “Concluído quando: A peça está publicada ou programada, com materiais, chamada, destino e evidência registrados.”
A24: 2 | B24: PRODUTO | C24: 2.7 | D24: Persona principal | E24: formulario_original | F24: parcial | G24: Não há artefato de persona (nome, cenário, objetivos, frustrações) em nenhum documento. O que existe são duas descrições de ICP em conflito — as mesmas do campo 1.2 — acrescidas de perspectivas em primeira pessoa que funcionam como matéria-prima de persona. Versão A (DOC-C05-001): “Homens, adultos, neurodivergentes, autônomos, na faixa dos 25–35 anos, recém-diagnosticados, que gerenciam múltiplos processos e projetos ao mesmo tempo […] já utilizaram e abandonaram outros aplicativos por não manterem o uso e rejeitam alta complexidade de configuração.” Versão B (DOC-C07-009, ICP-01): “profissional independente/solo brasileiro, aproximadamente 25–44 anos, multiprojeto, que perde contexto, tem dificuldade recorrente para escolher próxima ação, já tentou ferramentas de produtividade e controla/influencia a própria compra”, sem exigir diagnóstico. Persona do ECO-07 documentada em separado: “profissionais solo, autônomos e pequenos negócios com trabalho, informação, clientes e projetos dispersos”, com tabela “É para / Não é para”. | H24: hipotese | I24: media | J24: ECO-01 (com persona própria em ECO-07) | K24: DOC-C05-001;DOC-C07-009;DOC-C12-003 | L24: DOC-C05-001 (Corpo, linha Público): texto integral da versão A, com a perspectiva do usuário “Quero começar o dia, semana, mês de trabalho executando as tarefas sem, ao mesmo tempo, me preocupar com a ordem e controle da progressão.” | DOC-C07-009 (ICP comercial a testar): texto integral da versão B, com “Decisão ICP-01: testar comportamento e problema primeiro; diagnóstico não define o ICP comercial inicial.” | DOC-C12-003: dez perguntas do formulário de entrada do Estúdio, que operacionalizam o perfil (como trabalha hoje, principal atrito, ferramentas atuais, dificuldade de retomada, relação com papel/físico). | M24: Falta a persona formalizada, e falta resolver o conflito de ICP (faixa etária 25–35 × 25–44, gênero, papel do diagnóstico). O artefato estaria num documento de pesquisa de usuário/persona — inexistente; e a própria decisão ICP-01 tem status DECIDED_FOR_TEST, isto é, hipótese a validar em recrutamento. | N24: Resolver o conflito de ICP e escrever uma persona única derivada da versão vencedora; ICP-01 já prevê “recrutar ICP comportamental e medir ativação, recorrência, pagamento e retenção”.
A25: 2 | B25: PRODUTO | C25: 2.8 | D25: Jornada — Descoberta | E25: formulario_original | F25: parcial | G25: A jornada de descoberta está desenhada para os eixos editorial e de serviços, não para o app. Editorial (ECO-02): a descoberta é governada por níveis de consciência — “Não consciente → consciente do problema → consciente das soluções → consciente do método → pronto para agir” — com CTA correspondente por nível (“Baixa consciência: não empurre Produto; CTA ideal ‘Entenda o que está acontecendo’”; “Alta intenção: não empurre mais teoria; CTA ‘Experimentar Executar / conhecer Studio’”). O artigo canônico é a peça-mãe e cada peça segue a narrativa “CENA → PROBLEMA → MECANISMO → EVIDÊNCIA → MODELO → APLICAÇÃO → DEMONSTRAÇÃO → PRÓXIMO PASSO”. A campanha inaugural do ECO-02 vai de D1 (artigo + landing) a D14 (síntese + CTA editorial), com CTA “ler, explorar, assinar e baixar o Mapa de Risco Cognitivo” e o produto deliberadamente em segundo plano. Serviços (ECO-07): “Conteúdo → Showroom → Formulário visual → Encontro → Projeto”, com regra de showroom “Problema → entrada real → transformação → resultado → prova → CTA”. Porta de entrada de captação: brinde canônico BRINDE-001/GIFT-001, com cadeia “asset → capa → landing → formulário → confirmação → entrega/download → CTA → tracking → evidence”. | H25: decisao | I25: media | J25: ECO-02 e ECO-07 documentadas; ECO-01 sem jornada de descoberta própria | K25: DOC-C05-001;DOC-C02-043;DOC-C06-001;DOC-C10-029;DOC-C11-010;DOC-C12-004 | L25: DOC-C05-001 (CTA por nível de consciência): “Baixa | não empurre Produto | CTA ideal Entenda o que está acontecendo”; “Alta intenção | não empurre Mais teoria | CTA Experimentar Executar / conhecer Studio.” | DOC-C05-001 (Showroom — regra geral): “Problema → entrada real → transformação → resultado → prova → CTA. Não faça vídeos ‘Veja meu agente incrível’.” | DOC-C02-043: “CTA inicial: ler, explorar, assinar e baixar o Mapa de Risco Cognitivo; o EXECUTAR fica para uma campanha posterior.” | DOC-C10-029: “asset → capa → landing → formulário → confirmação → entrega/download → CTA → tracking → evidence” (cadeia do brinde). | M25: Falta a jornada de descoberta específica do app: como um usuário chega ao EXECUTAR (loja de apps, landing, indicação) não está documentado. Os eventos acquisition_source e campaign_id existem como especificação de telemetria, sem mapa de jornada correspondente. | N25: Desenhar a jornada de descoberta do ECO-01 ligando os CTAs CH-001/CH-002 aos eventos acquisition_source e install_or_signup.
A26: 2 | B26: PRODUTO | C26: 2.9 | D26: Jornada — Ativação | E26: formulario_original | F26: preenchido | G26: A ativação está definida com precisão no ECO-01 pelo VALUE_EVENT-01: “Projeto real → contexto interpretado → próxima ação válida → ação executada → conclusão/evidência registrada”. Os eventos de telemetria que a marcam são activated_at e first_value_at. As decisões que governam os primeiros minutos: PROD-12 — “Nos primeiros segundos, mostrar estado atual, resultado necessário e próxima ação — não o projeto inteiro”; PROD-09 — “A interface deve tornar explícita uma única próxima ação principal”; PROD-08 — “Usar perguntas de auto-observação e funcionamento cotidiano; proibir triagem diagnóstica baseada em um único teste, score ou tarefa do app”; PROD-05 — reduzir densidade simultânea de informação. Tecnicamente, o app é local-first (hidrata de localStorage via chaveOrganizacao + restaurarEstado), o que remove exigência de credenciais ou servidor para o primeiro uso. ECO-07 tem ativação própria: D0 formulário visual de 5 minutos → D1 conversa + desenho da solução ao vivo → D4 protótipo funcional → D6 entrega + onboarding. | H26: decisao | I26: media | J26: ECO-01 (com jornada de ativação própria em ECO-07) | K26: DOC-C07-009;DOC-C04-002;DOC-C05-001;DOC-C11-004 | L26: DOC-C07-009 (telemetry): “value_event_01: Projeto real → contexto interpretado → próxima ação válida → ação executada → conclusão/evidência registrada”; required_events incluem “activated_at” e “first_value_at”. | DOC-C07-009 (PROD-12): “Nos primeiros segundos, mostrar estado atual, resultado necessário e próxima ação — não o projeto inteiro.” | DOC-C04-002: “App é local-first: EstadoOperacional hidrata de localStorage via chaveOrganizacao + restaurarEstado, sincroniza com servidor só opcionalmente.” | DOC-C05-001 (Jornada canônica do Studio): “D0 Formulário de 5 minutos… D6 Versão final — Entrega + onboarding.” | M26: O VALUE_EVENT-01 está definido, mas não instrumentado: não existe nenhuma taxa de ativação medida. | N26: Instrumentar activated_at e first_value_at e medir a taxa de conclusão do VALUE_EVENT-01 no piloto de ≥40 usuários previsto em PMF-01.
A27: 2 | B27: PRODUTO | C27: 2.10 | D27: Jornada — Uso recorrente | E27: formulario_original | F27: parcial | G27: O uso recorrente é desenhado como uso deliberadamente baixo — e isso é assumido como hipótese, não como fato. Promessa: “uso mínimo do app — cerca de 1–2 vezes por semana”; princípio: “o usuário não estrutura, organiza ou prioriza; o usuário visualiza, acompanha e administra”. O Diferencial 03 registra explicitamente que “a superioridade específica do analógico e a frequência ideal de ‘1–2 vezes por semana’ permanecem hipóteses de produto/design, não resultados empiricamente demonstrados nos documentos”. O loop operacional recorrente está demonstrado pelo Agente 007: “/bomdia → reconstruir estado → mostrar trabalho atual” e a sequência “/bomdia → /agora → execução → evidência → /fechardia → /estado → replanejamento”. Métricas de recorrência especificadas: coortes W1/W2/W4/W8, execution_cycles_per_week, last_value_event_at e renewed_at. No plano físico, o Mapa-OS existe para sustentar o trabalho fora da tela: “Seu sistema de execução não precisa viver na tela para continuar sustentando o trabalho.” ECO-07 tem recorrência contratual própria: manutenção programada em 10/20/30 dias, com expansão tratada como novo projeto. | H27: hipotese | I27: media | J27: ECO-01 (com recorrência contratual própria em ECO-07) | K27: DOC-C05-001;DOC-C07-009;DOC-C11-006;DOC-C11-008 | L27: DOC-C05-001 (Promessa principal): “Zero configuração, mínimo de personalização, uso mínimo do app — cerca de 1–2 vezes por semana — e externalização cognitiva”; (Diferencial 03): “a superioridade específica do analógico e a frequência ideal de ‘1–2 vezes por semana’ permanecem hipóteses de produto/design, não resultados empiricamente demonstrados nos documentos.” | DOC-C11-006 (Cena A): “/bomdia → reconstruir estado → mostrar trabalho atual.” | DOC-C07-009 (telemetry): “cohorts: W1, W2, W4, W8”; “execution_cycles_per_week”. | DOC-C11-008 (Mensagem): “O sistema pode sustentar o trabalho sem exigir permanência contínua na tela.” | M27: Falta qualquer dado de retenção observada: nenhuma coorte medida, nenhuma frequência real de uso, e o próprio churn de 10/15/20% é premissa. O dado nasceria das coortes W1/W2/W4/W8 do warehouse, ainda não populadas. | N27: Medir a frequência real de uso no piloto para confirmar ou falsear a hipótese de 1–2 vezes por semana, que hoje sustenta a promessa central do produto.
A28: 2 | B28: PRODUTO | C28: 2.11 | D28: Momento 'aha' | E28: formulario_original | F28: parcial | G28: Nenhum documento usa a expressão “momento aha”. O equivalente funcional canônico é o VALUE_EVENT-01 — “Projeto real → contexto interpretado → próxima ação válida → ação executada → conclusão/evidência registrada” —, definido como o evento que caracteriza valor entregue e que governa o gate de PMF. As cenas de demonstração que materializam esse momento são: Cena A do app — “‘Tenho 30 minutos.’ Mostrar o sistema reduzindo um projeto complexo à próxima ação possível”; Cena B — “Alterar uma condição do dia e mostrar plano preservado + rota recalculada”; e o loop do Agente 007 — “/bomdia → reconstruir estado → mostrar trabalho atual”. A frase de posicionamento que descreve o momento: “Você não precisa reorganizar o projeto toda vez que o dia muda. O sistema recalcula a rota e mostra o próximo passo possível.” A mensagem correspondente é “O plano continua. A rota se adapta. Você executa.” | H28: inferencia | I28: media | J28: ECO-01 | K28: DOC-C07-009;DOC-C11-004;DOC-C11-006;DOC-C05-001 | L28: DOC-C07-009 (telemetry.value_event_01): cadeia literal de cinco etapas. | DOC-C11-004 (Cena A): “‘Tenho 30 minutos.’ Mostrar o sistema reduzindo um projeto complexo à próxima ação possível”; (Cena B): “Alterar uma condição do dia e mostrar plano preservado + rota recalculada.” | DOC-C05-001 (Frase de posicionamento 01 e Mensagem 01): “Você não precisa reorganizar o projeto toda vez que o dia muda. O sistema recalcula a rota e mostra o próximo passo possível.” / “O plano continua. A rota se adapta. Você executa.” | M28: Falta nomear e medir o momento aha: não há definição de qual etapa exata do VALUE_EVENT-01 produz o reconhecimento de valor, nem tempo-alvo para alcançá-lo — o endpoint time_to_next_action existe, mas sem meta. | N28: Adotar “primeira próxima ação válida executada em menos de X minutos” como definição operacional do momento aha e fixar X após observar time_to_next_action no piloto.
A29: 2 | B29: PRODUTO | C29: 2.12 | D29: User story de referência | E29: formulario_original | F29: parcial | G29: Não existe user story em formato canônico (“Como <persona>, quero <ação>, para <benefício>”) em nenhum dos documentos lidos — a busca por “user story” e por padrões “Como … quero …” nos 214 arquivos não retorna ocorrências. O que existe são três declarações em primeira pessoa registradas como “Perspectiva do usuário” no workbook, que cumprem a mesma função. (1) Público: “Quero começar o dia, semana, mês de trabalho executando as tarefas sem, ao mesmo tempo, me preocupar com a ordem e controle da progressão.” (2) Problema: “Perco dinheiro e oportunidades por atrasos e desorganização. Quando consigo terminar aquilo que foi planejado, o custo emocional e cognitivo é tão alto que não faço mais nada. O momento de maior ansiedade e aflição são os primeiros 30 minutos iniciais, pois não sei onde estava ontem, o que devo fazer agora e como sei que terminei.” (3) Categoria: “Esse app me entende e foi desenhado para mim e organiza tudo para mim de forma confiável e com metodologias válidas.” A declaração (2) é a mais utilizável como story de referência porque nomeia gatilho (retomada), momento (primeiros 30 minutos) e as três perguntas do usuário — onde parei, o que faço agora, como sei que terminei — que mapeiam diretamente nos requisitos de contexto persistente, próxima ação e DoD verificável. | H29: fato_interno | I29: media | J29: ECO-01 | K29: DOC-C05-001;DOC-C11-004 | L29: DOC-C05-001 (Corpo, linha Problema, Perspectiva do usuário): “Perco dinheiro e oportunidades por atrasos e desorganização. […] O momento de maior ansiedade e aflição são os primeiros 30 minutos iniciais, pois não sei onde estava ontem, o que devo fazer agora e como sei que terminei.” | DOC-C05-001 (Corpo, linha Público): “Quero começar o dia, semana, mês de trabalho executando as tarefas sem, ao mesmo tempo, me preocupar com a ordem e controle da progressão.” | DOC-C11-004 (Cena A): “‘Tenho 30 minutos.’” | M29: Falta a user story formal com critérios de aceite acoplados. O artefato estaria num backlog ou PRD — inexistentes no corpus. | N29: Converter a perspectiva dos “primeiros 30 minutos” em user story formal, com critérios de aceite ligados a retomada de contexto, próxima ação e DoD verificável.
A30: 2 | B30: PRODUTO | C30: 2.13 | D30: Exploração de problema (pré-PRD) | E30: enriquecido_via_plugin | F30: preenchido | G30: A exploração de problema pré-PRD é a parte mais desenvolvida de toda a Área 2, e existe em quatro artefatos. (a) DATA-ADHD-PM-001 — matriz GP-01…GP-11: para cada função de gestão de projetos, mapeia capacidade exigida → vulnerabilidade associada → classe de evidência (B/C/E) → impacto operacional → compensação sistêmica → decisão de produto, com fonte clínica e científica por linha. (b) Os 28 pontos reorganizados como cadeia progressiva “fundamento → problema humano → efeito → compensação → sistema → produto → validação”. (c) Framework de 694 perguntas com cobertura analítica: 248 RAW, 116 knowledge, 161 evidence candidates, 0 strict VERIFIED, 28 vínculos diretos candidatos, 484 vínculos temáticos, 182 perguntas sem evidência — do qual derivam as 22 decisões operacionais. (d) Mapa de pesquisa e prior art do ECO-03: o que já existe, whitespace provisório, guardrail e seis strings de busca sugeridas (A a F). O corpus separa explicitamente evidência publicada de inferência, com o invariante “original ≠ extração ≠ evidência ≠ decisão”. | H30: fato_interno | I30: alta | J30: TRANSVERSAL — ECO-01 e ECO-03 | K30: DOC-C07-010;DOC-C07-002;DOC-C07-003;DOC-C05-001;DOC-C07-009;DOC-C02-031;DOC-C01-005 | L30: DOC-C07-010 (3P+N): “Progresso — A hipótese central é parcialmente sustentada: há convergência forte para organização, planejamento, gestão temporal, atenção sustentada e conclusão; evidência moderada para memória prospectiva, flexibilidade e metacognição”; “Next 01 Transformar a matriz abaixo em requisitos funcionais e princípios de design verificáveis.” | DOC-C07-002 e DOC-C07-003: 11 linhas GP-01…GP-11 com colunas Função de gestão · Capacidade exigida · Vulnerabilidade associada · Evidência · Impacto operacional · Compensação sistêmica · Decisão de produto/design. | DOC-C07-009 (kpis): “questions_694: 694 · candidate_direct_links: 28 · thematic_links: 484 · no_evidence: 182 · operational_decisions: 22 · strict_verified: 0.” | DOC-C02-031 (item 3, WHITESPACE PROVISÓRIO): “perfil executivo individual → demanda cognitiva da tarefa → evento provável de falha → probabilidade/impacto → controle compensatório → evidência de execução.” | M30: 182 das 694 perguntas continuam sem evidência e o gate estrito registra 0 VERIFIED — a exploração é ampla, mas nenhum vínculo está formalmente verificado. | N30: Fechar o gate factual pelo menos das evidências que sustentam as 15 decisões PROD-01…PROD-15, hoje todas classificadas como DECISION_DERIVED_FROM_CANDIDATE_EVIDENCE.
A31: 3 | B31: ARQUITETURA & FULL STACK | C31: 3.1 | D31: Stack — Frontend | E31: formulario_original | F31: pendente
A32: 3 | B32: ARQUITETURA & FULL STACK | C32: 3.2 | D32: Stack — Backend | E32: formulario_original | F32: pendente
A33: 3 | B33: ARQUITETURA & FULL STACK | C33: 3.3 | D33: Banco de dados | E33: formulario_original | F33: pendente
A34: 3 | B34: ARQUITETURA & FULL STACK | C34: 3.4 | D34: Infraestrutura / hosting | E34: formulario_original | F34: pendente
A35: 3 | B35: ARQUITETURA & FULL STACK | C35: 3.5 | D35: Autenticação | E35: formulario_original | F35: pendente
A36: 3 | B36: ARQUITETURA & FULL STACK | C36: 3.6 | D36: Estrutura de repositório | E36: formulario_original | F36: pendente
A37: 3 | B37: ARQUITETURA & FULL STACK | C37: 3.7 | D37: Mapa de rotas principais | E37: formulario_original | F37: pendente
A38: 3 | B38: ARQUITETURA & FULL STACK | C38: 3.8 | D38: Decisão de arquitetura #1 (ADR) | E38: formulario_original | F38: pendente
A39: 3 | B39: ARQUITETURA & FULL STACK | C39: 3.9 | D39: Decisão de arquitetura #2 (ADR) | E39: formulario_original | F39: pendente
A40: 3 | B40: ARQUITETURA & FULL STACK | C40: 3.10 | D40: Trade-offs aceitos | E40: formulario_original | F40: pendente
A41: 3 | B41: ARQUITETURA & FULL STACK | C41: 3.11 | D41: Dívida técnica conhecida | E41: enriquecido_via_plugin | F41: pendente
A42: 4 | B42: IMPLEMENTAÇÃO | C42: 4.1 | D42: Modelo de dados / schema | E42: formulario_original | F42: pendente
... A71: 7 | B71: DOCUMENTAÇÃO FUNDACIONAL | C71: 7.6 | D71: Memória de trabalho para agentes | E71: enriquecido_via_plugin | F71: pendente
A72: 8 | B72: GESTÃO DE PROJETOS & PMBOK | C72: 8.1 | D72: Problema/oportunidade que justifica o projeto | E72: formulario_original | F72: parcial | G72: Gap entre intenção e execução: pessoas capazes — sobretudo adultos neurodivergentes e autônomos com múltiplos projetos — perdem tempo e energia organizando, priorizando, retomando contexto, lembrando dependências e administrando ferramentas, a ponto de a própria organização virar fonte de atrito. A oportunidade é ocupar a integração ainda pouco explorada entre neurodivergência, ergonomia cognitiva, human factors e gestão de riscos aplicada à execução. | H72: fato_interno | I72: alta | L72: §02 Problema e Mercado (Gap Intenção–Execução; Carga Executiva; Adultos Neurodivergentes) e §01 Síntese Estratégica (Integração Operacional). | M72: O próprio §03-T1 registra que a justificativa ainda precisa ser consolidada formalmente como problema central + oportunidade de mercado em documento único. | N72: Consolidar 8.1 em declaração formal de problema/oportunidade no Project Charter (PC-01).
A73: 8 | B73: GESTÃO DE PROJETOS & PMBOK | C73: 8.2 | D73: Sponsor / Patrocinador | E73: formulario_original | F73: preenchido | G73: Não há patrocinador formal definido neste estágio. A operação é conduzida por trabalhador solo independente, que acumula de fato a autoridade decisória. | H73: fato_interno | I73: alta | L73: §03-T1 · 01. Justificativa e Governança · Patrocínio · 8.2. | N73: Registrar formalmente a autoridade decisória do owner no Project Charter (PC-01/PC-02).
A74: 8 | B74: GESTÃO DE PROJETOS & PMBOK | C74: 8.3 | D74: Critério de sucesso principal | E74: formulario_original | F74: parcial | G74: Captar clientes para a Consultoria EXECUTAR enquanto as demais linhas do ecossistema são desenvolvidas, validadas e solidificadas — a consultoria funciona como principal mecanismo de geração de caixa e de mapa de calor das necessidades reais do público. | H74: decisao | I74: alta | L74: §03-T1 · Critério de Sucesso · 8.3 + 03. Objetivos Táticos T1 + 09. Indicadores de Sucesso · Receita. | M74: Falta meta numérica e prazo: quantos clientes, qual receita, até quando. O campo exige indicador objetivo com meta e prazo. | N74: Definir meta quantitativa de clientes/receita de consultoria e a data-alvo, ancorada no roadmap set/2026–jan/2027.
A75: 8 | B75: GESTÃO DE PROJETOS & PMBOK | C75: 8.4 | D75: Decisão Go/No-Go | E75: formulario_original | F75: lacuna | L75: §03-T1 · Gate de Decisão · 8.4 registra explicitamente TBD. | M75: Não existem critérios objetivos definidos para continuar, corrigir, suspender ou despriorizar cada linha do ecossistema. | N75: Definir critérios Go/No-Go por linha (app, blog, infoprodutos, físicos, consultoria, livro), ancorados no Gate de Revisão de 24/10/2026.
A76: 8 | B76: GESTÃO DE PROJETOS & PMBOK | C76: 8.5 | D76: Abordagem do projeto | E76: formulario_original | F76: lacuna | L76: §03-T1 · Modelo de Gestão · 8.5 registra TBD; restrição conhecida: operação predominantemente solo. | M76: Abordagem preditiva, ágil ou híbrida ainda não escolhida nem documentada. | N76: Selecionar e documentar a abordagem (o PMBOK 8 contempla preditiva, adaptativa e híbrida — PDF Fundamentos §3.6), coerente com operação solo e baixo overhead administrativo.
A77: 8 | B77: GESTÃO DE PROJETOS & PMBOK | C77: 8.6 | D77: Relato de status | E77: enriquecido_via_plugin | F77: lacuna | L77: §03-T1 · Status Executivo · 8.6 registra TBD; §10 Pontos em Aberto · Semáforo de Status confirma. | M77: Não há padrão Verde/Amarelo/Vermelho com critérios objetivos de prazo, risco, bloqueio e resultado. | N77: Formalizar regras do semáforo de status e a cadência de emissão do relato.
A78: 9 | B78: PLANEJAMENTO ESTRATÉGICO, TÁTICO E OPERACIONAL | C78: 9.1 | D78: Objetivo estratégico (12+ meses) | E78: formulario_original | F78: preenchido | G78: Tornar-se referência em Risco Cognitivo e temas relacionados por meio de um ecossistema consolidado de conteúdo, produtos, software, educação e serviços — construindo autoridade em território pouco explorado via pesquisa, publicação, aplicação prática, casos e participação de especialistas. | H78: decisao | I78: alta | L78: §03-T1 · 02. Objetivos Estratégicos · 9.1 + Autoridade + Ecossistema.
A79: 9 | B79: PLANEJAMENTO ESTRATÉGICO, TÁTICO E OPERACIONAL | C79: 9.2 | D79: Objetivo tático (trimestre/ciclo) | E79: formulario_original | F79: preenchido | G79: Ciclo atual (T1): Consultoria e Capitalização — priorizar consultoria para gerar receita, aprender com clientes e construir mapa de calor das necessidades reais. Sequência tática subsequente: T2 consolidação do App SAS-EXECUTAR; T3 produtos e infoprodutos; T4 comunidade e ONG. Em paralelo: livro sobre risco cognitivo e parcerias com especialistas no blog. | H79: inferencia | I79: media | L79: §03-T1 · 03. Objetivos Táticos · T1–T4, Autoridade Editorial e Parcerias. | M79: Mapeamento inferido: a base documental lista os objetivos táticos T1–T4 mas não os rotula explicitamente como o campo 9.2, nem fixa o horizonte trimestral de cada um. | N79: Confirmar com o owner qual objetivo tático corresponde ao trimestre corrente e sua data de fechamento.
A80: 9 | B80: PLANEJAMENTO ESTRATÉGICO, TÁTICO E OPERACIONAL | C80: 9.3 | D80: Prioridade operacional da semana | E80: formulario_original | F80: preenchido | G80: Lançar o blog, configurar as contas, definir a linha editorial e ativar o ecossistema editorial antes do lançamento público do app beta — concluir a fundação editorial e os canais de aquisição antes de avançar para o EXECUTAR beta. | H80: decisao | I80: alta | L80: §03-T1 · 04. Prioridade Operacional · 9.3 + Sequência Blog → App; confirmado pelo roadmap (blog 07/09/2026, app beta 14/09/2026).
A81: 9 | B81: PLANEJAMENTO ESTRATÉGICO, TÁTICO E OPERACIONAL | C81: 9.4 | D81: Dependência entre horizontes | E81: formulario_original | F81: parcial | G81: Cadeia material já descrita na base: Consultoria → Capitalização (caixa enquanto produtos escaláveis amadurecem); Consultoria → Necessidades (clientes geram evidência de dores recorrentes); Necessidades → App (aprendizado orienta funcionalidades do SAS-EXECUTAR); Conteúdo → Produtos (audiência sustenta distribuição e validação); Produtos → Comunidade (comunidade/ONG só após consolidação de autoridade e operação). | H81: fato_interno | I81: media | L81: §03-T1 · 05. Dependências Estratégicas (cinco pares de dependência declarados). | M81: CONFLITO REGISTRADO: a linha 9.4 do §03-T1 marca "TBD — deve ser formalizada a cadeia de dependências", mas o mesmo bloco §05 já enumera cinco dependências materiais. Falta a formalização com predecessores, sucessores, bloqueios e gates explícitos. | N81: Formalizar o grafo de dependências entre horizontes com gates verificáveis (resolve também MASTER-04).
A82: 9 | B82: PLANEJAMENTO ESTRATÉGICO, TÁTICO E OPERACIONAL | C82: 9.5 | D82: Capacidade de recursos | E82: enriquecido_via_plugin | F82: preenchido | G82: Não aplicável no modelo atual: não há planejamento formal de contratação ou ampliação imediata de equipe. Restrição vigente: operação predominantemente individual, com capacidade limitada de execução simultânea e necessidade de limite de WIP para evitar dispersão. | H82: fato_interno | I82: alta | L82: §03-T1 · 06. Recursos e Capacidade · 9.5 + Operação Solo + Limite de WIP. | N82: Definir o número máximo de iniciativas simultâneas (limite de WIP numérico) — hoje é diretriz qualitativa.
A83: 10 | B83: ROADMAP, CRONOGRAMA, CICLOS E BACKLOG | C83: 10.1 | D83: Marco de médio prazo #1 | E83: formulario_original | F83: lacuna | L83: §03-T1 · 07. Marcos e Roadmap · 10.1 registra TBD. | M83: CONFLITO REGISTRADO: 10.1 está marcado TBD, mas o §05-Cronograma traz marcos datados (blog 07/09/2026; app beta 14/09/2026; serviços 21/09/2026; infoprodutos e físicos 28/09/2026; curso 19/10/2026; Gate de Revisão 24/10/2026; manuscrito 12/12/2026; livro 10/01/2027). Falta eleger qual deles é o marco de médio prazo #1 verificável. | N83: Eleger o marco de médio prazo #1 — candidato mais forte: Gate de Revisão de 24/10/2026, único ponto do roadmap que já é definido como decisão baseada em dados acumulados.
A84: 10 | B84: ROADMAP, CRONOGRAMA, CICLOS E BACKLOG | C84: 10.2 | D84: Ciclo semanal atual | E84: formulario_original | F84: preenchido | G84: Ciclo Zero — dedicado à preparação, estruturação e ativação inicial do ecossistema: canais, conteúdo, contas, processos, ativos e preparação dos primeiros lançamentos. | H84: fato_interno | I84: alta | L84: §03-T1 · 07. Marcos e Roadmap · 10.2 + 08. Modelo Operacional · Ciclo Zero. | M84: O formulário original oferece as opções Editorial/Desenvolvimento/Governança; "Ciclo Zero" é um estado anterior a essas três fases e não estava previsto na lista de opções. | N84: Ampliar o domínio de valores de 10.2 para incluir Ciclo Zero (fundação) além de Editorial, Desenvolvimento e Governança.
A85: 10 | B85: ROADMAP, CRONOGRAMA, CICLOS E BACKLOG | C85: 10.3 | D85: Item de backlog crítico | E85: formulario_original | F85: lacuna | L85: §03-T1 · Backlog · 10.3 registra TBD; §10 Pontos em Aberto · Item Crítico confirma. | M85: Não foi identificado o único item cuja não execução bloqueia o próximo marco. Candidato derivável de 9.3: o lançamento do blog em 07/09/2026 (predecessor declarado do app beta). | N85: Confirmar com o owner o item de backlog crítico único e amarrá-lo ao marco de 10.1.
A86: 10 | B86: ROADMAP, CRONOGRAMA, CICLOS E BACKLOG | C86: 10.4 | D86: Cadência de revisão | E86: formulario_original | F86: preenchido | G86: Revisão quinzenal: a cada 15 dias estratégia, backlog e roadmap são confrontados com dados reais de execução e mercado. Responsável: o owner do projeto (operação solo). | H86: decisao | I86: alta | L86: §03-T1 · 07. Marcos e Roadmap · 10.4 + 08. Modelo Operacional · Revisão Quinzenal.
A87: 10 | B87: ROADMAP, CRONOGRAMA, CICLOS E BACKLOG | C87: 10.5 | D87: Planejamento de sprint | E87: enriquecido_via_plugin | F87: lacuna | L87: §03-T1 · Sprint · 10.5 registra TBD; §10 Pontos em Aberto · Capacidade confirma. | M87: Não existe mecanismo para selecionar trabalho por prioridade, dependência e capacidade real. Restrição conhecida (9.5): operação solo exige regra simples e limite de WIP. | N87: Criar regra mínima de planejamento que limite compromissos do ciclo à capacidade real disponível.
A88: 11 | B88: EDITORIAL, CAMPANHAS E CONTEÚDO | C88: 11.1 | D88: Linha editorial | E88: formulario_original | F88: pendente
A89: 11 | B89: EDITORIAL, CAMPANHAS E CONTEÚDO | C89: 11.2 | D89: Calendário de publicação | E89: formulario_original | F89: pendente
A90: 11 | B90: EDITORIAL, CAMPANHAS E CONTEÚDO | C90: 11.3 | D90: Campanha ativa | E90: formulario_original | F90: pendente
A91: 11 | B91: EDITORIAL, CAMPANHAS E CONTEÚDO | C91: 11.4 | D91: Trilha de conteúdo | E91: formulario_original | F91: pendente
A92: 11 | B92: EDITORIAL, CAMPANHAS E CONTEÚDO | C92: 11.5 | D92: Banco de conteúdo | E92: enriquecido_via_plugin | F92: pendente
A93: 11 | B93: EDITORIAL, CAMPANHAS E CONTEÚDO | C93: 11.6 | D93: Identidade visual e voz de marca | E93: enriquecido_via_plugin | F93: pendente
A94: 11 | B94: EDITORIAL, CAMPANHAS E CONTEÚDO | C94: 11.7 | D94: Design system e componentes | E94: enriquecido_via_plugin | F94: pendente
A95: 11 | B95: EDITORIAL, CAMPANHAS E CONTEÚDO | C95: 11.8 | D95: Revisão de acessibilidade | E95: enriquecido_via_plugin | F95: pendente
A96: 11 | B96: EDITORIAL, CAMPANHAS E CONTEÚDO | C96: 11.9 | D96: Pesquisa de usuário para conteúdo | E96: enriquecido_via_plugin | F96: pendente
A97: 11 | B97: EDITORIAL, CAMPANHAS E CONTEÚDO | C97: 11.10 | D97: SEO e performance de conteúdo | E97: enriquecido_via_plugin | F97: pendente
A98: 12 | B98: STAKEHOLDERS | C98: 12.1 | D98: Stakeholder principal | E98: formulario_original | F98: pendente
A99: 12 | B99: STAKEHOLDERS | C99: 12.2 | D99: Forma de comunicação | E99: formulario_original | F99: pendente
... A123: 17 | B123: PROMPT ENGINEERING & COMANDOS | C123: 17.4 | D123: Sincronização de tarefas e memória | E123: enriquecido_via_plugin | F123: pendente

Sheet 03_FRAMEWORKS
A1: framework | B1: dimension | C1: entity | D1: business_model | E1: channel | F1: claim | G1: evidence | H1: evidence_record_ids | I1: evidence_strength | J1: confidence | K1: status | L1: impact | M1: urgency | N1: recommendation
A2: SA-01 | B2: legal_regulatory | C2: ECO-01 | D2: software | E2: app | F2: Posicionar o app como diagnostico ou tratamento de TDAH pode acionar o regime de Software como Dispositivo Medico da Anvisa. | G2: Fonte SRC-RG8-ANVISA-SAMD no dashboard: 'RDC 657/2022 - Software como Dispositivo Medico... Enquadramento SaMD depende da indicacao e funcao; software que diagnostica/trata pode entrar no regime regulatorio.' | H2: DOC-C07-009 | I2: strong | J2: 0.9 | K2: fact | L2: high | M2: high | N2: Manter POSITION-01 e CLAIM-01 como travas de copy e submeter o texto final de lancamento a revisao juridica antes de 07/09.
A3: SA-01 | B3: legal_regulatory | C3: ECO-01 | D3: software | E3: app | F3: Coletar diagnostico de TDAH no onboarding transformaria a base em dado pessoal sensivel sob a LGPD, sem necessidade funcional. | G3: Fonte SRC-RG8-ANPD-LGPD: 'Dado referente a saude e dado pessoal sensivel; minimizacao favorece nao coletar diagnostico quando desnecessario.' Decisao ICP-01: 'diagnostico nao define o ICP comercial inicial'. | H3: DOC-C07-009 | I3: strong | J3: 0.9 | K3: fact | L3: high | M3: medium | N3: Manter diagnostico como variavel opcional pos-ativacao, com base legal e finalidade declaradas, nunca como criterio de entrada.
A4: SA-01 | B4: legal_regulatory | C4: ECO-02 | D4: content_community | E4: owned_web | F4: A politica de claims proibe hoje seis formulacoes clinicas no conteudo editorial e comercial. | G4: claims_policy.prohibited_now: 'Reduz sintomas de TDAH', 'Melhora funcao executiva clinicamente', 'Trata TDAH', 'Diagnostica ou identifica TDAH', 'Substitui terapia, tratamento ou medicacao', 'Cientificamente comprovado para TDAH'. | H4: DOC-C07-009 | I4: strong | J4: 0.9 | K4: fact | L4: high | M4: high | N4: Transformar a lista em checklist de QA editorial obrigatorio antes de publicar cada peca (PECA-001/002/003).
A5: SA-01 | B5: ethical | C5: ECO-03 | D5: digital_product | F5: Qualquer estudo proprio de eficacia com participantes humanos fica sujeito a Resolucao CNS 466/2012. | G5: Fonte SRC-RG8-CNS-466: 'Resolucao CNS 466/2012'; decisao EFFICACY-01 exige 'protocolo proprio, diagnostico confirmado, instrumento validado, comparador e revisao etica aplicavel'. | H5: DOC-C07-009;DOC-C02-015 | I5: strong | J5: 0.85 | K5: fact | L5: medium | M5: medium | N5: Separar o piloto exploratorio de 10-20 participantes (validacao de framework) de um eventual estudo clinico, que exigira CEP/CONEP.
A6: SA-01 | B6: social | C6: ECO-01 | D6: software | E6: app | F6: O Brasil tinha 26,1 milhoes de trabalhadores por conta propria em 2025, contexto do ICP de profissionais independentes. | G6: Finding BRA-MKT-01, fonte SRC-RG8-IBGE-SELFEMPLOYED-2025 (PNAD Continua): '26,1 milhoes de trabalhadores por conta propria em 2025'. Uso declarado: 'Contexto de mercado; nao equivale a TAM do EXECUTAR.' | H6: DOC-C07-009 | I6: strong | J6: 0.9 | K6: fact | L6: medium | M6: low | N6: Usar como contexto de mercado; nao converter em TAM sem taxa de adocao e disposicao a pagar observadas.
A7: SA-01 | B7: technological | C7: ECO-01 | D7: software | E7: app | F7: O acesso a internet no Brasil e majoritariamente movel, sustentando arquitetura mobile-first. | G7: Finding BRA-MOBILE-01 (IBGE 2025): '90,5% da populacao de 10+ usava internet e 98,7% dos usuarios acessavam por celular'. Uso: 'Sustenta estrategia mobile-first; nao prova preferencia especifica do ICP.' | H7: DOC-C07-009 | I7: strong | J7: 0.85 | K7: fact | L7: medium | M7: medium | N7: Manter o teste de rota em celular como criterio de aceite das paginas (ja previsto em PAG-001/002/003).
A8: SA-01 | B8: economic | C8: ECO-03 | D8: digital_product | F8: Ha estimativas internacionais de carga economica excedente associada ao TDAH adulto que sustentam o problema, mas nao sao perda individual. | G8: RC-003: 'US$ 14.092 de custo excedente por adulto/ano'; RC-004: 'EUR 15.652 por adulto diagnosticado/ano'; guardrail: 'valor e carga economica/social media, nao perda literal individual'. | H8: DOC-C02-021;DOC-C02-032;DOC-C02-043 | I8: strong | J8: 0.85 | K8: fact | L8: medium | M8: medium | N8: Usar como lastro do problema no artigo fundador sempre com a ressalva metodologica ja escrita na propria fonte.
A9: SA-01 | B9: social | C9: ECO-02 | D9: content_community | E9: owned_web | F9: Evidencia brasileira populacional associa rastreio positivo de TDAH a maior desemprego, com n=2.297 e 4,59% de rastreio positivo. | G9: RC-SRC-004 (Mattos et al., 2024, J Atten Disord): 'n=2.297; 4,59% de TDAH sintomatico (IC95% 3,56-5,44)'; limitacao registrada: 'ASRS-6 e screener; nao apresentar 4,59% como prevalencia diagnostica nacional'. | H9: DOC-C02-032;DOC-C02-021 | I9: strong | J9: 0.9 | K9: fact | L9: medium | M9: medium | N9: Citar como principal evidencia brasileira e reproduzir a limitacao no proprio corpo do artigo.
A10: SA-01 | B10: social | C10: ECO-02 | D10: content_community | E10: owned_web | F10: Amostra brasileira de empreendedores mostrou 27,4% com rastreio positivo, sem associacao significativa com lucro. | G10: RC-006: 'Em amostra selecionada de 259 empreendedores, 71 (27,4%) preencheram criterios'; DOC-C02-042: 'maior risk-taking, menor proatividade e nenhuma associacao significativa com lucro'; guardrail: nao generalizar. | H10: DOC-C02-021;DOC-C02-042;DOC-C02-032 | I10: moderate | J10: 0.8 | K10: fact | L10: medium | M10: low | N10: Usar no eixo empreendedorismo/trabalho autonomo apenas como sinal, nunca como prevalencia do segmento.
A11: SA-01 | B11: social | C11: ECO-02 | D11: content_community | E11: owned_web | F11: Ha evidencia internacional citada de 17,4% de demissoes em adultos com TDAH contra 3,7% em controles. | G11: RC-007: 'Estudo internacional citado reportou 17,4% de demissao em adultos com TDAH'; nota: 'A diferenca e aproximadamente 4,7 vezes, mas nao e dado brasileiro'. | H11: DOC-C02-021;DOC-C02-043 | I11: moderate | J11: 0.75 | K11: fact | L11: medium | M11: low | N11: Rotular explicitamente como dado internacional ao usar em peca brasileira.
A12: SA-01 | B12: competitive_political | C12: ECO-03 | D12: digital_product | F12: A APM publicou em 26/08/2026 a formulacao de que projetos tambem podem falhar cognitivamente, criando adjacencia temporal muito proxima a tese. | G12: DOC-C02-042 (Alerta): 'Sarah Gardner... publicou na APM em 26/08/2026 a formulacao de que projetos tambem podem falhar cognitivamente, embora seu foco seja IA, julgamento e governanca'; RC-TERM-009 marca STATUS SINAL_RECENTE. | H12: DOC-C02-042;DOC-C02-030;DOC-C02-022 | I12: strong | J12: 0.85 | K12: fact | L12: high | M12: high | N12: Acelerar o registro publico da formulacao propria (artigo fundador datado + white paper) para preservar anterioridade documentada.
A13: SA-01 | B13: economic | C13: ECO-02 | D13: content_community | E13: owned_web | F13: O material interno cita R$ 3.498 como custo de avaliacao neuropsicologica, tratado como barreira economica de acesso ao diagnostico. | G13: QT-0143: 'Custo citado de avaliacao neuropsicologica: 3498.0 R$'; observacao da propria fonte: 'A imagem cita a referencia por numero, mas a lista bibliografica [1]-[8] nao esta no material anexado'. | H13: DOC-C07-007;DOC-C07-009 | I13: weak | J13: 0.45 | K13: fact | L13: low | M13: low | N13: Nao publicar esse numero antes de recuperar a referencia primaria [6]; hoje ele e transcricao de imagem sem fonte resolvida.
A14: SA-01 | B14: environmental | C14: ECO-01 | D14: software | F14: Nao ha analise PESTEL formal por unidade no acervo; os fatores existem dispersos em fontes de evidencia e decisao. | G14: Nenhum documento lido apresenta secao PESTEL; os fatores regulatorios estao no dashboard de sintese e os sociais/economicos nas bases de evidencia. | H14: DOC-C07-009;DOC-C02-032 | I14: none | J14: 0.6 | K14: gap | L14: low | M14: low | N14: Consolidar um PESTEL de uma pagina por unidade a partir das fontes ja catalogadas, sem pesquisa nova.
A15: SA-02 | B15: rivalry | C15: ECO-01 | D15: software | E15: app | F15: Os concorrentes diretos citados sao ferramentas horizontais de produtividade com limitacoes documentadas para o publico-alvo. | G15: QL-000053: 'Trello... necessitando de plug-ins adicionais para rastrear progresso'; QL-000054: 'Todoist... limitado para iniciar tarefas e sem recursos de regulacao emocional'; QT-000172: '30,0% dos usuarios com TDAH consideram o Notion dificil de configurar/usar'. | H15: DOC-C07-007;DOC-C07-009 | I15: moderate | J15: 0.7 | K15: fact | L15: high | M15: high | N15: Ancorar o posicionamento na lacuna de iniciacao e retomada, nao em paridade de features com Notion/Trello/Todoist.
A16: SA-02 | B16: rivalry | C16: ECO-01 | D16: software | E16: app | F16: Existem concorrentes com evidencia clinica ou aprovacao regulatoria que o EXECUTAR nao pode igualar hoje. | G16: QT-000177: 'Eficacia de app baseado em TCC (estudo aberto do app Inflow)'; QT-000178/179: 'videogame terapeutico aprovado por agencia regulatoria... p<0.0001... 72,5% melhoria na qualidade de vida (STARS-ADHD-Adult)'. | H16: DOC-C07-007;DOC-C07-009 | I16: moderate | J16: 0.75 | K16: fact | L16: high | M16: high | N16: Competir por eficacia funcional (time-to-next-action, resume latency), terreno onde nao ha comparador regulado, e nao por desfecho clinico.
A17: SA-02 | B17: supplier_power | C17: ECO-01 | D17: software | E17: app | F17: A operacao depende de fornecedores externos criticos cuja falha bloqueia o lancamento. | G17: DOC-C06-001 lista dependencias externas Amazon e Hotmart iniciadas em D1 e reserva de 12h para 'problema de CMS/Hotmart, formulario, link'; DOC-C02-017 fixa Vercel + Payload + PostgreSQL/Neon + Vercel Blob. | H17: DOC-C06-001;DOC-C02-017 | I17: moderate | J17: 0.65 | K17: inference | L17: medium | M17: medium | N17: Registrar Amazon Associados, Hotmart, Vercel e Neon como riscos de fornecedor com plano B explicito no mapa de dependencias.
A18: SA-02 | B18: buyer_power | C18: ECO-01 | D18: software | E18: app | F18: O ICP escolhido controla ou influencia a propria compra, o que elimina ciclo de aprovacao mas expoe a decisao a preco. | G18: ICP comercial no dashboard: 'Profissional independente/solo brasileiro... e controla/influencia a propria compra'; faixa de teste R$29,90/49,90/79,90 com 'preco canonico ainda nao existe'. | H18: DOC-C07-009 | I18: strong | J18: 0.8 | K18: fact | L18: medium | M18: medium | N18: Rodar PRICE-01 como experimento com coorte real antes de fixar preco de tabela na pagina de lancamento.
A19: SA-02 | B19: substitutes | C19: ECO-01 | D19: software | E19: app | F19: O substituto mais provavel e o sistema analogico ou improvisado que o proprio usuario ja mantem. | G19: DOC-C05-001 descreve a categoria como sistema 'com uso digital minimo e integracao analogica' e DOC-C11-008 mostra 'o mesmo projeto no digital e no material fisico'; QL-0022 registra necessidade de 'externalizacao de funcoes executivas'. | H19: DOC-C05-001;DOC-C11-008;DOC-C07-007 | I19: moderate | J19: 0.6 | K19: inference | L19: medium | M19: low | N19: Tratar papel/Mapa-OS como complemento monetizavel (produto fisico) em vez de concorrente a ser combatido.
A20: SA-02 | B20: new_entrants | C20: ECO-01 | D20: software | F20: Nao ha no acervo qualquer analise de barreiras a entrada para a categoria do app. | G20: Nenhum dos documentos lidos discute custo de entrada, efeitos de rede ou defensabilidade tecnica frente a novos entrantes. | I20: none | J20: 0.6 | K20: gap | L20: medium | M20: low | N20: Definir explicitamente qual e o ativo defensavel (base de evidencias governada, motor de rota ou dados de execucao) antes do lancamento comercial.
A21: SA-02 | B21: rivalry | C21: ECO-02 | D21: content_community | E21: owned_web | F21: O setor de conteudo sobre TDAH e descrito como segmentado em quatro categorias competitivas. | G21: QL-0017: 'O setor e segmentado em midia/autoridade medica, infoprodutores, comercio eletronico de nicho e instituicoes/clinicas.' | H21: DOC-C07-007;DOC-C07-009 | I21: moderate | J21: 0.7 | K21: fact | L21: medium | M21: medium | N21: Escolher explicitamente contra qual categoria o Risco Cognitivo compete; hoje o material sugere uma quinta posicao (autor-investigador) nao mapeada.
A22: SA-02 | B22: rivalry | C22: ECO-03 | D22: digital_product | F22: O framework compete com corpos metodologicos ja consolidados, e a fonte reconhece isso. | G22: RC-TERM-007/008 classificam 'Cognitive Risk' e 'Managing Cognitive Risk' como ANTERIORIDADE; RC-012: 'PMI estrutura multiplos dominios'; RC-TERM-011/012/013 marcam ergonomia cognitiva, fatores humanos e neuroergonomia como adjacentes fortes. | H22: DOC-C02-030;DOC-C02-022;DOC-C02-031 | I22: strong | J22: 0.85 | K22: fact | L22: high | M22: high | N22: Manter o guardrail de nao reivindicar o termo e posicionar a contribuicao como integracao especifica, conforme RC-030.
A23: SA-02 | B23: rivalry | C23: ECO-07 | D23: professional_service | E23: direct_sales | F23: Nao ha mapeamento de concorrentes para o Estudio no acervo lido. | G23: DOC-C09-006, DOC-C12-006 e DOC-C12-007 definem oferta, pagina e formulario, mas nenhum documento nomeia concorrentes de automacao/consultoria. | H23: DOC-C09-006;DOC-C12-006;DOC-C12-007 | I23: none | J23: 0.7 | K23: gap | L23: medium | M23: medium | N23: Levantar 5 comparaveis de consultoria de automacao no Brasil antes de fixar o preco de R$700 como diferencial.
A24: SA-03A | B24: category_definition | C24: ECO-01 | D24: software | E24: app | F24: A categoria declarada do produto e sistema de gestao de processos, projetos, tarefas e workflows orientado a execucao. | G24: DOC-C05-001, item 03 do index: 'Sistema de gestao de processos, projetos, tarefas e workflows, orientado a execucao, adaptado as vulnerabilidades do usuario, com uso digital minimo e integracao analogica'. | H24: DOC-C05-001 | I24: strong | J24: 0.9 | K24: fact | L24: high | M24: medium | N24: Usar essa definicao como texto canonico da pagina inicial em vez de 'app de produtividade'.
A25: SA-03A | B25: market_boundaries | C25: ECO-03 | D25: digital_product | F25: A tese explora a fronteira entre tres mercados de conteudo hoje separados. | G25: DOC-C01-005: 'Ha tres mercados de conteudo que normalmente ficam separados... neurodivergencia... produtividade pessoal... gestao de riscos'; a proposta e 'colocar uma ponte no meio'. | H25: DOC-C01-005;DOC-C03-002 | I25: strong | J25: 0.85 | K25: fact | L25: high | M25: medium | N25: Descrever o territorio como interseccao, o que tambem explica por que nao ha benchmark direto de tamanho de mercado.
A26: SA-03A | B26: growth | C26: ECO-02 | D26: content_community | E26: owned_web | F26: O material interno registra crescimento de 576% em buscas por TDAH em 5 anos e CAGR de 25-30% (2022-2025) caindo para 10-12% (2025-2030). | G26: QT-0137 '576,0% / 5 anos'; QT-0138 '25,0-30,0% ao ano / 2022-2025'; QT-0139 '10,0-12,0% ao ano / 2025-2030'. Todos com 'base amostral: Nao informada na imagem' e 'Requer validacao na referencia original'. | H26: DOC-C07-007;DOC-C07-009 | I26: weak | J26: 0.45 | K26: fact | L26: medium | M26: medium | N26: Nao publicar esses numeros; recuperar a referencia [4] ou substituir por serie primaria antes de qualquer uso externo.
A27: SA-03B | B27: tam | C27: ECO-01 | D27: software | F27: O material interno afirma TAM estimado de R$ 5,07 bilhoes (Brasil), sem metodologia recuperavel. | G27: QT-0131: 'TAM estimado 5070000000.0 R$', geografia Brasil, fonte 'Documento Final Unificado: Sintese Estrategica de Neuroexecucao Aplicada', arquivo IMG_0537.HEIC, 'base amostral: Nao informada na imagem', 'Requer validacao na referencia original'. | H27: DOC-C07-007;DOC-C07-009 | I27: weak | J27: 0.35 | K27: fact | L27: high | M27: high | N27: Tratar como numero herdado nao auditavel; nao usar em deck, investidor ou copy ate existir memoria de calculo.
A28: SA-03B | B28: tam_methodology | C28: ECO-01 | D28: software | F28: Nao ha base nem metodologia identificavel para produzir um TAM defensavel do EXECUTAR neste acervo. | G28: Falta: universo de compradores definido, taxa de adocao, preco medio validado e fonte bibliografica ([1]-[8] ausente). O proprio dashboard adverte que 26,1 mi de trabalhadores por conta propria 'Nao equivale a TAM do EXECUTAR'. | H28: DOC-C07-009;DOC-C07-007 | I28: none | J28: 0.85 | K28: gap | L28: high | M28: high | N28: Para fechar: fixar universo (ex.: conta propria com uso de ferramenta digital), taxa de adocao observada e ARPU validado por PRICE-01; so entao calcular.
A29: SA-03B | B29: tam_conflict | C29: ECO-01 | D29: software | F29: Ha duas posicoes incompativeis sobre dimensionamento de mercado dentro do mesmo acervo. | G29: Versao A (QT-0131/132/133): TAM R$5,07 bi, SAM R$357,3 mi, SOM R$3,26 mi em 3 anos. Versao B (dashboard V3 Final): 'Contexto de mercado. Nao equivale a TAM do EXECUTAR' e 'Strict VERIFIED 0'. | H29: DOC-C07-007;DOC-C07-009 | I29: moderate | J29: 0.85 | K29: conflict | L29: high | M29: high | N29: Registrar formalmente que a V3 supera a estimativa herdada e marcar QT-0131/132/133 como legado nao verificado no proprio warehouse.
A30: SA-03C | B30: sam | C30: ECO-01 | D30: software | F30: O material interno afirma SAM de R$ 357,3 milhoes e publico potencial de 6 milhoes de pessoas, sem metodologia recuperavel. | G30: QT-0132: 'SAM estimado 357300000.0 R$'; QT-0134: 'Publico potencial do SAM 6000000.0 pessoas'. Mesma limitacao: 'A imagem cita a referencia por numero, mas a lista bibliografica [1]-[8] nao esta no material anexado'. | H30: DOC-C07-007;DOC-C07-009 | I30: weak | J30: 0.35 | K30: fact | L30: high | M30: high | N30: Recalcular SAM a partir do recorte ICP-01 (independente/solo, 25-44, multiprojeto) quando houver taxa de qualificacao observada.
A31: SA-03D | B31: som | C31: ECO-01 | D31: software | F31: O material interno projeta SOM de R$ 3,26 milhoes em 3 anos, com meta de 500.000 inscritos e 1% de conversao anual. | G31: QT-0133 'SOM projetado para tres anos 3260000.0 R$'; QT-0135 'Meta de inscritos 500000.0 / 3 anos'; QT-0136 'Conversao anual projetada 1,0%'. | H31: DOC-C07-007;DOC-C07-009 | I31: weak | J31: 0.35 | K31: fact | L31: high | M31: high | N31: Confrontar a meta de 500 mil inscritos com o objetivo SMART vigente, que proibe 'metas arbitrarias de seguidores ou leads sem baseline'.
A32: SA-03D | B32: som_conflict | C32: ECO-02 | D32: content_community | E32: social | F32: A meta herdada de 500.000 inscritos contradiz a regra vigente de nao fixar metas sem baseline. | G32: QT-0135: 'Meta de inscritos 500000.0'. DOC-C02-043 (Objetivo SMART): 'Nao estabelecer ainda metas arbitrarias de seguidores ou leads sem baseline.' | H32: DOC-C07-007;DOC-C02-043 | I32: moderate | J32: 0.8 | K32: conflict | L32: medium | M32: medium | N32: Aposentar a meta de 500 mil ate a campanha D1-D14 gerar baseline de visualizacoes, retencao, inscricoes e downloads.
A33: SA-03B | B33: tam | C33: ECO-02 | D33: content_community | F33: Nao existe dimensionamento de mercado especifico para a unidade editorial. | G33: Os unicos numeros de mercado no acervo (QT-0131/132/133) referem-se ao projeto de produto/neuroexecucao, nao a receita editorial; nenhum documento estima receita de publicidade, newsletter ou patrocinio. | H33: DOC-C07-007 | I33: none | J33: 0.8 | K33: gap | L33: medium | M33: low | N33: Se o blog for monetizar, dimensionar por RPM x sessoes projetadas apos a campanha inaugural, nao antes.
A34: SA-03B | B34: tam | C34: ECO-07 | D34: professional_service | E34: direct_sales | F34: Nao existe TAM/SAM/SOM para os servicos; ha apenas preco e capacidade. | G34: DOC-C05-001 registra 'Um projeto, uma entrega, uma semana: R$ 700,00' e 'Limite de um cliente por semana', mas nenhum documento estima demanda ou numero de compradores potenciais. | H34: DOC-C05-001 | I34: none | J34: 0.85 | K34: gap | L34: medium | M34: medium | N34: Para servico com capacidade travada em 1 cliente/semana, o dimensionamento relevante e fila de demanda qualificada, nao TAM.
A35: SA-04A | B35: segmentation_axis | C35: ECO-01 | D35: software | E35: app | F35: A segmentacao adotada e comportamental, nao clinica. | G35: Decisao ICP-01: 'Iniciar testes por profissionais independentes multiprojeto, sem exigir diagnostico de TDAH'; 'O que nao e criterio de entrada: Diagnostico de TDAH'. | H35: DOC-C07-009 | I35: strong | J35: 0.9 | K35: fact | L35: high | M35: high | N35: Instrumentar a captacao para medir comportamento (perda de contexto, dificuldade de proxima acao) e nao autodeclaracao de diagnostico.
A36: SA-04A | B36: segment_definition | C36: ECO-02 | D36: content_community | E36: owned_web | F36: O material editorial define publico prioritario como empreendedores e profissionais liberais adultos com TDAH. | G36: QL-0018: 'Empreendedores e profissionais liberais adultos com TDAH sao definidos como publico prioritario'; QT-0140/0141 fixam faixa etaria 25-44 anos. | H36: DOC-C07-007;DOC-C07-009 | I36: moderate | J36: 0.75 | K36: fact | L36: medium | M36: medium | N36: Alinhar com ICP-01: o editorial segmenta por diagnostico, o produto segmenta por comportamento; a diferenca precisa ser deliberada, nao acidental.
A37: SA-04A | B37: segment_conflict | C37: ECO-01 | D37: software | F37: Ha tensao entre a segmentacao clinica do editorial e a segmentacao comportamental do produto. | G37: Editorial (QL-0018): publico e 'adultos com TDAH'. Produto (ICP-01): 'diagnostico nao define o ICP comercial inicial'. As duas convivem no mesmo funil de lancamento de 07/09. | H37: DOC-C07-007;DOC-C07-009;DOC-C12-005 | I37: moderate | J37: 0.75 | K37: conflict | L37: high | M37: high | N37: Decidir e registrar como o trafego editorial (TDAH) converte para uma oferta que nao usa TDAH como criterio, evitando promessa implicita de tratamento.
A38: SA-04A | B38: segment_definition | C38: ECO-03 | D38: digital_product | F38: O framework define dois publicos distintos: leitores interessados e especialistas como critica externa. | G38: DOC-C02-039 (BMC): 'Leitores interessados em funcoes executivas, neurodivergencia, trabalho, projetos e risco; especialistas entram como critica externa, nao como endosso.' | H38: DOC-C02-039;DOC-C02-042 | I38: strong | J38: 0.85 | K38: fact | L38: medium | M38: medium | N38: Manter a separacao no material: endosso de especialista nao pode virar prova social antes da revisao critica.
A39: SA-04A | B39: segment_definition | C39: ECO-07 | D39: professional_service | E39: direct_sales | F39: Nao ha definicao de segmento para os servicos alem de tres familias nao especificadas no acervo lido. | G39: DOC-C09-006 lista como pendencia 'tres familias de servico' e 'condicao de preco inicial'; DOC-C02-004 registra CONS-01/CONS-02 como CONCLUIDO, mas nenhum documento lido nomeia as tres familias. | H39: DOC-C09-006;DOC-C02-004;DOC-C12-006 | I39: none | J39: 0.75 | K39: gap | L39: high | M39: high | N39: Recuperar ou redigir a especificacao das tres familias de servico antes de publicar PAG-002-SERVICOS.
A40: SA-04B | B40: icp | C40: ECO-01 | D40: software | E40: app | F40: O ICP comercial a testar esta escrito de forma operacional e falseavel. | G40: Dashboard: 'Profissional independente/solo brasileiro, aproximadamente 25-44 anos, multiprojeto, que perde contexto, tem dificuldade recorrente para escolher proxima acao, ja tentou ferramentas de produtividade e controla/influencia a propria compra.' | H40: DOC-C07-009 | I40: strong | J40: 0.9 | K40: fact | L40: high | M40: high | N40: Converter cada clausula do ICP em pergunta de triagem do formulario de captacao FORM-002.
A41: SA-04B | B41: icp_validation | C41: ECO-01 | D41: software | E41: app | F41: O ICP permanece hipotese: nao ha validacao com clientes reais. | G41: gaps[0]: 'ICP comercial - HIPOTESE FORTE / TESTAVEL - closed: false - remaining: Validacao com clientes reais'; finding ICP-HYP-01 tem epistemic_class E e status HYPOTHESIS. | H41: DOC-C07-009 | I41: strong | J41: 0.9 | K41: fact | L41: high | M41: high | N41: Recrutar coorte comportamental no lancamento de 07/09 e medir ativacao, recorrencia, pagamento e renovacao (next_validation de ICP-01).
A42: SA-04B | B42: icp | C42: ECO-07 | D42: professional_service | E42: direct_sales | F42: O ICP do Estudio esta implicito no formulario de entrada, nao declarado. | G42: DOC-C12-003 pergunta 'como trabalha hoje; principal atrito; ferramentas atuais; resultado desejado; ... prazo desejado; faixa de investimento' - e um instrumento de qualificacao, mas nenhum documento declara o perfil-alvo. | H42: DOC-C12-003;DOC-C09-006 | I42: moderate | J42: 0.7 | K42: gap | L42: medium | M42: medium | N42: Derivar o ICP do Estudio a partir das respostas das primeiras semanas e registra-lo antes de escalar a oferta.
A43: SA-04C | B43: job_statement | C43: ECO-02 | D43: content_community | E43: owned_web | F43: O acervo formula oito enunciados de job em primeira pessoa que descrevem a distancia entre intencao e execucao. | G43: DOC-C01-005: 'Quero fazer, mas nao consigo iniciar. Comeco, mas nao consigo sustentar. Sei fazer, mas esqueco etapas... Entrego, mas atraves de urgencia, estresse e recuperacao posterior. Crio sistemas de produtividade, mas nao consigo mante-los.' | H43: DOC-C01-005;DOC-C03-002 | I43: strong | J43: 0.9 | K43: fact | L43: high | M43: high | N43: Usar os oito enunciados como titulos-semente do calendario editorial: cada um e um artigo com vulnerabilidade, demanda, falha e controle.
A44: SA-04C | B44: functional_job | C44: ECO-01 | D44: software | E44: app | F44: O job funcional central e transformar contexto em proxima acao valida e preservar o estado do trabalho. | G44: positioning: 'Sistema de execucao para profissionais multiprojeto que transforma contexto em proxima acao e preserva o estado do trabalho'; VALUE_EVENT-01: 'Projeto real -> contexto interpretado -> proxima acao valida -> acao executada -> conclusao/evidencia registrada'. | H44: DOC-C07-009 | I44: strong | J44: 0.9 | K44: fact | L44: high | M44: high | N44: Instrumentar VALUE_EVENT-01 como evento unico de ativacao antes do lancamento; sem ele nao ha PMF mensuravel.
A45: SA-04C | B45: job_map | C45: ECO-03 | D45: digital_product | F45: A matriz GP-01 a GP-11 mapeia onze jobs de gestao de projetos contra vulnerabilidades executivas e controles compensatorios. | G45: DOC-C07-003 traz 11 linhas com colunas Funcao / Capacidade exigida / Vulnerabilidade / Evidencia (B/C/E) / Impacto operacional / Compensacao sistemica / Decisao de produto, de 'Iniciacao e escopo' a 'Capacidade e forecasting'. | H45: DOC-C07-003;DOC-C07-002;DOC-C07-004 | I45: strong | J45: 0.9 | K45: fact | L45: high | M45: high | N45: Tratar a matriz como o artefato mais reutilizavel do acervo: ela serve simultaneamente a roadmap de produto, pauta editorial e escopo do framework.
A46: SA-04C | B46: job_pain | C46: ECO-03 | D46: digital_product | F46: O mecanismo de falha mais forte da matriz e o de execucao sustentada, classificado como evidencia B/C forte. | G46: GP-06: 'Competicao entre estimulos + duracao -> abandono, fragmentacao ou multiplos trabalhos parcialmente abertos', evidencia 'B/C forte', compensacao 'Modo foco, WIP baixo, fila separada, captura de interrupcoes sem abandonar tarefa atual'. | H46: DOC-C07-003;DOC-C07-002 | I46: strong | J46: 0.85 | K46: fact | L46: high | M46: medium | N46: Priorizar WIP baixo e fila unica como feature de lancamento, por ser a linha com a evidencia mais forte da matriz.
A47: SA-04C | B47: job_statement | C47: ECO-07 | D47: professional_service | E47: direct_sales | F47: O job do cliente de servico e declarado como sair com um sistema funcionando em sete dias. | G47: DOC-C09-006: 'Traga o problema. Em 7 dias, saia com um sistema funcionando'; modelo '1 cliente por semana - 1 projeto - 1 entrega principal - 7 dias'. | H47: DOC-C09-006;DOC-C05-001 | I47: strong | J47: 0.9 | K47: fact | L47: high | M47: medium | N47: Manter a promessa de 7 dias como criterio de escopo: qualquer pedido que nao caiba em 7 dias vira outra oferta, nao excecao.
A48: SA-04D | B48: primary_research | C48: ECO-01 | D48: software | F48: Nao existe pesquisa primaria com clientes reais em nenhuma das quatro unidades. | G48: Dashboard: 'Strict VERIFIED 0'; gaps ICP/Preco/CAC/LTV/PMF/Eficacia todos com closed: false e remaining apontando para validacao com clientes/coorte real; a base tem 240 registros legados, sendo 142 de livro e 98 de documento interno. | H48: DOC-C07-009;DOC-C07-007 | I48: strong | J48: 0.9 | K48: fact | L48: high | M48: high | N48: Rodar 10-15 entrevistas com o ICP durante a campanha de lancamento; e o insumo mais barato e mais ausente do acervo.
A49: SA-04D | B49: stated_need | C49: ECO-02 | D49: content_community | E49: owned_web | F49: As necessidades explicitas e implicitas do publico estao registradas, mas derivam de documento interno e nao de escuta direta. | G49: QL-0021: 'necessidades de foco, organizacao e reducao da procrastinacao'; QL-0022: 'validacao nao moral, externalizacao de funcoes executivas e reforcos externos imediatos'; conjunto: 'Documento interno do projeto'. | H49: DOC-C07-007 | I49: moderate | J49: 0.65 | K49: fact | L49: medium | M49: medium | N49: Testar as necessidades implicitas como hipoteses de copy A/B na campanha, tratando-as como suposicao e nao como voz do cliente.
A50: SA-04D | B50: emotional_job | C50: ECO-02 | D50: content_community | E50: owned_web | F50: A dor moral (culpa e interpretacao de preguica) e registrada como agravante do problema funcional. | G50: QL-0020: 'Culpa e interpretacao de preguica agravam o problema funcional'; QL-0019: 'falha cronica de autorregulacao e funcao executiva, expressa por procrastinacao e abandono apesar de criatividade e hiperfoco'. | H50: DOC-C07-007 | I50: moderate | J50: 0.7 | K50: fact | L50: high | M50: medium | N50: Manter o tom nao moralizante como regra editorial explicita; e o diferencial percebido mais barato de sustentar.
A51: SA-04D | B51: demand_signal | C51: ECO-02 | D51: content_community | E51: owned_web | F51: Ha estimativas internas de volume de busca por cinco termos-chave, sem metodologia nem data. | G51: QT-0154 'TDAH adulto 110.000-140.000 buscas/mes'; QT-0155 'TDAH procrastinacao 18.000-25.000'; QT-0156 'funcoes executivas 12.000-18.000'; QT-0157 'como organizar com TDAH 9.000-15.000'; QT-0158 'planner para TDAH 6.000-10.000'. Observacao: 'metodologia e data da pesquisa nao aparecem na imagem'. | H51: DOC-C07-007;DOC-C07-009 | I51: weak | J51: 0.45 | K51: fact | L51: medium | M51: medium | N51: Refazer o levantamento em ferramenta propria antes de usar como base de plano de SEO; hoje sao faixas transcritas de imagem.
A52: SA-04D | B52: behavioral_evidence | C52: ECO-01 | D52: software | E52: app | F52: Ha dois numeros de contexto de trabalho citados a partir de blog corporativo, com forca de evidencia baixa. | G52: QT-000175: '23,0 minutos para recuperar o foco apos notificacao/troca de contexto'; QT-000176: 'intervalo de 2,0 minutos entre notificacoes', ambos fonte 'Toggl (blog corporativo)', publico 'Trabalhadores do conhecimento'. | H52: DOC-C07-007 | I52: weak | J52: 0.45 | K52: fact | L52: medium | M52: low | N52: Nao usar os 23 minutos como claim publico; se necessario, buscar a fonte primaria ou substituir por metrica propria de resume latency.
A53: SA-05 | B53: prior_art | C53: ECO-03 | D53: digital_product | F53: O termo cognitive risk ja possui anterioridade publicada, e o acervo registra isso explicitamente. | G53: RC-TERM-007 aponta o livro 'Cognitive Risk' (Bone & Lee, Routledge) e RC-TERM-008 o capitulo 'Managing Cognitive Risk' (Emerald) como STATUS ANTERIORIDADE; guardrail: 'Nao reivindicar autoria do termo'. | H53: DOC-C02-030;DOC-C02-022 | I53: strong | J53: 0.9 | K53: fact | L53: high | M53: high | N53: Publicar o mapa de anterioridade junto com o framework; e o que separa contribuicao defensavel de reivindicacao fragil.
A54: SA-05 | B54: whitespace | C54: ECO-03 | D54: digital_product | F54: O whitespace declarado e a integracao perfil executivo -> demanda cognitiva -> falha -> probabilidade/impacto -> controle -> evidencia, aplicada a projetos e neurodivergencia. | G54: DOC-C02-031, item 3: 'Nao foi identificado, nesta rodada, um framework consolidado que una explicitamente: perfil executivo individual -> demanda cognitiva da tarefa -> evento provavel de falha -> probabilidade/impacto -> controle compensatorio -> evidencia de execucao'. | H54: DOC-C02-031;DOC-C02-016 | I54: strong | J54: 0.85 | K54: fact | L54: high | M54: high | N54: Manter a formulacao literal como definicao da contribuicao; ela e especifica o bastante para ser testada e defendida.
A55: SA-05 | B55: whitespace_risk | C55: ECO-03 | D55: digital_product | F55: Tratar a ausencia de framework equivalente como prova de ineditismo e registrado como risco de credibilidade pelo proprio acervo. | G55: DOC-C02-031, item 4: 'Nao encontramos nao significa nao existe'; DOC-C02-039 (Riscos): 'Tratar a ausencia de um framework equivalente nas buscas como prova de ineditismo pode comprometer a credibilidade cientifica e estrategica da proposta'. | H55: DOC-C02-031;DOC-C02-039;DOC-C02-043 | I55: strong | J55: 0.9 | K55: fact | L55: high | M55: high | N55: Executar a scoping review sistematica (RC-P02-VAL01, etapa 1) antes de qualquer comunicacao publica de ineditismo.
A56: SA-05 | B56: competitor_benchmark | C56: ECO-02 | D56: content_community | E56: social | F56: O acervo estima receita anual de R$595-654 mil para o concorrente TDAH Descomplicado, sem fonte resolvida. | G56: QT-0145: 'Receita anual estimada do concorrente TDAH Descomplicado, 595000.0-654000.0 R$/ano', 'Requer validacao na referencia original', bibliografia [2][4] ausente do material. | H56: DOC-C07-007;DOC-C07-009 | I56: weak | J56: 0.4 | K56: fact | L56: medium | M56: low | N56: Usar apenas como ordem de grandeza interna; nao citar publicamente numero de receita de terceiro sem fonte.
A57: SA-05 | B57: competitive_gap | C57: ECO-02 | D57: content_community | E57: owned_web | F57: A lacuna competitiva hipotetizada e que concorrentes seriam fortes em sintomas e medicacao e fracos em aplicacao pratica. | G57: QL-0026: 'Concorrentes seriam mais fortes em sintomas e medicacao do que em aplicacao pratica e desempenho'; recomendacao da propria fonte: 'Validar a lacuna por auditoria de conteudo e entrevistas, antes de assumir oceano azul'. | H57: DOC-C07-007 | I57: moderate | J57: 0.65 | K57: hypothesis | L57: high | M57: medium | N57: Fazer auditoria de 20 conteudos concorrentes classificando por Entender/Estruturar/Executar/Evoluir para confirmar ou derrubar a hipotese.
A58: SA-05 | B58: competitive_practice | C58: ECO-01 | D58: software | E58: app | F58: Dark patterns em apps de produtividade sao registrados como fator negativo de confianca, criando espaco de diferenciacao etica. | G58: QL-000050: 'Padroes de design enganoso (dificuldade para cancelar assinatura, inducao de culpa, continuidade forcada) sao apontados como prejudiciais a confianca do usuario em aplicativos de produtividade'. | H58: DOC-C07-007 | I58: moderate | J58: 0.7 | K58: fact | L58: medium | M58: medium | N58: Transformar em compromisso publico verificavel (cancelamento em um clique, sem inducao de culpa) - barato e alinhado ao publico.
A59: SA-06A | B59: revenue_streams | C59: ECO-01 | D59: software | F59: O ecossistema declara seis fontes de receita distintas ligadas por um registro unico de CTAs. | G59: CTA Registry (DOC-C06-001): CTA-001 App, CTA-004 E-book, CTA-005 Curso, CTA-006 Studio (servico), CTA-007 Amazon Affiliate, CTA-009 Office Kit (fisico), alem de CTA-003 Biblioteca e CTA-008/010 captacao de lead. | H59: DOC-C06-001;DOC-C05-001 | I59: strong | J59: 0.9 | K59: fact | L59: high | M59: high | N59: Antes de 07/09, marcar quais dos 10 CTAs tem destino real e quais devem ser desligados; um CTA sem destino queima trafego de lancamento.
A60: SA-06A | B60: margin_pool | C60: ECO-01 | D60: digital_product | E60: education_platform | F60: O material posiciona infoprodutos como motor de margem e produtos fisicos como retencao e marca. | G60: QL-0039: 'Infoprodutos sao propostos como motor de margem e produtos fisicos como retencao e marca'; QT-0148: 'Margem bruta de infoprodutos 83,0% ou mais'; QT-0151: 'Preco sugerido de produto fisico premium 350,0 R$ ou mais'. | H60: DOC-C07-007;DOC-C07-009 | I60: weak | J60: 0.5 | K60: fact | L60: medium | M60: medium | N60: Tratar os 83% como premissa herdada; validar com custo real de plataforma, imposto e taxa de checkout antes de planejar caixa.
A61: SA-06A | B61: affiliate_pool | C61: ECO-02 | D61: content_community | E61: affiliate | F61: A monetizacao por afiliados esta desenhada como camada editorial com comissao de 10% em livros na Amazon. | G61: DOC-C05-001, Macro 01: 'A tabela padrao atual informa 10% para livros e livros digitais em compras qualificadas'; AF-04: 'Recomendacao editorial primeiro; monetizacao depois'; biblioteca inicial BK-01/02/03 (Barkley, Ana Beatriz Silva, Barkley EF). | H61: DOC-C05-001 | I61: strong | J61: 0.85 | K61: fact | L61: low | M61: medium | N61: Executar AF-SETUP-001 (cadastro + IDs por canal + substituicao dos links-base) antes de publicar as pecas que citam os livros.
A62: SA-06A | B62: revenue_conflict | C62: ECO-02 | D62: content_community | E62: owned_web | F62: Ha conflito registrado sobre a alocacao da receita de AdSense ao braco social. | G62: QT-0152: 'Alocacao de AdSense inicialmente cogitada 70,0% da receita'; QT-0153: 'Alocacao inicial recomendada 10,0%'; QL-0016: '70% ... e considerada incompativel com reinvestimento e consistencia operacional'. | H62: DOC-C07-007;DOC-C07-009 | I62: moderate | J62: 0.75 | K62: conflict | L62: medium | M62: low | N62: Registrar formalmente a decisao (10%) e o motivo, para que a versao de 70% nao volte por copia de material antigo.
A63: SA-06B | B63: unit_economics | C63: ECO-01 | D63: software | E63: app | F63: O modelo economico do app e integralmente hipotetico: ARPU, margem e churn sao premissas, nao observacoes. | G63: unit_economics.status: 'MODEL_HYPOTHESIS_NOT_OBSERVED'; cenarios: churn 10%/15%/20% -> LTV R$424 / R$282,77 / R$212 e CAC maximo para LTV:CAC=3 de R$141 / R$94 / R$71, com ARPU R$49,90 e margem bruta 85%. | H63: DOC-C07-009 | I63: strong | J63: 0.9 | K63: fact | L63: high | M63: high | N63: Nao usar LTV de R$282,77 em nenhuma decisao de investimento; substituir por LTV_30/60/90/180/365 assim que houver coorte paga.
A64: SA-06B | B64: cac_guardrail | C64: ECO-01 | D64: software | E64: direct_sales | F64: O guardrail de CAC e R$70 (conservador) com alerta em aproximadamente R$95, e a fonte distingue CAC de metricas intermediarias. | G64: Decisao CAC-01 e painel: 'CAC observado = gasto atribuivel / novos clientes pagantes. CPI, CPM, clique e cadastro nao substituem CAC.' | H64: DOC-C07-009 | I64: strong | J64: 0.9 | K64: fact | L64: high | M64: high | N64: Implementar os eventos de telemetria acquisition_source, campaign_id, paid_at e gross_revenue antes da primeira campanha paga.
A65: SA-06B | B65: pricing | C65: ECO-01 | D65: software | E65: app | F65: O preco e um experimento declarado, nao uma tabela: R$29,90 / R$49,90 / R$79,90 mensais e R$299 / R$499 / R$799 anuais. | G65: research.pricing: monthly_branches_brl [29.9, 49.9, 79.9], annual_branches_brl [299, 499, 799], central_test_price_brl 49.9, status 'HYPOTHESIS_TO_TEST'; painel: 'Preco canonico ainda nao existe'. | H65: DOC-C07-009 | I65: strong | J65: 0.9 | K65: fact | L65: high | M65: high | N65: Publicar apenas o ponto central R$49,90 no lancamento e reservar as pontas para teste, evitando ancoragem publica de tres precos.
A66: SA-06B | B66: service_pricing | C66: ECO-07 | D66: professional_service | E66: direct_sales | F66: O servico tem preco declarado de R$700 por projeto de uma semana, com capacidade de um cliente por semana. | G66: DOC-C05-001: 'Preco: Um projeto, uma entrega, uma semana: R$ 700,00'; 'Capacidade e escassez: Limite de um cliente por semana, apresentado como diferencial do servico'. | H66: DOC-C05-001;DOC-C09-006 | I66: strong | J66: 0.9 | K66: fact | L66: high | M66: high | N66: Confirmar se R$700 e preco de portfolio ou preco-alvo; a pagina PAG-003-ESTUDIO nao pode ir ao ar com essa ambiguidade.
A67: SA-06B | B67: service_capacity_ceiling | C67: ECO-07 | D67: professional_service | E67: direct_sales | F67: Com R$700 por semana e um cliente por semana, o teto teorico de receita do Estudio e cerca de R$36,4 mil por ano. | G67: Derivacao aritmetica direta de DOC-C05-001: R$700 x 52 semanas = R$36.400/ano, ignorando ferias, semanas sem cliente e os primeiros clientes atendidos sem cobranca. | H67: DOC-C05-001 | I67: moderate | J67: 0.8 | K67: inference | L67: high | M67: high | N67: Se o Estudio precisa ser motor de receita, o preco ou o modelo de capacidade precisa mudar; se e motor de portfolio e autoridade, declarar isso e nao cobrar meta de receita dele.
A68: SA-06B | B68: pricing_strategy | C68: ECO-07 | D68: professional_service | E68: direct_sales | F68: Os primeiros clientes podem ser atendidos sem cobranca para construcao de portfolio. | G68: DOC-C05-001: 'Primeiros clientes podem ser atendidos sem cobranca para construcao de portfolio, com transparencia sobre fase inicial e possiveis refinamentos'. | H68: DOC-C05-001 | I68: strong | J68: 0.85 | K68: fact | L68: medium | M68: high | N68: Fixar quantos clientes gratuitos (ex.: 2) e qual o criterio de saida dessa fase, para nao ancorar o servico em preco zero.
A69: SA-06B | B69: cost_structure | C69: ECO-01 | D69: software | E69: app | F69: O custo variavel de IA e reconhecido como evento a medir, mas nao ha nenhum valor estimado no acervo. | G69: telemetry.required_events inclui 'variable_ai_cost', porem nenhum documento lido apresenta custo por usuario, por execucao ou por token. | H69: DOC-C07-009 | I69: none | J69: 0.8 | K69: gap | L69: high | M69: high | N69: Estimar custo variavel por usuario ativo antes de fixar R$49,90; com margem premissa de 85%, o custo de IA e a variavel que pode derrubar o modelo.
A70: SA-06B | B70: economics | C70: ECO-02 | D70: content_community | E70: owned_web | F70: Nao existe modelo economico proprio para a unidade editorial. | G70: O BMC de DOC-C02-039 tem 'Riscos / custos cognitivos' e 'Entregas / evidencia', mas nenhuma linha de receita, custo ou ponto de equilibrio; o objetivo declarado da fase e validar interesse, nao receita. | H70: DOC-C02-039;DOC-C02-043 | I70: none | J70: 0.8 | K70: gap | L70: medium | M70: low | N70: Aceitar o blog como investimento de categoria na fase 1 e definir explicitamente quando ele passa a ter meta economica.
A71: SA-07A | B71: content_chain | C71: ECO-02 | D71: content_community | E71: owned_web | F71: A cadeia editorial e de derivacao 1 para N a partir de um conteudo canonico. | G71: DOC-C10-003: 'Artigo canonico -> imagem principal -> diagramas -> video -> cortes curtos -> carrossel/post -> chamada -> agenda'; DOC-C02-043 registra 'produzir tudo por derivacao 1->N, comecando pelo artigo mestre'. | H71: DOC-C10-003;DOC-C02-043;DOC-C02-014 | I71: strong | J71: 0.9 | K71: fact | L71: high | M71: medium | N71: Manter a regra de nao iniciar derivados antes do canonico estar fechado; e o que protege as 60h comprometidas do GTM.
... A73: SA-07A | B73: service_chain | C73: ECO-07 | D73: professional_service | E73: direct_sales | F73: A cadeia de servico tem nove etapas em aproximadamente sete dias, do formulario ao pos-entrega. | G73: DOC-C05-001: 'Jornada de aproximadamente sete dias, com formulario inicial, consulta extensa, desenvolvimento, prototipo, teste, refinamento, entrega, onboarding e periodo posterior para duvidas'. | H73: DOC-C05-001;DOC-C11-010;DOC-C12-003 | I73: strong | J73: 0.85 | K73: fact | L73: high | M73: medium | N73: Cronometrar as nove etapas no primeiro cliente real; nove etapas em sete dias e o principal risco de sobrecompromisso do Estudio.
A74: SA-07A | B74: ecosystem_loop | C74: ECO-01 | D74: software | F74: O ecossistema e desenhado como ciclo em que o proprio produto serve de showroom da capacidade de servico. | G74: DOC-C05-001: 'Autoridade pessoal -> Conteudo -> Produtos -> Demonstracao pratica -> Servico -> Cliente -> Caso real -> Portfolio -> Mais autoridade'; e 'o Executar nao e apenas um produto... funciona simultaneamente como produto, laboratorio, prova de competencia, showroom e principal ativo de autoridade comercial'. | H74: DOC-C05-001 | I74: strong | J74: 0.9 | K74: fact | L74: high | M74: medium | N74: Explorar o loop deliberadamente: cada release do app deve gerar um ativo de demonstracao reutilizavel pelo Estudio.
A75: SA-07A | B75: tech_stack | C75: ECO-02 | D75: content_community | E75: owned_web | F75: A infraestrutura editorial esta definida e tem criterio de aceite operacional, nao tecnico. | G75: DOC-C02-017: 'Vercel Payload Website Starter + Next.js + Payload CMS + PostgreSQL/Neon + Vercel Blob'; DoD: 'Abrir /admin -> criar artigo -> ... -> publicar, sem editar codigo'. | H75: DOC-C02-017;DOC-C02-043 | I75: strong | J75: 0.9 | K75: fact | L75: high | M75: high | N75: Validar o DoD com uma publicacao de teste ponta a ponta antes do D1 editorial; sem isso a campanha de 14 dias nao pode comecar.
A76: SA-07B | B76: engineering | C76: ECO-01 | D76: software | E76: app | F76: A capacidade de engenharia esta comprovada por estado real de repositorio, nao por declaracao. | G76: DOC-C04-002: 'HEAD de main: 4c8f360 (merge do PR #77)... typecheck limpo... 51/51 vitest passando... 347/347 testes de governanca... CI 3/3 checks verdes em cada um dos PRs mesclados'; handoff gerado 'a partir do estado real do repositorio (git log + GitHub API)'. | H76: DOC-C04-002 | I76: strong | J76: 0.9 | K76: fact | L76: high | M76: medium | N76: Usar o handoff como prova de capacidade nas pecas do Estudio; e a evidencia mais forte de competencia tecnica do acervo.
A77: SA-07B | B77: product_engine | C77: ECO-01 | D77: software | E77: app | F77: O diferencial declarado e arquitetural: plano estavel com rota recalculada, nao uma feature isolada. | G77: DOC-C05-001: 'Tempo disponivel, dependencias, WIP e ciclo definem elegibilidade; Flow Score e Context Score ordenam as alternativas; Progress Points registram somente o trabalho efetivamente concluido'; 'PLAN != ROUTE / ROUTE subconjunto de PLAN'; mensagem: 'O plano continua. A rota se adapta. Voce executa.' | H77: DOC-C05-001 | I77: strong | J77: 0.9 | K77: fact | L77: high | M77: high | N77: Demonstrar o recalculo de rota ao vivo (Cena B da DOC-C11-004) - e a unica prova visual do diferencial que nao pode ser copiada em copy.
A78: SA-07B | B78: epistemic_governance | C78: ECO-01 | D78: software | F78: Existe uma capacidade rara no acervo: governanca epistemologica que separa candidato de verificado. | G78: DOC-C07-009, invariantes: 'original != extracao != evidencia != decisao - candidate != verified - benchmark != dado do EXECUTAR - modelo economico != unit economics observado - literatura externa != eficacia do EXECUTAR - similaridade != suporte factual'. | H78: DOC-C07-009;DOC-C07-007 | I78: strong | J78: 0.9 | K78: fact | L78: high | M78: medium | N78: Transformar a governanca em ativo publico (pagina de metodo): ela e um diferencial defensavel frente a concorrentes de infoproduto.
A79: SA-07B | B79: framework_components | C79: ECO-03 | D79: digital_product | F79: O framework CERM tem cinco componentes provisorios e uma arquitetura de sete elos. | G79: DOC-C02-016: arquitetura 'Perfil executivo -> demanda cognitiva -> risco de execucao -> impacto/probabilidade -> controle compensatorio -> monitoramento -> evidencia/feedback'; componentes: Cognitive Risk Profile, Cognitive Demand Map, Cognitive Risk Register, Compensating Controls, Execution Evidence. | H79: DOC-C02-016;DOC-C02-031 | I79: strong | J79: 0.9 | K79: fact | L79: high | M79: medium | N79: Mapear cada um dos cinco componentes contra um modulo existente do app; o que nao tiver correspondencia e a proxima especificacao de produto.
A80: SA-07B | B80: method_capability | C80: ECO-03 | D80: digital_product | F80: O framework editorial de sete etapas e declarado como adaptacao da logica da ISO 31000, nao como norma. | G80: DOC-C01-005: 'Contexto -> Identificar -> Analisar -> Avaliar -> Tratar -> Controlar -> Monitorar'; ressalva: 'seria um framework seu inspirado na ISO 31000, nao um protocolo clinico ou uma metodologia oficialmente reconhecida pela ISO'. | H80: DOC-C01-005;DOC-C03-002 | I80: strong | J80: 0.9 | K80: fact | L80: high | M80: medium | N80: Repetir a ressalva em toda peca que citar ISO 31000; e o ponto onde a credibilidade e mais facil de perder.
A81: SA-07B | B81: capacity_constraint | C81: ECO-07 | D81: professional_service | E81: direct_sales | F81: A capacidade do Estudio e uma pessoa, e isso e apresentado como diferencial e nao como limite. | G81: DOC-C05-001: 'Limite de um cliente por semana, apresentado como diferencial do servico'; nenhum documento lido preve equipe, subcontratacao ou padronizacao de entrega. | H81: DOC-C05-001;DOC-C09-006 | I81: strong | J81: 0.85 | K81: fact | L81: high | M81: high | N81: Padronizar 3 entregaveis repetiveis (os das tres familias) para reduzir o custo marginal por cliente antes de considerar aumentar preco ou volume.
A82: SA-07B | B82: execution_capacity | C82: ECO-01 | D82: software | F82: O plano de entregaveis mostra 33 de 43 itens ainda ATIVOS as vesperas do lancamento. | G82: DOC-C02-004: 43 linhas, status 'ATIVO' 33 e 'CONCLUIDO' 10, distribuidas em 10 areas (APP 6, Editorial 6, GTM 5, Produtos Fisicos 5, Infoprodutos 5, Showroom 5, Dados 4, Studio 4, Freeze/Launch 2, Governanca 1). | H82: DOC-C02-004 | I82: strong | J82: 0.85 | K82: fact | L82: high | M82: high | N82: Cortar escopo por area antes de cortar qualidade: com 60h comprometidas, 33 entregaveis ativos em 10 frentes e o principal risco do 07/09.
A83: SA-08A | B83: customer | C83: ECO-01 | D83: software | E83: app | F83: O cliente e definido por comportamento observavel e por um evento de valor unico. | G83: ICP-01 (comportamento, sem diagnostico) combinado a VALUE_EVENT-01 e aos endpoints funcionais time_to_next_action, resume_latency, completion_rate, context_reconstruction, execution_cycles_per_week e abandonment_rate. | H83: DOC-C07-009 | I83: strong | J83: 0.85 | K83: fact | L83: high | M83: high | N83: Fazer do painel de ativacao o primeiro dashboard interno pos-lancamento, nao o de downloads.
A84: SA-08B | B84: company | C84: ECO-01 | D84: software | F84: A companhia e um operador unico que sustenta simultaneamente app, blog, framework, servicos, infoprodutos, produtos fisicos e afiliados. | G84: DOC-C05-001 e DOC-C06-001 descrevem sete frentes com capacidade declarada de 6h/dia e 60h comprometidas em 12 dias; DOC-C02-004 confirma 10 areas de entregavel simultaneas. | H84: DOC-C05-001;DOC-C06-001;DOC-C02-004 | I84: strong | J84: 0.85 | K84: inference | L84: high | M84: high | N84: Nomear explicitamente qual unidade e prioritaria em caso de conflito de agenda; hoje o plano assume que todas cabem.
A85: SA-08C | B85: competitor | C85: ECO-02 | D85: content_community | E85: owned_web | F85: O concorrente relevante do blog nao e outro blog de TDAH, e sim a categoria de conteudo de produtividade e a de conteudo clinico. | G85: DOC-C01-005: 'Eu nao posicionaria Risco Cognitivo como mais um blog sobre TDAH'; QL-0017 divide o setor em midia/autoridade medica, infoprodutores, e-commerce de nicho e instituicoes/clinicas. | H85: DOC-C01-005;DOC-C07-007 | I85: moderate | J85: 0.75 | K85: inference | L85: medium | M85: medium | N85: Medir share of search nos cinco termos ja levantados como proxy de posicao competitiva na categoria escolhida.
A86: SA-09A | B86: strength | C86: ECO-01 | D86: software | E86: app | F86: Forca: produto real em producao com governanca de evidencia e 22 decisoes operacionais documentadas. | G86: DOC-C04-002 comprova repositorio, CI e testes; DOC-C07-009 registra '22 decisoes operacionais: 15 produto/seguranca + 7 negocio/pesquisa'. | H86: DOC-C04-002;DOC-C07-009 | I86: strong | J86: 0.85 | K86: fact | L86: high | M86: medium | N86: Usar as 22 decisoes como backlog de requisitos rastreaveis; poucos concorrentes conseguem mostrar essa cadeia.
A87: SA-09B | B87: weakness | C87: ECO-01 | D87: software | E87: app | F87: Fraqueza: zero registros no gate estrito de verificacao e nenhum cliente pagante. | G87: DOC-C07-009: 'Strict VERIFIED 0 - gate factual permanece preservado'; '161 evidence candidates'; 'governed_verified_links: 0'; gaps de CAC/LTV/PMF com 'remaining: Campanhas e clientes pagantes' e 'Cohort real'. | H87: DOC-C07-009 | I87: strong | J87: 0.9 | K87: fact | L87: high | M87: high | N87: Aceitar que o lancamento de 07/09 e um experimento de aquisicao, nao uma operacao comercial validada, e comunicar internamente assim.
A88: SA-09C | B88: opportunity | C88: ECO-03 | D88: digital_product | F88: Oportunidade: converter a matriz GP-01..GP-11 em white paper citavel antes que o campo se popule. | G88: DOC-C02-015 preve 'White paper v1 de 15-30 paginas' e 'DOI somente apos estabilizacao'; DOC-C02-042 registra que a APM ja publicou formulacao proxima em 26/08/2026. | H88: DOC-C02-015;DOC-C02-042;DOC-C07-003 | I88: moderate | J88: 0.75 | K88: inference | L88: high | M88: high | N88: Antecipar o white paper para logo apos a campanha editorial; a janela de anterioridade esta se fechando.
A89: SA-09D | B89: threat | C89: ECO-02 | D89: content_community | E89: owned_web | F89: Ameaca: saturacao e desinformacao no tema podem derrubar a confianca do publico. | G89: QL-0015: 'Conteudo superficial e desinformacao sao tratados como riscos de saturacao e perda de confianca'; QL-0013 descreve 'transicao de conscientizacao acelerada para maturacao e monetizacao do mercado'. | H89: DOC-C07-007 | I89: moderate | J89: 0.7 | K89: fact | L89: high | M89: medium | N89: Fazer da politica de citacao e da separacao evidencia/interpretacao um elemento visivel da marca, nao um detalhe interno.
A90: SA-09D | B90: threat | C90: ECO-01 | D90: software | E90: app | F90: Ameaca: uma unica peca de copy com claim clinico pode acionar risco regulatorio e reputacional simultaneo. | G90: CLAIM-01 exige 'Revisao juridica/regulatoria da copy final e auditoria de implementacao'; a lista de proibidos inclui 'Cientificamente comprovado para TDAH', e o funil de lancamento parte de conteudo sobre TDAH. | H90: DOC-C07-009;DOC-C10-011;DOC-C10-019 | I90: strong | J90: 0.85 | K90: inference | L90: high | M90: high | N90: Inserir um gate de revisao de claims no fluxo de publicacao, entre 'texto aprovado' e 'CMS carregado'.
A91: SA-09B | B91: weakness | C91: ECO-07 | D91: professional_service | E91: direct_sales | F91: Fraqueza: a oferta de servico esta incompleta em quatro elementos criticos as vesperas do lancamento. | G91: DOC-C09-006 lista como pendentes: 'pagina institucional de servicos; pagina Estudio; formulario visual inicial; tres familias de servico; condicao de preco inicial; demonstracoes de casos proprios; chamada CH-006 funcionando'. | H91: DOC-C09-006;DOC-C12-006;DOC-C12-007 | I91: strong | J91: 0.9 | K91: fact | L91: high | M91: high | N91: Ou fechar os sete itens ate 05/09 ou remover o Estudio do lancamento e mante-lo como lista de interesse.
A92: SA-09C | B92: opportunity | C92: ECO-07 | D92: professional_service | E92: direct_sales | F92: Oportunidade: o proprio EXECUTAR e o showroom do servico, eliminando o custo de portfolio inicial. | G92: DOC-C05-001: 'O app Executar, o Agente 007, skills e plugins funcionam como provas visuais e como principal showroom das capacidades oferecidas'. | H92: DOC-C05-001;DOC-C11-010 | I92: strong | J92: 0.85 | K92: fact | L92: high | M92: medium | N92: Gravar as demonstracoes 01-04 uma unica vez e reutiliza-las como material comercial permanente do Estudio.
A93: SA-10A | B93: market_attractiveness | C93: ECO-01 | D93: software | F93: Nao ha base para pontuar atratividade de mercado do app: nenhum dos insumos de tamanho, crescimento ou rentabilidade esta verificado. | G93: TAM/SAM/SOM sem metodologia (QT-0131/132/133), CAGR sem fonte resolvida (QT-0138/139), LTV e CAC apenas modelados, e 'Strict VERIFIED 0'. | H93: DOC-C07-007;DOC-C07-009 | I93: none | J93: 0.85 | K93: gap | L93: high | M93: medium | N93: Adiar qualquer scoring formal de atratividade; a decisao de continuar deve se apoiar em PMF-01, nao em tamanho de mercado.
A94: SA-10A | B94: market_attractiveness | C94: ECO-03 | D94: digital_product | F94: A atratividade do territorio de framework e sustentada por evidencia de problema, nao por evidencia de mercado. | G94: DOC-C01-005: 'A evidencia disponivel sustenta claramente a existencia do problema social. O que ainda precisara ser demonstrado... e se organizar essas dificuldades atraves de um framework explicito... constitui uma abordagem util e empiricamente defensavel.' | H94: DOC-C01-005;DOC-C02-031 | I94: strong | J94: 0.85 | K94: fact | L94: high | M94: medium | N94: Separar as duas perguntas nos relatorios internos: existencia do problema (respondida) e utilidade do framework (aberta).
A95: SA-10B | B95: ability_to_win | C95: ECO-01 | D95: software | E95: app | F95: A capacidade de vencer se apoia em ativos verificaveis: produto operante, base de evidencia governada e matriz de decisao de design. | G95: DOC-C04-002 (CI verde, 398 testes), DOC-C07-009 (22 decisoes, invariantes epistemicos), DOC-C07-003 (11 linhas GP com compensacao sistemica e decisao de produto). | H95: DOC-C04-002;DOC-C07-009;DOC-C07-003 | I95: strong | J95: 0.8 | K95: inference | L95: high | M95: medium | N95: Comunicar a cadeia evidencia -> decisao -> feature como diferencial verificavel; e o que nenhum concorrente de infoproduto pode replicar rapido.
A96: SA-10B | B96: ability_to_win | C96: ECO-07 | D96: professional_service | E96: direct_sales | F96: A capacidade de vencer no servico e limitada por capacidade humana, nao por demanda ou diferenciacao. | G96: Um cliente por semana (DOC-C05-001), tres familias de servico ainda nao especificadas (DOC-C09-006) e nenhuma padronizacao de entrega documentada. | H96: DOC-C05-001;DOC-C09-006 | I96: moderate | J96: 0.75 | K96: inference | L96: high | M96: medium | N96: Tratar o Estudio como gerador de casos e insumo editorial na fase 1; escalar so depois de 5 entregas com escopo repetido.
A97: SA-10B | B97: ability_to_win | C97: ECO-02 | D97: content_community | E97: owned_web | F97: A capacidade de vencer no editorial depende de um ativo que ainda nao existe: o site publicado. | G97: DOC-C02-039 registra status 'fundacao editorial definida; validacao e publicacao pendentes' e AGORA = 'Confirmar dominio e reservar @riscocognitivo'; DOC-C02-043 lista 11 proximos passos comecando por dominio e repositorio. | H97: DOC-C02-039;DOC-C02-043 | I97: strong | J97: 0.9 | K97: fact | L97: high | M97: high | N97: Dominio, repositorio e CMS no ar sao pre-requisitos duros; qualquer plano editorial anterior a isso e planejamento sem canal.
A98: SA-11A | B98: where_to_play | C98: ECO-02 | D98: content_community | E98: owned_web | F98: A escolha declarada e ocupar um territorio editorial proprio, e nao a categoria blog de TDAH. | G98: DOC-C02-043: 'Risco Cognitivo deixa de ser apenas um blog sobre TDAH e passa a ser um territorio editorial sobre funcoes executivas, neurodivergencia, trabalho, projetos, risco e execucao'; DOC-C01-005 reforca 'TDAH pode ser seu primeiro laboratorio'. | H98: DOC-C02-043;DOC-C01-005 | I98: strong | J98: 0.9 | K98: fact | L98: high | M98: high | N98: Aplicar o teste em cada pauta: se ela so faz sentido para quem tem TDAH, ela pertence a Biblioteca EXECUTAR, nao ao Risco Cognitivo.
A99: SA-11A | B99: where_to_play_conflict | C99: ECO-02 | D99: content_community | E99: owned_web | F99: Ha duas arquiteturas editoriais concorrentes no acervo, com categorias diferentes. | G99: Versao A (DOC-C02-043/DOC-C01-005): territorio 'Risco Cognitivo', mais amplo que TDAH. Versao B (DOC-C10-003): 'Arquitetura editorial unica - Categoria: TDAH adulto aplicado ao trabalho, a gestao e a execucao', com tres pilares e 4E. | H99: DOC-C02-043;DOC-C01-005;DOC-C10-003;DOC-C05-001 | I99: strong | J99: 0.85 | K99: conflict | L99: high | M99: high | N99: Decidir se sao duas publicacoes (Risco Cognitivo e Biblioteca EXECUTAR) ou uma; hoje o lancamento de 07/09 usa a Versao B e o pacote Risco Cognitivo usa a Versao A.
A100: SA-11A | B100: where_to_play | C100: ECO-01 | D100: software | E100: app | F100: A escolha de terreno do produto e execucao multiprojeto, explicitamente fora do terreno clinico. | G100: POSITION-01: 'Posicionar o EXECUTAR como sistema de execucao para rotinas multiprojeto, nao como tratamento de TDAH'; nota: 'Neurocompativel por design pode ser explorado como linguagem de design, mas nao como claim clinico'. | H100: DOC-C07-009 | I100: strong | J100: 0.9 | K100: fact | L100: high | M100: high | N100: Definir publicamente o que 'neurocompativel por design' significa em termos de design, senao o termo sera lido como claim clinico.
A101: SA-11A | B101: where_to_play | C101: ECO-03 | D101: digital_product | F101: O terreno do framework e a integracao especifica, nao o termo generico. | G101: RC-030: 'Nao reivindicar criacao do termo - a contribuicao defensavel e a sintese/aplicacao especifica'; DOC-C02-016 (GUARDRAIL): 'a contribuicao defensavel e a integracao especifica com funcoes executivas, neurodivergencia e execucao de projetos'. | H101: DOC-C02-016;DOC-C02-042;DOC-C02-030 | I101: strong | J101: 0.9 | K101: fact | L101: high | M101: medium | N101: Escrever a frase de contribuicao em uma unica sentenca canonica e reutiliza-la sem variacao em todos os materiais.
...

Sheet 04_EVIDENCIAS
A1: evidencia_id | B1: origem | C1: rodada | D1: claim_ou_campo | E1: framework | F1: dimensao | G1: unidade | H1: documento_id | I1: evidencia | J1: forca | K1: confianca | L1: status
A2: EV-8a4ad69b20 | B2: strategic_analysis | C2: r1 | D2: Posicionar o app como diagnostico ou tratamento de TDAH pode acionar o regime de Software como Dispositivo Medico da Anvisa. | E2: SA-01 | F2: legal_regulatory | G2: ECO-01 | H2: DOC-C07-009 | I2: Fonte SRC-RG8-ANVISA-SAMD no dashboard: 'RDC 657/2022 - Software como Dispositivo Medico... Enquadramento SaMD depende da indicacao e funcao; software que diagnostica/trata pode entrar no regime regulatorio.' | J2: strong | K2: 0.9 | L2: fact
A3: EV-495a2f033b | B3: strategic_analysis | C3: r1 | D3: Coletar diagnostico de TDAH no onboarding transformaria a base em dado pessoal sensivel sob a LGPD, sem necessidade funcional. | E3: SA-01 | F3: legal_regulatory | G3: ECO-01 | H3: DOC-C07-009 | I3: Fonte SRC-RG8-ANPD-LGPD: 'Dado referente a saude e dado pessoal sensivel; minimizacao favorece nao coletar diagnostico quando desnecessario.' Decisao ICP-01: 'diagnostico nao define o ICP comercial inicial'. | J3: strong | K3: 0.9 | L3: fact
A4: EV-de94db3e25 | B4: strategic_analysis | C4: r1 | D4: A politica de claims proibe hoje seis formulacoes clinicas no conteudo editorial e comercial. | E4: SA-01 | F4: legal_regulatory | G4: ECO-02 | H4: DOC-C07-009 | I4: claims_policy.prohibited_now: 'Reduz sintomas de TDAH', 'Melhora funcao executiva clinicamente', 'Trata TDAH', 'Diagnostica ou identifica TDAH', 'Substitui terapia, tratamento ou medicacao', 'Cientificamente comprovado para TDAH'. | J4: strong | K4: 0.9 | L4: fact
A5: EV-f04a701f8e | B5: strategic_analysis | C5: r1 | D5: Qualquer estudo proprio de eficacia com participantes humanos fica sujeito a Resolucao CNS 466/2012. | E5: SA-01 | F5: ethical | G5: ECO-03 | H5: DOC-C07-009 | I5: Fonte SRC-RG8-CNS-466: 'Resolucao CNS 466/2012'; decisao EFFICACY-01 exige 'protocolo proprio, diagnostico confirmado, instrumento validado, comparador e revisao etica aplicavel'. | J5: strong | K5: 0.85 | L5: fact
A6: EV-69f96afd6b | B6: strategic_analysis | C6: r1 | D6: Qualquer estudo proprio de eficacia com participantes humanos fica sujeito a Resolucao CNS 466/2012. | E6: SA-01 | F6: ethical | G6: ECO-03 | H6: DOC-C02-015 | I6: Fonte SRC-RG8-CNS-466: 'Resolucao CNS 466/2012'; decisao EFFICACY-01 exige 'protocolo proprio, diagnostico confirmado, instrumento validado, comparador e revisao etica aplicavel'. | J6: strong | K6: 0.85 | L6: fact
A7: EV-a783716a71 | B7: strategic_analysis | C7: r1 | D7: O Brasil tinha 26,1 milhoes de trabalhadores por conta propria em 2025, contexto do ICP de profissionais independentes. | E7: SA-01 | F7: social | G7: ECO-01 | H7: DOC-C07-009 | I7: Finding BRA-MKT-01, fonte SRC-RG8-IBGE-SELFEMPLOYED-2025 (PNAD Continua): '26,1 milhoes de trabalhadores por conta propria em 2025'. Uso declarado: 'Contexto de mercado; nao equivale a TAM do EXECUTAR.' | J7: strong | K7: 0.9 | L7: fact
A8: EV-147350e17f | B8: strategic_analysis | C8: r1 | D8: O acesso a internet no Brasil e majoritariamente movel, sustentando arquitetura mobile-first. | E8: SA-01 | F8: technological | G8: ECO-01 | H8: DOC-C07-009 | I8: Finding BRA-MOBILE-01 (IBGE 2025): '90,5% da populacao de 10+ usava internet e 98,7% dos usuarios acessavam por celular'. Uso: 'Sustenta estrategia mobile-first; nao prova preferencia especifica do ICP.' | J8: strong | K8: 0.85 | L8: fact
A9: EV-161a0a642b | B9: strategic_analysis | C9: r1 | D9: Ha estimativas internacionais de carga economica excedente associada ao TDAH adulto que sustentam o problema, mas nao sao perda individual. | E9: SA-01 | F9: economic | G9: ECO-03 | H9: DOC-C02-021 | I9: RC-003: 'US$ 14.092 de custo excedente por adulto/ano'; RC-004: 'EUR 15.652 por adulto diagnosticado/ano'; guardrail: 'valor e carga economica/social media, nao perda literal individual'. | J9: strong | K9: 0.85 | L9: fact
A10: EV-eb5f8c5c02 | B10: strategic_analysis | C10: r1 | D10: Ha estimativas internacionais de carga economica excedente associada ao TDAH adulto que sustentam o problema, mas nao sao perda individual. | E10: SA-01 | F10: economic | G10: ECO-03 | H10: DOC-C02-032 | I10: RC-003: 'US$ 14.092 de custo excedente por adulto/ano'; RC-004: 'EUR 15.652 por adulto diagnosticado/ano'; guardrail: 'valor e carga economica/social media, nao perda literal individual'. | J10: strong | K10: 0.85 | L10: fact
A11: EV-dd70afc2df | B11: strategic_analysis | C11: r1 | D11: Ha estimativas internacionais de carga economica excedente associada ao TDAH adulto que sustentam o problema, mas nao sao perda individual. | E11: SA-01 | F11: economic | G11: ECO-03 | H11: DOC-C02-043 | I11: RC-003: 'US$ 14.092 de custo excedente por adulto/ano'; RC-004: 'EUR 15.652 por adulto diagnosticado/ano'; guardrail: 'valor e carga economica/social media, nao perda literal individual'. | J11: strong | K11: 0.85 | L11: fact
A12: EV-421441a4cc | B12: strategic_analysis | C12: r1 | D12: Evidencia brasileira populacional associa rastreio positivo de TDAH a maior desemprego, com n=2.297 e 4,59% de rastreio positivo. | E12: SA-01 | F12: social | G12: ECO-02 | H12: DOC-C02-032 | I12: RC-SRC-004 (Mattos et al., 2024, J Atten Disord): 'n=2.297; 4,59% de TDAH sintomatico (IC95% 3,56-5,44)'; limitacao registrada: 'ASRS-6 e screener; nao apresentar 4,59% como prevalencia diagnostica nacional'. | J12: strong | K12: 0.9 | L12: fact
... A548: EV-1509c16684 | B548: strategic_analysis | C548: r2 | D548: O relacionamento com a audiencia esta definido por acoes de baixo compromisso antes de qualquer oferta. | E548: SA-08B | F548: customer | G548: ECO-08 | H548: DOC-C02-042 | I548: BMC, Relacao com audiencia: 'Ler, explorar, assinar e baixar o Mapa de Risco Cognitivo; medir interesse antes de introduzir o EXECUTAR'; texto 2.txt: 'com CTA para ler, explorar, assinar ou baixar - nao para comprar/conhecer o EXECUTAR'. | J548: strong | K548: 0.9 | L548: fact
A549: EV-1deac821c8 | B549: formulario | C549: dia1-2 | D549: 1.1 Problema central | F549: NEGÓCIO & GTM | G549: TRANSVERSAL (detalhado por ECO-01, ECO-03 e ECO-02) | H549: DOC-C05-001 | I549: DOC-C05-001 (seção “Corpo”, linha Problema): “Paralisia por excesso, dificuldade de iniciação das tarefas, não linearidade de execução, troca de contexto cognitivo, retrabalho por não respeitar cadeia única de valor e dependências, memória de trabalho limitada, ausência de processos padronizados e múltiplas fontes de execução e plataformas.” Perspectiva do usuário no mesmo documento: “Perco dinheiro e oportunidades por atrasos e desorganização. […] O momento de maior ansiedade e aflição são os primeiros 30 minutos iniciais, pois não sei onde estava ontem, o que devo fazer agora e como sei que terminei.” | DOC-C07-009 (decisão PROD-03): “Definir a dor central como dificuldade de transformar intenção em comportamento organizado ao longo do tempo, evitando o posicionamento genérico de ‘produtividade’.” | DOC-C01-005: “Eu evitaria usar não execução como problema principal. É estreito demais.” e “A distância entre intenção e execução diante de vulnerabilidades cognitivas e demandas reais.” | DOC-C02-039 (BMC, célula Problema): “Apresentar o EXECUTAR cedo demais pode reduzir a credibilidade da investigação e impedir distinguir interesse genuíno pelo problema de interesse no produto.” | K549: alta | L549: preenchido
A550: EV-018c2900c2 | B550: formulario | C550: dia1-2 | D550: 1.1 Problema central | F550: NEGÓCIO & GTM | G550: TRANSVERSAL (detalhado por ECO-01, ECO-03 e ECO-02) | H550: DOC-C07-009 | I550: DOC-C05-001 (seção “Corpo”, linha Problema): “Paralisia por excesso, dificuldade de iniciação das tarefas, não linearidade de execução, troca de contexto cognitivo, retrabalho por não respeitar cadeia única de valor e dependências, memória de trabalho limitada, ausência de processos padronizados e múltiplas fontes de execução e plataformas.” Perspectiva do usuário no mesmo documento: “Perco dinheiro e oportunidades por atrasos e desorganização. […] O momento de maior ansiedade e aflição são os primeiros 30 minutos iniciais, pois não sei onde estava ontem, o que devo fazer agora e como sei que terminei.” | DOC-C07-009 (decisão PROD-03): “Definir a dor central como dificuldade de transformar intenção em comportamento organizado ao longo do tempo, evitando o posicionamento genérico de ‘produtividade’.” | DOC-C01-005: “Eu evitaria usar não execução como problema principal. É estreito demais.” e “A distância entre intenção e execução diante de vulnerabilidades cognitivas e demandas reais.” | DOC-C02-039 (BMC, célula Problema): “Apresentar o EXECUTAR cedo demais pode reduzir a credibilidade da investigação e impedir distinguir interesse genuíno pelo problema de interesse no produto.” | K550: alta | L550: preenchido
A551: EV-98299e07d5 | B551: formulario | C551: dia1-2 | D551: 1.1 Problema central | F551: NEGÓCIO & GTM | G551: TRANSVERSAL (detalhado por ECO-01, ECO-03 e ECO-02) | H551: DOC-C01-005 | I551: DOC-C05-001 (seção “Corpo”, linha Problema): “Paralisia por excesso, dificuldade de iniciação das tarefas, não linearidade de execução, troca de contexto cognitivo, retrabalho por não respeitar cadeia única de valor e dependências, memória de trabalho limitada, ausência de processos padronizados e múltiplas fontes de execução e plataformas.” Perspectiva do usuário no mesmo documento: “Perco dinheiro e oportunidades por atrasos e desorganização. […] O momento de maior ansiedade e aflição são os primeiros 30 minutos iniciais, pois não sei onde estava ontem, o que devo fazer agora e como sei que terminei.” | DOC-C07-009 (decisão PROD-03): “Definir a dor central como dificuldade de transformar intenção em comportamento organizado ao longo do tempo, evitando o posicionamento genérico de ‘produtividade’.” | DOC-C01-005: “Eu evitaria usar não execução como problema principal. É estreito demais.” e “A distância entre intenção e execução diante de vulnerabilidades cognitivas e demandas reais.” | DOC-C02-039 (BMC, célula Problema): “Apresentar o EXECUTAR cedo demais pode reduzir a credibilidade da investigação e impedir distinguir interesse genuíno pelo problema de interesse no produto.” | K551: alta | L551: preenchido
A552: EV-e468f3d947 | B552: formulario | C552: dia1-2 | D552: 1.1 Problema central | F552: NEGÓCIO & GTM | G552: TRANSVERSAL (detalhado por ECO-01, ECO-03 e ECO-02) | H552: DOC-C02-039 | I552: DOC-C05-001 (seção “Corpo”, linha Problema): “Paralisia por excesso, dificuldade de iniciação das tarefas, não linearidade de execução, troca de contexto cognitivo, retrabalho por não respeitar cadeia única de valor e dependências, memória de trabalho limitada, ausência de processos padronizados e múltiplas fontes de execução e plataformas.” Perspectiva do usuário no mesmo documento: “Perco dinheiro e oportunidades por atrasos e desorganização. […] O momento de maior ansiedade e aflição são os primeiros 30 minutos iniciais, pois não sei onde estava ontem, o que devo fazer agora e como sei que terminei.” | DOC-C07-009 (decisão PROD-03): “Definir a dor central como dificuldade de transformar intenção em comportamento organizado ao longo do tempo, evitando o posicionamento genérico de ‘produtividade’.” | DOC-C01-005: “Eu evitaria usar não execução como problema principal. É estreito demais.” e “A distância entre intenção e execução diante de vulnerabilidades cognitivas e demandas reais.” | DOC-C02-039 (BMC, célula Problema): “Apresentar o EXECUTAR cedo demais pode reduzir a credibilidade da investigação e impedir distinguir interesse genuíno pelo problema de interesse no produto.” | K552: alta | L552: preenchido
A553: EV-7073f874fd | B553: formulario | C553: dia1-2 | D553: 1.1 Problema central | F553: NEGÓCIO & GTM | G553: TRANSVERSAL (detalhado por ECO-01, ECO-03 e ECO-02) | H553: DOC-C07-002 | I553: DOC-C05-001 (seção “Corpo”, linha Problema): “Paralisia por excesso, dificuldade de iniciação das tarefas, não linearidade de execução, troca de contexto cognitivo, retrabalho por não respeitar cadeia única de valor e dependências, memória de trabalho limitada, ausência de processos padronizados e múltiplas fontes de execução e plataformas.” Perspectiva do usuário no mesmo documento: “Perco dinheiro e oportunidades por atrasos e desorganização. […] O momento de maior ansiedade e aflição são os primeiros 30 minutos iniciais, pois não sei onde estava ontem, o que devo fazer agora e como sei que terminei.” | DOC-C07-009 (decisão PROD-03): “Definir a dor central como dificuldade de transformar intenção em comportamento organizado ao longo do tempo, evitando o posicionamento genérico de ‘produtividade’.” | DOC-C01-005: “Eu evitaria usar não execução como problema principal. É estreito demais.” e “A distância entre intenção e execução diante de vulnerabilidades cognitivas e demandas reais.” | DOC-C02-039 (BMC, célula Problema): “Apresentar o EXECUTAR cedo demais pode reduzir a credibilidade da investigação e impedir distinguir interesse genuíno pelo problema de interesse no produto.” | K553: alta | L553: preenchido
A554: EV-7ed21435c5 | B554: formulario | C554: dia1-2 | D554: 1.1 Problema central | F554: NEGÓCIO & GTM | G554: TRANSVERSAL (detalhado por ECO-01, ECO-03 e ECO-02) | H554: DOC-C07-010 | I554: DOC-C05-001 (seção “Corpo”, linha Problema): “Paralisia por excesso, dificuldade de iniciação das tarefas, não linearidade de execução, troca de contexto cognitivo, retrabalho por não respeitar cadeia única de valor e dependências, memória de trabalho limitada, ausência de processos padronizados e múltiplas fontes de execução e plataformas.” Perspectiva do usuário no mesmo documento: “Perco dinheiro e oportunidades por atrasos e desorganização. […] O momento de maior ansiedade e aflição são os primeiros 30 minutos iniciais, pois não sei onde estava ontem, o que devo fazer agora e como sei que terminei.” | DOC-C07-009 (decisão PROD-03): “Definir a dor central como dificuldade de transformar intenção em comportamento organizado ao longo do tempo, evitando o posicionamento genérico de ‘produtividade’.” | DOC-C01-005: “Eu evitaria usar não execução como problema principal. É estreito demais.” e “A distância entre intenção e execução diante de vulnerabilidades cognitivas e demandas reais.” | DOC-C02-039 (BMC, célula Problema): “Apresentar o EXECUTAR cedo demais pode reduzir a credibilidade da investigação e impedir distinguir interesse genuíno pelo problema de interesse no produto.” | K554: alta | L554: preenchido
A555: EV-0d5c4a9300 | B555: formulario | C555: dia1-2 | D555: 1.2 Público-alvo / ICP | F555: NEGÓCIO & GTM | G555: TRANSVERSAL — conflito em ECO-01; ECO-07 e ECO-02 têm públicos próprios | H555: DOC-C05-001 | I555: DOC-C05-001: “Homens, adultos, neurodivergentes, autônomos, na faixa dos 25–35 anos, recém-diagnosticados…” | DOC-C07-009 (ICP-01, status DECIDED_FOR_TEST, confiança MÉDIA-ALTA): “Iniciar testes por profissionais independentes multiprojeto, sem exigir diagnóstico de TDAH”; e “O que não é critério de entrada: Diagnóstico de TDAH. Diagnóstico/autodeclaração deve ser variável opcional posterior, especialmente porque dados de saúde são sensíveis e não são necessários para o core funcional.” | DOC-C05-001 (SSOT Executar Studio, item 02 Público): “Profissionais solo, autônomos e pequenos negócios com trabalho, informação, clientes e projetos dispersos.” | DOC-C02-039 (BMC, Público/validação): “Leitores interessados em funções executivas, neurodivergência, trabalho, projetos e risco.” | K555: alta | L555: conflito
A556: EV-b80822cbbc | B556: formulario | C556: dia1-2 | D556: 1.2 Público-alvo / ICP | F556: NEGÓCIO & GTM | G556: TRANSVERSAL — conflito em ECO-01; ECO-07 e ECO-02 têm públicos próprios | H556: DOC-C07-009 | I556: DOC-C05-001: “Homens, adultos, neurodivergentes, autônomos, na faixa dos 25–35 anos, recém-diagnosticados…” | DOC-C07-009 (ICP-01, status DECIDED_FOR_TEST, confiança MÉDIA-ALTA): “Iniciar testes por profissionais independentes multiprojeto, sem exigir diagnóstico de TDAH”; e “O que não é critério de entrada: Diagnóstico de TDAH. Diagnóstico/autodeclaração deve ser variável opcional posterior, especialmente porque dados de saúde são sensíveis e não são necessários para o core funcional.” | DOC-C05-001 (SSOT Executar Studio, item 02 Público): “Profissionais solo, autônomos e pequenos negócios com trabalho, informação, clientes e projetos dispersos.” | DOC-C02-039 (BMC, Público/validação): “Leitores interessados em funções executivas, neurodivergência, trabalho, projetos e risco.” | K556: alta | L556: conflito
A557: EV-c33a843c3c | B557: formulario | C557: dia1-2 | D557: 1.2 Público-alvo / ICP | F557: NEGÓCIO & GTM | G557: TRANSVERSAL — conflito em ECO-01; ECO-07 e ECO-02 têm públicos próprios | H557: DOC-C02-039 | I557: DOC-C05-001: “Homens, adultos, neurodivergentes, autônomos, na faixa dos 25–35 anos, recém-diagnosticados…” | DOC-C07-009 (ICP-01, status DECIDED_FOR_TEST, confiança MÉDIA-ALTA): “Iniciar testes por profissionais independentes multiprojeto, sem exigir diagnóstico de TDAH”; e “O que não é critério de entrada: Diagnóstico de TDAH. Diagnóstico/autodeclaração deve ser variável opcional posterior, especialmente porque dados de saúde são sensíveis e não são necessários para o core funcional.” | DOC-C05-001 (SSOT Executar Studio, item 02 Público): “Profissionais solo, autônomos e pequenos negócios com trabalho, informação, clientes e projetos dispersos.” | DOC-C02-039 (BMC, Público/validação): “Leitores interessados em funções executivas, neurodivergência, trabalho, projetos e risco.” | K557: alta | L557: conflito
A558: EV-ad60eb62e3 | B558: formulario | C558: dia1-2 | D558: 1.3 Proposta de valor | F558: NEGÓCIO & GTM | G558: TRANSVERSAL — respostas distintas em ECO-01, ECO-07, ECO-02/03, ECO-05 e ECO-04 | H558: DOC-C05-001 | I558: DOC-C05-001 (Benefício e Promessa principal; Mensagem final): “O usuário executa. O sistema sustenta a execução.”; Headline 01: “O app de produtividade feito para você não usar.”; Descrição 01: “Executar é um sistema de gestão de projetos orientado à execução que reduz configuração, organização manual e decisões repetitivas para mostrar o que pode ser feito agora.” | DOC-C07-009 (campo positioning): “Sistema de execução para profissionais multiprojeto que transforma contexto em próxima ação e preserva o estado do trabalho.” | DOC-C09-004: “O aplicativo de produtividade feito para você usar menos. O sistema sustenta a estrutura; o usuário executa.” | DOC-C09-006: “Traga o problema. Em 7 dias, saia com um sistema funcionando.” | DOC-C02-039 (BMC, Proposta de valor): “Transformar Risco Cognitivo em uma categoria editorial e investigável antes de conectá-la ao produto.” | K558: alta | L558: preenchido
A559: EV-61423513c7 | B559: formulario | C559: dia1-2 | D559: 1.3 Proposta de valor | F559: NEGÓCIO & GTM | G559: TRANSVERSAL — respostas distintas em ECO-01, ECO-07, ECO-02/03, ECO-05 e ECO-04 | H559: DOC-C07-009 | I559: DOC-C05-001 (Benefício e Promessa principal; Mensagem final): “O usuário executa. O sistema sustenta a execução.”; Headline 01: “O app de produtividade feito para você não usar.”; Descrição 01: “Executar é um sistema de gestão de projetos orientado à execução que reduz configuração, organização manual e decisões repetitivas para mostrar o que pode ser feito agora.” | DOC-C07-009 (campo positioning): “Sistema de execução para profissionais multiprojeto que transforma contexto em próxima ação e preserva o estado do trabalho.” | DOC-C09-004: “O aplicativo de produtividade feito para você usar menos. O sistema sustenta a estrutura; o usuário executa.” | DOC-C09-006: “Traga o problema. Em 7 dias, saia com um sistema funcionando.” | DOC-C02-039 (BMC, Proposta de valor): “Transformar Risco Cognitivo em uma categoria editorial e investigável antes de conectá-la ao produto.” | K559: alta | L559: preenchido
A560: EV-d2871aa446 | B560: formulario | C560: dia1-2 | D560: 1.3 Proposta de valor | F560: NEGÓCIO & GTM | G560: TRANSVERSAL — respostas distintas em ECO-01, ECO-07, ECO-02/03, ECO-05 e ECO-04 | H560: DOC-C09-004 | I560: DOC-C05-001 (Benefício e Promessa principal; Mensagem final): “O usuário executa. O sistema sustenta a execução.”; Headline 01: “O app de produtividade feito para você não usar.”; Descrição 01: “Executar é um sistema de gestão de projetos orientado à execução que reduz configuração, organização manual e decisões repetitivas para mostrar o que pode ser feito agora.” | DOC-C07-009 (campo positioning): “Sistema de execução para profissionais multiprojeto que transforma contexto em próxima ação e preserva o estado do trabalho.” | DOC-C09-004: “O aplicativo de produtividade feito para você usar menos. O sistema sustenta a estrutura; o usuário executa.” | DOC-C09-006: “Traga o problema. Em 7 dias, saia com um sistema funcionando.” | DOC-C02-039 (BMC, Proposta de valor): “Transformar Risco Cognitivo em uma categoria editorial e investigável antes de conectá-la ao produto.” | K560: alta | L560: preenchido
... A681: EV-68ddd607f3 | B681: formulario | C681: dia1-2 | D681: 2.13 Exploração de problema (pré-PRD) | F681: PRODUTO | G681: TRANSVERSAL — ECO-01 e ECO-03 | H681: DOC-C01-005 | I681: DOC-C07-010 (3P+N): “Progresso — A hipótese central é parcialmente sustentada: há convergência forte para organização, planejamento, gestão temporal, atenção sustentada e conclusão; evidência moderada para memória prospectiva, flexibilidade e metacognição”; “Next 01 Transformar a matriz abaixo em requisitos funcionais e princípios de design verificáveis.” | DOC-C07-002 e DOC-C07-003: 11 linhas GP-01…GP-11 com colunas Função de gestão · Capacidade exigida · Vulnerabilidade associada · Evidência · Impacto operacional · Compensação sistêmica · Decisão de produto/design. | DOC-C07-009 (kpis): “questions_694: 694 · candidate_direct_links: 28 · thematic_links: 484 · no_evidence: 182 · operational_decisions: 22 · strict_verified: 0.” | DOC-C02-031 (item 3, WHITESPACE PROVISÓRIO): “perfil executivo individual → demanda cognitiva da tarefa → evento provável de falha → probabilidade/impacto → controle compensatório → evidência de execução.” | K681: alta | L681: preenchido

Sheet 05_HIPOTESES
A1: hipotese_id | B1: unidade | C1: framework | D1: hipotese | E1: evidencia_atual | F1: documento_ids | G1: confianca | H1: teste_necessario | I1: origem
A2: HY-bc73815278 | B2: ECO-02 | C2: SA-05 | D2: A lacuna competitiva hipotetizada e que concorrentes seriam fortes em sintomas e medicacao e fracos em aplicacao pratica. | E2: QL-0026: 'Concorrentes seriam mais fortes em sintomas e medicacao do que em aplicacao pratica e desempenho'; recomendacao da propria fonte: 'Validar a lacuna por auditoria de conteudo e entrevistas, antes de assumir oceano azul'. | F2: DOC-C07-007 | G2: 0.65 | H2: Fazer auditoria de 20 conteudos concorrentes classificando por Entender/Estruturar/Executar/Evoluir para confirmar ou derrubar a hipotese. | I2: strategic_analysis
A3: HY-1a1c1c7ab8 | B3: ECO-06 | C3: SA-10A | D3: A atratividade do livro autoral e afirmada por whitespace, e o proprio acervo classifica isso como hipotese e nao como achado validado. | E3: MASTER_INDEX RC-016, status HIPOTESE: 'Nao foi encontrado na pesquisa executada um framework consolidado que una TDAH/funcoes executivas + risco endogeno + gestao de projetos + controles compensatorios de execucao... Validar com scoping review sistematica e especialistas.' | F3: DOC-C02-002 | G3: 0.9 | H3: Manter o status de hipotese em toda comunicacao interna e externa ate a scoping review estar concluida. | I3: strategic_analysis
A4: HY-8f65223004 | B4: ECO-01 | D4: 1.7 CAC (custo de aquisição): Não existe CAC observado. Existe apenas guardrail modelado: TARGET-CAC provisório ≤ R$70 (alvo conservador) e alerta/limite de aproximadamente R$95 (cenário-base); e CAC máximo por cenário para manter | E4: DOC-C07-009 (bloco “CAC guardrail”): “≤ R$70 alvo conservador; ≈ R$95 alerta / cenário-base. CAC observado = gasto atribuível / novos clientes pagantes. CPI, CPM, clique e cadastro não substituem CAC.” | Achado CAC-HYP-01 (epistemic_class E, status MODEL_GUARDRAIL): “Guardrail econômico; CAC observado só existe após campanha e aquisição pagante.” | Gap registrado: {gap: CAC, status: “MODELO + GUARDRAIL”, closed: false, remaining: “Campanhas e clientes pagantes.”} | F4: DOC-C07-009 | G4: media | H4: Não preencher com número. Instrumentar acquisition_source/campaign_id/paid_at antes da primeira campanha paga e só então calcular CAC observado. | I4: formulario
A5: HY-a97b042d7b | B5: ECO-01 | D5: 1.8 LTV (valor do tempo de vida): Não existe LTV observado. Existe apenas LTV modelado sob premissas declaradas como classe E: ARPU mensal de R$49,90 e margem bruta assumida de 85%; cenário otimista com churn mensal de 10% → LTV R$424 | E5: DOC-C07-009 (unit_economics, status MODEL_HYPOTHESIS_NOT_OBSERVED): “arpu_monthly_brl: 49.9; gross_margin_assumption: 0.85; scenarios: optimistic churn 0.10 → ltv 424; base churn 0.15 → ltv 282.77; conservative churn 0.20 → ltv 212.” | Achado LTV-HYP-01: “LTV_MODEL_BASE ≈ R$282,77 sob ARPU R$49,90, margem bruta 85% e churn mensal 15%. […] Não persistir como LTV factual.” | Gap registrado: {gap: LTV, status: “MODELO HIPOTÉTICO”, closed: false, remaining: “Retenção, churn e margem reais.”} | F5: DOC-C07-009 | G5: media | H5: Não preencher com número. Rodar as coortes LTV_30/60/90 após o primeiro piloto pagante e substituir o modelo. | I5: formulario
A6: HY-0faf54c756 | B6: ECO-01 (com persona própria em ECO-07) | D6: 2.7 Persona principal: Não há artefato de persona (nome, cenário, objetivos, frustrações) em nenhum documento. O que existe são duas descrições de ICP em conflito — as mesmas do campo 1.2 — acrescidas de perspectivas em pri | E6: DOC-C05-001 (Corpo, linha Público): texto integral da versão A, com a perspectiva do usuário “Quero começar o dia, semana, mês de trabalho executando as tarefas sem, ao mesmo tempo, me preocupar com a ordem e controle da progressão.” | DOC-C07-009 (ICP comercial a testar): texto integral da versão B, com “Decisão ICP-01: testar comportamento e problema primeiro; diagnóstico não define o ICP comercial inicial.” | DOC-C12-003: dez perguntas do formulário de entrada do Estúdio, que operacionalizam o perfil (como trabalha hoje, principal atrito, ferramentas atuais, dificuldade de retomada, relação com papel/físico). | F6: DOC-C05-001;DOC-C07-009;DOC-C12-003 | G6: media | H6: Resolver o conflito de ICP e escrever uma persona única derivada da versão vencedora; ICP-01 já prevê “recrutar ICP comportamental e medir ativação, recorrência, pagamento e retenção”. | I6: formulario
A7: HY-5a7dbdfa59 | B7: ECO-01 (com recorrência contratual própria em ECO-07) | D7: 2.10 Jornada — Uso recorrente: O uso recorrente é desenhado como uso deliberadamente baixo — e isso é assumido como hipótese, não como fato. Promessa: “uso mínimo do app — cerca de 1–2 vezes por semana”; princípio: “o usuário não e | E7: DOC-C05-001 (Promessa principal): “Zero configuração, mínimo de personalização, uso mínimo do app — cerca de 1–2 vezes por semana — e externalização cognitiva”; (Diferencial 03): “a superioridade específica do analógico e a frequência ideal de ‘1–2 vezes por semana’ permanecem hipóteses de produto/design, não resultados empiricamente demonstrados nos documentos.” | DOC-C11-006 (Cena A): “/bomdia → reconstruir estado → mostrar trabalho atual.” | DOC-C07-009 (telemetry): “cohorts: W1, W2, W4, W8”; “execution_cycles_per_week”. | DOC-C11-008 (Mensagem): “O sistema pode sustentar o trabalho sem exigir permanência contínua na tela.” | F7: DOC-C05-001;DOC-C07-009;DOC-C11-006;DOC-C11-008 | G7: media | H7: Medir a frequência real de uso no piloto para confirmar ou falsear a hipótese de 1–2 vezes por semana, que hoje sustenta a promessa central do produto. | I7: formulario

Sheet 06_RISCOS
A1: risco_id | B1: unidade | C1: framework | D1: evento | E1: causa_evidencia | F1: documento_ids | G1: impacto | H1: urgencia | I1: controle | J1: status_evidencia
A2: RI-4196aa2cf4 | B2: ECO-01 | C2: SA-01 | D2: Posicionar o app como diagnostico ou tratamento de TDAH pode acionar o regime de Software como Dispositivo Medico da Anvisa. | E2: Fonte SRC-RG8-ANVISA-SAMD no dashboard: 'RDC 657/2022 - Software como Dispositivo Medico... Enquadramento SaMD depende da indicacao e funcao; software que diagnostica/trata pode entrar no regime regulatorio.' | F2: DOC-C07-009 | G2: high | H2: high | I2: Manter POSITION-01 e CLAIM-01 como travas de copy e submeter o texto final de lancamento a revisao juridica antes de 07/09. | J2: fact
A3: RI-f75dcb68ce | B3: ECO-01 | C3: SA-01 | D3: Coletar diagnostico de TDAH no onboarding transformaria a base em dado pessoal sensivel sob a LGPD, sem necessidade funcional. | E3: Fonte SRC-RG8-ANPD-LGPD: 'Dado referente a saude e dado pessoal sensivel; minimizacao favorece nao coletar diagnostico quando desnecessario.' Decisao ICP-01: 'diagnostico nao define o ICP comercial inicial'. | F3: DOC-C07-009 | G3: high | H3: medium | I3: Manter diagnostico como variavel opcional pos-ativacao, com base legal e finalidade declaradas, nunca como criterio de entrada. | J3: fact
A4: RI-569869652a | B4: ECO-02 | C4: SA-01 | D4: A politica de claims proibe hoje seis formulacoes clinicas no conteudo editorial e comercial. | E4: claims_policy.prohibited_now: 'Reduz sintomas de TDAH', 'Melhora funcao executiva clinicamente', 'Trata TDAH', 'Diagnostica ou identifica TDAH', 'Substitui terapia, tratamento ou medicacao', 'Cientificamente comprovado para TDAH'. | F4: DOC-C07-009 | G4: high | H4: high | I4: Transformar a lista em checklist de QA editorial obrigatorio antes de publicar cada peca (PECA-001/002/003). | J4: fact
A5: RI-5b044fb03c | B5: ECO-03 | C5: SA-01 | D5: A APM publicou em 26/08/2026 a formulacao de que projetos tambem podem falhar cognitivamente, criando adjacencia temporal muito proxima a tese. | E5: DOC-C02-042 (Alerta): 'Sarah Gardner... publicou na APM em 26/08/2026 a formulacao de que projetos tambem podem falhar cognitivamente, embora seu foco seja IA, julgamento e governanca'; RC-TERM-009 marca STATUS SINAL_RECENTE. | F5: DOC-C02-042;DOC-C02-030;DOC-C02-022 | G5: high | H5: high | I5: Acelerar o registro publico da formulacao propria (artigo fundador datado + white paper) para preservar anterioridade documentada. | J5: fact
A6: RI-cd8ffd01f1 | B6: ECO-01 | C6: SA-02 | D6: Os concorrentes diretos citados sao ferramentas horizontais de produtividade com limitacoes documentadas para o publico-alvo. | E6: QL-000053: 'Trello... necessitando de plug-ins adicionais para rastrear progresso'; QL-000054: 'Todoist... limitado para iniciar tarefas e sem recursos de regulacao emocional'; QT-000172: '30,0% dos usuarios com TDAH consideram o Notion dificil de configurar/usar'. | F6: DOC-C07-007;DOC-C07-009 | G6: high | H6: high | I6: Ancorar o posicionamento na lacuna de iniciacao e retomada, nao em paridade de features com Notion/Trello/Todoist. | J6: fact
A7: RI-06a9442012 | B7: ECO-01 | C7: SA-02 | D7: Existem concorrentes com evidencia clinica ou aprovacao regulatoria que o EXECUTAR nao pode igualar hoje. | E7: QT-000177: 'Eficacia de app baseado em TCC (estudo aberto do app Inflow)'; QT-000178/179: 'videogame terapeutico aprovado por agencia regulatoria... p<0.0001... 72,5% melhoria na qualidade de vida (STARS-ADHD-Adult)'. | F7: DOC-C07-007;DOC-C07-009 | G7: high | H7: high | I7: Competir por eficacia funcional (time-to-next-action, resume latency), terreno onde nao ha comparador regulado, e nao por desfecho clinico. | J7: fact
A8: RI-44e652eb15 | B8: ECO-03 | C8: SA-02 | D8: O framework compete com corpos metodologicos ja consolidados, e a fonte reconhece isso. | E8: RC-TERM-007/008 classificam 'Cognitive Risk' e 'Managing Cognitive Risk' como ANTERIORIDADE; RC-012: 'PMI estrutura multiplos dominios'; RC-TERM-011/012/013 marcam ergonomia cognitiva, fatores humanos e neuroergonomia como adjacentes fortes. | F8: DOC-C02-030;DOC-C02-022;DOC-C02-031 | G8: high | H8: high | I8: Manter o guardrail de nao reivindicar o termo e posicionar a contribuicao como integracao especifica, conforme RC-030. | J8: fact
A9: RI-3ebf9d6364 | B9: ECO-01 | C9: SA-03A | D9: A categoria declarada do produto e sistema de gestao de processos, projetos, tarefas e workflows orientado a execucao. | E9: DOC-C05-001, item 03 do index: 'Sistema de gestao de processos, projetos, tarefas e workflows, orientado a execucao, adaptado as vulnerabilidades do usuario, com uso digital minimo e integracao analogica'. | F9: DOC-C05-001 | G9: high | H9: medium | I9: Usar essa definicao como texto canonico da pagina inicial em vez de 'app de produtividade'. | J9: fact
A10: RI-a9310b8e2d | B10: ECO-03 | C10: SA-03A | D10: A tese explora a fronteira entre tres mercados de conteudo hoje separados. | E10: DOC-C01-005: 'Ha tres mercados de conteudo que normalmente ficam separados... neurodivergencia... produtividade pessoal... gestao de riscos'; a proposta e 'colocar uma ponte no meio'. | F10: DOC-C01-005;DOC-C03-002 | G10: high | H10: medium | I10: Descrever o territorio como interseccao, o que tambem explica por que nao ha benchmark direto de tamanho de mercado. | J10: fact
A11: RI-b7801ff903 | B11: ECO-01 | C11: SA-03B | D11: O material interno afirma TAM estimado de R$ 5,07 bilhoes (Brasil), sem metodologia recuperavel. | E11: QT-0131: 'TAM estimado 5070000000.0 R$', geografia Brasil, fonte 'Documento Final Unificado: Sintese Estrategica de Neuroexecucao Aplicada', arquivo IMG_0537.HEIC, 'base amostral: Nao informada na imagem', 'Requer validacao na referencia original'. | F11: DOC-C07-007;DOC-C07-009 | G11: high | H11: high | I11: Tratar como numero herdado nao auditavel; nao usar em deck, investidor ou copy ate existir memoria de calculo. | J11: fact
A12: RI-54c52eff6f | B12: ECO-01 | C12: SA-03B | D12: Nao ha base nem metodologia identificavel para produzir um TAM defensavel do EXECUTAR neste acervo. | E12: Falta: universo de compradores definido, taxa de adocao, preco medio validado e fonte bibliografica ([1]-[8] ausente). O proprio dashboard adverte que 26,1 mi de trabalhadores por conta propria 'Nao equivale a TAM do EXECUTAR'. | F12: DOC-C07-009;DOC-C07-007 | G12: high | H12: high | I12: Para fechar: fixar universo (ex.: conta propria com uso de ferramenta digital), taxa de adocao observada e ARPU validado por PRICE-01; so entao calcular. | J12: gap
... A200: RI-9ac473723e | B200: ECO-08 | C200: SA-08B | D200: O relacionamento com a audiencia esta definido por acoes de baixo compromisso antes de qualquer oferta. | E200: BMC, Relacao com audiencia: 'Ler, explorar, assinar e baixar o Mapa de Risco Cognitivo; medir interesse antes de introduzir o EXECUTAR'; texto 2.txt: 'com CTA para ler, explorar, assinar ou baixar - nao para comprar/conhecer o EXECUTAR'. | F200: DOC-C02-039;DOC-C02-042 | G200: high | H200: medium | I200: Manter a campanha de categoria sem CTA de compra e medir assinatura e download como conversao primaria. | J200: fact

Sheet 07_DECISOES
A1: decisao_id | B1: contexto | C1: decisao | D1: alternativas | E1: justificativa | F1: data | G1: impacto | H1: origem
A2: DEC-ff1bcb4e65 | B2: §03-T1 marca 9.4 como TBD, mas §05 do mesmo bloco enumera cinco dependências estratégicas materiais. | C2: em aberto | E2: Formalizar o grafo em vez de tratar como ausência de dado. | F2: 2026-08-31 | G2: 9.4 | H2: maestro
A3: DEC-84b2314af2 | B3: §03-T1 marca 10.1 como TBD, mas §05-Cronograma traz oito marcos datados entre 07/09/2026 e 10/01/2027. | C3: em aberto | E3: Eleger o marco #1 — candidato: Gate de Revisão de 24/10/2026. | F3: 2026-08-31 | G3: 10.1 | H3: maestro
A4: DEC-cdcde76419 | B4: O valor real é "Ciclo Zero", que não consta das opções previstas no formulário original (Editorial / Desenvolvimento / Governança). | C4: em aberto | E4: Ampliar o domínio de valores do campo. | F4: 2026-08-31 | G4: 10.2 | H4: maestro
A5: DEC-bb32e9e562 | B5: OUT-33 exige 34 IDs do XLS Entrypoint; o formulário fundido tem 122 campos. | C5: Decisão operacional do Maestro, na ausência de instrução contrária: preencher os 122 campos do formulário fundido, que é superconjunto dos 34 IDs exigidos por OUT-33 (1.1–1.12, 8.1–8.5, 9.1–9.4, 10.1–10.4, 12.1–12.3, 14.1–14.3, 16.1–16.3). Assim nenhum ID obrigatório de OUT-33 fica de fora (OUT-69) e o excedente permanece rastreável. Reversível se o owner pedir escopo estrito. | E5: Decisão do owner sobre o escopo de preenchimento. | F5: 2026-08-31 | G5: escopo INS-01 | H5: maestro
A6: DEC-760d30c732 | B6: O cronograma de envio (dias 1–6, 31/08 a 05/09/2026) coexiste com o roadmap do projeto (07/09/2026 a 10/01/2027). São eixos distintos: preenchimento documental vs. execução do ecossistema. | C6: em aberto | E6: Nenhuma — registrado para evitar leitura equivocada de conflito de datas. | F6: 2026-08-31 | G6: calendário | H6: maestro
A7: DEC-4270e3477c | B7: Ha duas posicoes incompativeis sobre dimensionamento de mercado dentro do mesmo acervo. | C7: NAO ARBITRADO — conflito preservado | D7: Versao A (QT-0131/132/133): TAM R$5,07 bi, SAM R$357,3 mi, SOM R$3,26 mi em 3 anos. Versao B (dashboard V3 Final): 'Contexto de mercado. Nao equivale a TAM do EXECUTAR' e 'Strict VERIFIED 0'. | E7: Registrar formalmente que a V3 supera a estimativa herdada e marcar QT-0131/132/133 como legado nao verificado no proprio warehouse. | F7: 2026-08-31 | G7: ECO-01/SA-03B | H7: strategic_analysis
A8: DEC-445c3d3510 | B8: A meta herdada de 500.000 inscritos contradiz a regra vigente de nao fixar metas sem baseline. | C8: NAO ARBITRADO — conflito preservado | D8: QT-0135: 'Meta de inscritos 500000.0'. DOC-C02-043 (Objetivo SMART): 'Nao estabelecer ainda metas arbitrarias de seguidores ou leads sem baseline.' | E8: Aposentar a meta de 500 mil ate a campanha D1-D14 gerar baseline de visualizacoes, retencao, inscricoes e downloads. | F8: 2026-08-31 | G8: ECO-02/SA-03D | H8: strategic_analysis
A9: DEC-771e78fe33 | B9: Ha tensao entre a segmentacao clinica do editorial e a segmentacao comportamental do produto. | C9: NAO ARBITRADO — conflito preservado | D9: Editorial (QL-0018): publico e 'adultos com TDAH'. Produto (ICP-01): 'diagnostico nao define o ICP comercial inicial'. As duas convivem no mesmo funil de lancamento de 07/09. | E9: Decidir e registrar como o trafego editorial (TDAH) converte para uma oferta que nao usa TDAH como criterio, evitando promessa implicita de tratamento. | F9: 2026-08-31 | G9: ECO-01/SA-04A | H9: strategic_analysis
A10: DEC-e8aac19797 | B10: Ha conflito registrado sobre a alocacao da receita de AdSense ao braco social. | C10: NAO ARBITRADO — conflito preservado | D10: QT-0152: 'Alocacao de AdSense inicialmente cogitada 70,0% da receita'; QT-0153: 'Alocacao inicial recomendada 10,0%'; QL-0016: '70% ... e considerada incompativel com reinvestimento e consistencia operacional'. | E10: Registrar formalmente a decisao (10%) e o motivo, para que a versao de 70% nao volte por copia de material antigo. | F10: 2026-08-31 | G10: ECO-02/SA-06A | H10: strategic_analysis
A11: DEC-4f498c61b9 | B11: Ha duas arquiteturas editoriais concorrentes no acervo, com categorias diferentes. | C11: NAO ARBITRADO — conflito preservado | D11: Versao A (DOC-C02-043/DOC-C01-005): territorio 'Risco Cognitivo', mais amplo que TDAH. Versao B (DOC-C10-003): 'Arquitetura editorial unica - Categoria: TDAH adulto aplicado ao trabalho, a gestao e a execucao', com tres pilares e 4E. | E11: Decidir se sao duas publicacoes (Risco Cognitivo e Biblioteca EXECUTAR) ou uma; hoje o lancamento de 07/09 usa a Versao B e o pacote Risco Cognitivo usa a Versao A. | F11: 2026-08-31 | G11: ECO-02/SA-11A | H11: strategic_analysis
A12: DEC-b1f7cf8210 | B12: Ha conflito direto entre a sequencia editorial (produto por ultimo) e o GTM de 07/09 (produto e ofertas no dia um). | C12: NAO ARBITRADO — conflito preservado | D12: DOC-C02-042/043: 'CTA inicial: ler, explorar, assinar e baixar... o EXECUTAR fica para uma campanha posterior'. DOC-C06-001/DOC-C08-011: lancamento em 07/09 com CTA-001 App, CTA-004 E-book, CTA-005 Curso, CTA-006 Studio, CTA-009 Office Kit e commerce em Hotmart configurado em D3. | E12: Resolver explicitamente: ou sao dois lancamentos com marcas separadas (Risco Cognitivo editorial e EXECUTAR comercial), ou a sequencia de categoria foi abandonada e isso precisa ser registrado como decisao. | F12: 2026-08-31 | G12: ECO-01/SA-11B | H12: strategic_analysis
A13: DEC-b39dde0534 | B13: Ha conflito entre a demonstracao planejada com QR e a decisao tecnica que substituiu QR por reconhecimento de forma. | C13: NAO ARBITRADO — conflito preservado | D13: DOC-C11-008 (Cena B): 'Usar QR/atalho para sair do objeto fisico e abrir o contexto correto'. DOC-C04-002: 'PR #75 substituiu QR impresso pelos 5 simbolos administrativos reconhecidos diretamente por forma na imagem da camera'. | E13: Atualizar o roteiro da Demonstracao 03 antes da gravacao de 02/09; gravar QR mostraria funcionalidade que nao existe mais. | F13: 2026-08-31 | G13: ECO-01/SA-12 | H13: strategic_analysis
A14: DEC-ce0bea302c | B14: Ha conflito sobre a extensao do artigo fundador entre dois documentos do mesmo pacote. | C14: NAO ARBITRADO — conflito preservado | D14: DOC-C01-004 (Execute): 'Escreva primeiro aproximadamente 2.500-3.500 palavras'. DOC-C02-043 e DOC-C02-042: 'Meta atual: 1.200-1.800 palavras e 14-18 paragrafos; a proposta anterior de cerca de 3.000 palavras foi descartada' e RC-040 registra a revisao. | E14: Marcar DOC-C01-004 como versao superada nesse ponto especifico; sem isso o redator pode escrever o dobro do necessario. | F14: 2026-08-31 | G14: ECO-02/SA-13 | H14: strategic_analysis
A15: DEC-1b30c7c11b | B15: Nao existe SAM para a linha fisica; o SAM do acervo (R$ 357,3 mi) e do projeto agregado, alem de conflitar com um segundo valor de SAM (R$ 6,0 mi) no mesmo dashboard. | C15: NAO ARBITRADO — conflito preservado | D15: Dashboard QT-0132: 'SAM estimado', grupo_segmento 'Projeto Neuroexecucao Aplicada', valor_pontual 357300000.0, base_amostral 'Nao informada na imagem'; ha ainda um registro com indicador 'SAM' e valor_pontual 6000000.0 no mesmo conjunto. | E15: Nao usar nenhum dos dois SAM antes de identificar de qual imagem cada um veio e qual base amostral sustenta cada valor. | F15: 2026-08-31 | G15: ECO-04/SA-03C | H15: strategic_analysis
A16: DEC-9b9b00e7e1 | B16: A unica segmentacao explicita da linha fisica e de genero, e vem de uma peca visual, nao de documento de oferta. | C16: NAO ARBITRADO — conflito preservado | D16: Referencia visual de organizacao fisica: mockup 'executar.com/kit-semanal-masculino' com titulo 'Kit Semanal Masculino', 'Organizar - Usar - Lavar' e sacos SEG a DOM; DOC-C09-008 descreve o item apenas como 'Kit de organizacao fisica | rotina por dias'. | E16: Decidir se o kit de organizacao e neutro (rotina por dias) ou segmentado por genero; hoje a peca e o documento divergem. | F16: 2026-08-31 | G16: ECO-04/SA-04A | H16: strategic_analysis
A17: DEC-9277db2e69 | B17: O destino declarado dos livros digitais e a pagina Biblioteca, cujo objetivo esta descrito como aprofundamento e nao como venda. | C17: NAO ARBITRADO — conflito preservado | D17: DOC-C12-009, Biblioteca: 'Objetivo: organizar conteudo e aprofundamento. Chamada principal: CH-003 / CH-007'; o registro de chamadas define CH-003 'Explorar a biblioteca' e CH-007 'Ver o livro - ligacao de afiliado'; a chamada de livro digital e CH-004, que aponta para a Loja. | E17: Decidir se o livro digital e vendido na Loja (CH-004) ou exposto na Biblioteca (CH-003); hoje a Biblioteca leva a afiliado e nao a produto proprio. | F17: 2026-08-31 | G17: ECO-06/SA-11A | H17: strategic_analysis
A18: DEC-c334794e67 | B18: A fronteira ECO-06 esta contida dentro de ECO-05 na propria arvore de pastas e na nota de visao: livros digitais sao um filho de Infoprodutos. | C18: NAO ARBITRADO — conflito preservado | D18: ARVORE-DE-PASTAS.txt: '01-OFERTAS/ ... 04-INFOPRODUTOS/ 01-LIVROS-DIGITAIS/ 02-CURSO/ 03-HOTMART/'; DOC-C09-016 lista sob 'Mergulhe aqui': 'Livros digitais | Curso | Hotmart'; DOC-C09-009 lista as pastas 'Livros Digitais, Curso, Hotmart' como subpastas de Infoprodutos. | E18: Nao arbitrar em silencio: ou ECO-06 e redefinida como sub-linha de ECO-05, ou o acervo precisa separar fisicamente o livro autoral dos e-books comerciais. | F18: 2026-08-31 | G18: ECO-06/SA-03A | H18: strategic_analysis
... A31: DEC-781750bd1c | B31: Existem dois planos de 14 dias sobre a mesma capacidade de 6h/dia, um do lancamento Executar e um da campanha Risco Cognitivo. | C31: NAO ARBITRADO — conflito preservado | D31: DOC-C08-011 lista a fila unica de 14 dias 25/08 a 07/09 do lancamento Executar. O BMC do Risco Cognitivo (data 2026-08-28) descreve '14 dias, campanha, 18 ativos' com D1-D14 proprios. Nenhum documento reconcilia os dois calendarios. | E31: Sequenciar as duas campanhas; 18 ativos editoriais somados a 3 pecas e 3 showrooms nao cabem em 72h. | F31: 2026-08-31 | G31: ECO-08/SA-13 | H31: strategic_analysis

Sheet 08_FONTES
A1: documento_id | B1: classificacao_id | C1: nome_arquivo | D1: caminho_relativo | E1: sha256 | F1: tipo_documental | G1: vezes_citado | H1: evidencia_ids
A2: DOC-C01-004 | B2: C01 | C2: 02 - Estratégia Editorial e Artigo Fundador.md | D2: RISCO-CONITIVO/Risco_Cognitivo_Hub_Editorial_v1.3/01_DOCUMENTOS/02 - Estratégia Editorial e Artigo Fundador.md | E2: 2839090886402d61ecd2e4e36af0b0784d6c7007608c5f433bdf58c9e9adf83f | F2: Estratégia e arquitetura | G2: 1 | H2: EV-51a2a417ea
A3: DOC-C01-005 | B3: C01 | C3: 03 - Framework de Risco Cognitivo e Prior Art.md | D3: RISCO-CONITIVO/Risco_Cognitivo_Hub_Editorial_v1.3/01_DOCUMENTOS/03 - Framework de Risco Cognitivo e Prior Art.md | E3: 50209f47aeed6f91f58cbf624f2e0f863a39a943225929764f95f10d50711b7d | F3: Evidência e pesquisa | G3: 12 | H3: EV-976e759c3b;EV-6c03b1000c;EV-7b1eaab9ad;EV-7cf257a1f6;EV-da200e8c27;EV-227def7ce5;EV-5878d10342;EV-b5b513261b;EV-c06ba61b34;EV-98299e07d5;EV-597a8c63f1;EV-68ddd607f3
A4: DOC-C01-006 | B4: C01 | C4: 04 - Marca Editorial Risco Cognitivo.md | D4: RISCO-CONITIVO/Risco_Cognitivo_Hub_Editorial_v1.3/01_DOCUMENTOS/04 - Marca Editorial Risco Cognitivo.md | E4: 1598e12ccbb5b2884a24222193f02a0e25830ef555c78433c671f8d700491fbd | F4: Estratégia e arquitetura | G4: 2 | H4: EV-864c677b05;EV-4ceeec2e1a
A5: DOC-C02-002 | B5: C02 | C5: RISCO_COGNITIVO_MASTER_INDEX.csv | D5: RISCO-CONITIVO/RISCO-COGNITIVO Fundacap /RISCO_COGNITIVO_MASTER_INDEX.csv | E5: 5a4188f163e402aa8f88247805e540cf071131c4952208e8df6cdd17da6251cd | F5: Índice e inventário | G5: 7 | H5: EV-adabf06d4a;EV-1758438480;EV-998da9b9e4;EV-61f6b6946a;EV-dec324d198;EV-f901aa075d;EV-7b3a744c1d
A6: DOC-C02-004 | B6: C02 | C6: EXECUTAR_ENTREGAVEIS_GATES_POR_AREA.csv | D6: RISCO-CONITIVO/RISCO-COGNITIVO Fundacap /Riscognitivo/EXECUTAR_ENTREGAVEIS_GATES_POR_AREA.csv | E6: 1345a5507c9cba88ecf8351d97d507b8c03f6f0a23cc232a085aa8dcbaa51938 | F6: Base de dados e planilha | G6: 4 | H6: EV-d95ff2504e;EV-2a687a7d33;EV-8fdf4e01d3;EV-bf62c50f8f
A7: DOC-C02-014 | B7: C02 | C7: RC-P01_PROJECT_BRIEF.txt | D7: RISCO-CONITIVO/RISCO-COGNITIVO Fundacap /Riscognitivo/RISCO_COGNITIVO_OS_PARA/01_PROJECTS/P01_LANCAMENTO_BLOG/RC-P01_PROJECT_BRIEF.txt | E7: 5d477181107e177208fc73d0bdf3bec07877b9d06412fe0adbab803545982c65 | F7: Handoff e brief | G7: 7 | H7: EV-3718a6adf1;EV-9fff03638b;EV-9661c13eee;EV-36ecd5dd68;EV-e3e96d8028;EV-c42e2133bb;EV-298ca3739a
A8: DOC-C02-015 | B8: C02 | C8: RC-P02-VAL01_VALIDACAO.txt | D8: RISCO-CONITIVO/RISCO-COGNITIVO Fundacap /Riscognitivo/RISCO_COGNITIVO_OS_PARA/01_PROJECTS/P02_FRAMEWORK_CERM/RC-P02-VAL01_VALIDACAO.txt | E8: 38f18771e7490d79913b090df4beade883ed8d1f9986e157cda63d3ba356e6ce | F8: Medição e validação | G8: 4 | H8: EV-69f96afd6b;EV-37a2ed6d65;EV-fe1951bcbe;EV-b6cc37aa22
A9: DOC-C02-016 | B9: C02 | C9: RC-P02_FRAMEWORK_V0_1.txt | D9: RISCO-CONITIVO/RISCO-COGNITIVO Fundacap /Riscognitivo/RISCO_COGNITIVO_OS_PARA/01_PROJECTS/P02_FRAMEWORK_CERM/RC-P02_FRAMEWORK_V0_1.txt | E9: c02413e286e9332bffdf481938dab4fd8a92305e5047478fa44182f310cc3939 | F9: Estratégia e arquitetura | G9: 7 | H9: EV-f5dfa2ab27;EV-e3e3b74404;EV-2381b25f07;EV-76ef63fa93;EV-0559824216;EV-d41cb56318;EV-e862e36094
A10: DOC-C02-017 | B10: C02 | C10: RC-P03_SITE_CMS_BRIEF.txt | D10: RISCO-CONITIVO/RISCO-COGNITIVO Fundacap /Riscognitivo/RISCO_COGNITIVO_OS_PARA/01_PROJECTS/P03_SITE_CMS/RC-P03_SITE_CMS_BRIEF.txt | E10: a9d6e4108a6b6a085c19c3ea2a002a7518964bf8aee20953e88529868acb72c2 | F10: Handoff e brief | G10: 6 | H10: EV-ebf7dd1990;EV-f77a1b9d17;EV-51cc07f648;EV-5612312d73;EV-b655fc9f07;EV-3a92ed7b27
A11: DOC-C02-021 | B11: C02 | C11: RC-R01_EVIDENCIAS_TDAH.txt | D11: RISCO-CONITIVO/RISCO-COGNITIVO Fundacap /Riscognitivo/RISCO_COGNITIVO_OS_PARA/03_RESOURCES/R01_TDAH_FUNCOES_EXECUTIVAS/RC-R01_EVIDENCIAS_TDAH.txt | E11: 3300f8903921e64dffa968cbf1d712d0386bd7685eb907c40e6ef3b2cf7ea877 | F11: Evidência e pesquisa | G11: 4 | H11: EV-161a0a642b;EV-c571b97b66;EV-8a3c42b08b;EV-0b17a4aaa5
A12: DOC-C02-022 | B12: C02 | C12: RC-R02_EVIDENCIAS_RISCO_PM.txt | D12: RISCO-CONITIVO/RISCO-COGNITIVO Fundacap /Riscognitivo/RISCO_COGNITIVO_OS_PARA/03_RESOURCES/R02_RISCO_GESTAO_PROJETOS/RC-R02_EVIDENCIAS_RISCO_PM.txt | E12: d2808db7f8bb1e7c1cbdc5fd4e30bca8201bf26f841fbfca2a803990da971967 | F12: Evidência e pesquisa | G12: 4 | H12: EV-027ebf9edf;EV-43055a96a9;EV-692e07a753;EV-cd777b07aa
... A87: DOC-C18-003 | B87: C18 | C87: ARVORE-DE-PASTAS.txt | D87: PLANO EDITORIAL-PRODUTOS-SERVICOS/ARVORE-DE-PASTAS.txt | E87: f84ef20ffd91746b2817fd57dadae6328bdc27fdbe5a0e9fbb82b3db7c031939 | F87: Índice e inventário | G87: 1 | H87: EV-0edc4e635a

Sheet 09_BACKLOG
A1: lacuna_id | B1: origem | C1: unidade | D1: alvo | E1: descricao | F1: pesquisa_necessaria | G1: prioridade
A2: GA-5ef3eb6171 | B2: strategic_analysis | C2: ECO-01 | D2: SA-01/environmental | E2: Nao ha analise PESTEL formal por unidade no acervo; os fatores existem dispersos em fontes de evidencia e decisao. | F2: Consolidar um PESTEL de uma pagina por unidade a partir das fontes ja catalogadas, sem pesquisa nova. | G2: low
A3: GA-c49ee82e38 | B3: strategic_analysis | C3: ECO-01 | D3: SA-02/new_entrants | E3: Nao ha no acervo qualquer analise de barreiras a entrada para a categoria do app. | F3: Definir explicitamente qual e o ativo defensavel (base de evidencias governada, motor de rota ou dados de execucao) antes do lancamento comercial. | G3: low
A4: GA-f64ebedfd8 | B4: strategic_analysis | C4: ECO-07 | D4: SA-02/rivalry | E4: Nao ha mapeamento de concorrentes para o Estudio no acervo lido. | F4: Levantar 5 comparaveis de consultoria de automacao no Brasil antes de fixar o preco de R$700 como diferencial. | G4: medium
A5: GA-ac6a83fa9f | B5: strategic_analysis | C5: ECO-01 | D5: SA-03B/tam_methodology | E5: Nao ha base nem metodologia identificavel para produzir um TAM defensavel do EXECUTAR neste acervo. | F5: Para fechar: fixar universo (ex.: conta propria com uso de ferramenta digital), taxa de adocao observada e ARPU validado por PRICE-01; so entao calcular. | G5: high
A6: GA-7e26ede5c3 | B6: strategic_analysis | C6: ECO-02 | D6: SA-03B/tam | E6: Nao existe dimensionamento de mercado especifico para a unidade editorial. | F6: Se o blog for monetizar, dimensionar por RPM x sessoes projetadas apos a campanha inaugural, nao antes. | G6: low
A7: GA-2d1937278e | B7: strategic_analysis | C7: ECO-07 | D7: SA-03B/tam | E7: Nao existe TAM/SAM/SOM para os servicos; ha apenas preco e capacidade. | F7: Para servico com capacidade travada em 1 cliente/semana, o dimensionamento relevante e fila de demanda qualificada, nao TAM. | G7: medium
A8: GA-905f4f84be | B8: strategic_analysis | C8: ECO-07 | D8: SA-04A/segment_definition | E8: Nao ha definicao de segmento para os servicos alem de tres familias nao especificadas no acervo lido. | F8: Recuperar ou redigir a especificacao das tres familias de servico antes de publicar PAG-002-SERVICOS. | G8: high
